Workbook

Sheet AÑO 2026
A1: INCLUIDO | B1: HIPOTECA 1 | C1: 800 | G1: SANTANDER | H1: KUTXA | I1: N26 | L1: INDEXA | M1: FONDO JBN | N1: FONDO YUG | O1: TOTAL INVERTIDO | R1: GRAN TOTAL | T1: OBJETIVO | U1: CUOTAS | V1: HACIENDA | X1: AHORRADO | Y1: RESTO HIPOTECA | Z1: 66500 | AA1: OBJETIVO | AB1: CUOTAS | AC1: AHORRADO | AD1: RESTO LOCAL | AE1: 29500
B2: HIPOTECA 2 | C2: 500 | F2: 46023 | G2: 6070.02 | H2: 3232.92 | I2: 15.314 | J2: =G2+H2+I2 -> 9318.254 | L2: 0 | M2: 1705.37 | N2: 1905.37 | O2: =SUM(L2:N2) -> 3610.74 | R2: =I2+O2 -> 3626.054 | S2: 1 | T2: AÑO 2025 | U2: 7000 | W2: 15400 | Y2: =Z1-U2-V2-W2-X2 -> 44100 | AA2: AÑO 2025 | AB2: 6000 | AD2: =AE1-AB2-AC2 -> 23500
B3: ALQUILER VITORIA | C3: 275 | F3: 46387 | G3: =Q15 -> 3605.67 | H3: =Q16 -> 3597.37 | I3: =Q17 -> 2269.984 | J3: =G3+H3+I3 -> 9473.024 | L3: 0 | M3: =Q18 -> 2122.59 | N3: =Q19 -> 2322.59 | O3: =SUM(L3:N3) -> 4445.18 | R3: =I3+O3 -> 6715.164 | S3: 2 | T3: AÑO 2026 | U3: 8400 | W3: 5000 | Y3: =Y2-U3-V3-W3-X3 -> 30700 | AA3: AÑO 2026 | AB3: 6000 | AD3: =AD2-AB3-AC3 -> 17500
B4: OBRAS LOCAL 6600 | C4: 550 | F4: AHORRO | G4: =G3-G2 -> -2464.35 | H4: =H3-H2 -> 364.45 | I4: =I3-I2 -> 2254.67 | J4: =G4+H4+I4 -> 154.77 | L4: =L3-L2 -> 0 | M4: =M3-M2 -> 417.22 | N4: =N3-N2 -> 417.22 | O4: =SUM(L4:N4) -> 834.44 | S4: 3 | T4: AÑO 2027 | U4: 8800 | W4: 5000 | Y4: =Y3-U4-V4-W4-X4 -> 16900 | AA4: AÑO 2027 | AB4: 6000 | AD4: =AD3-AB4-AC4 -> 11500
C5: =SUM(C1:C4) -> 2125 | E5: SIN CONTAR AMORTIZACION | F5: AHORRO * | G5: =G3-G2+F92+J92 -> -2464.35 | H5: =H3-H2 -> 364.45 | I5: =I3-I2 -> 2254.67 | J5: =G5+H5+I5 -> 154.77 | L5: =L3-L2 -> 0 | M5: =M3-M2 -> 417.22 | N5: =N3-N2 -> 417.22 | O5: =SUM(L5:N5) -> 834.44 | R5: =I5+O5 -> 3089.11 | S5: 4 | T5: AÑO 2028 | U5: 9300 | W5: 7500 | Y5: =Y4-U5-V5-W5-X5 -> 100 | AA5: AÑO 2028 | AB5: 9300 | AD5: =AD4-AB5-AC5 -> 2200
S6: 5 | T6: AÑO 2029 | U6: 9600 | Y6: =Y5-U6-V6-W6-X6 -> -9500 | AA6: AÑO 2029 | AB6: 9600 | AD6: =AD5-AB6-AC6 -> -7400
S7: 6 | T7: AÑO 2030 | U7: 6003 | Y7: =Y6-U7-V7-W7-X7 -> -15503 | AA7: AÑO 2030 | AB7: 6003 | AD7: =AD6-AB7-AC7 -> -13403
B9: CASH EN SANTANDER A PRIMEROS DE MES | F9: =G2 -> 6070.02 | G9: =F15 -> 5146.28 | H9: =G15 -> 6081.17 | I9: =H15 -> 4416.61 | J9: =I15 -> 5348.76 | K9: =J15 -> 5485.05 | L9: =K15 -> 3697.18 | M9: =L15 -> 7035.03 | N9: =M15 -> 4500.9 | ... Q9: =P15 -> 3697.51 | R9: =SUM(F9:Q9) -> 58783.77
B10: CASH EN KUTXA A PRIMEROS DE MES | F10: =H2 -> 3232.92 | G10: =F16 -> 3912.66 | H10: =G16 -> 3646.6 | I10: =H16 -> 3463.17 | J10: =I16 -> 1020.92 | K10: =J16 -> 2974.03 | L10: =K16 -> 3383.77 | M10: =L16 -> 3405.97 | N10: =M16 -> 1545.24 | ... Q10: =P16 -> 3269.57 | R10: =SUM(F10:Q10) -> 34698.34
B11: CASH EN N26 A PRIMEROS DE MES | F11: =I2 -> 15.314 | G11: =F17 -> 470.874 | H11: =G17 -> 269.884 | I11: =H17 -> 629.884 | J11: =I17 -> 1128.834 | K11: =J17 -> 1321.414 | L11: =K17 -> 1685.004 | M11: =L17 -> 1871.044 | N11: =M17 -> 2269.984 | ... Q11: =P17 -> 2269.984 | R11: =SUM(F11:Q11) -> 16472.188 | T11: A primeros de 2028 tendremos pendiente 6.800€
B12: CASH EN EPSV KUTXA JULIO PRIMEROS DE MES | F12: =M2 -> 1705.37 | G12: =F18 -> 1739.24 | H12: =G18 -> 1774.09 | I12: =H18 -> 1808.94 | J12: =I18 -> 1843.79 | K12: =J18 -> 1878.64 | L12: =K18 -> 1913.49 | M12: =L18 -> 1948.34 | N12: =M18 -> 1983.19 | ... Q12: =P18 -> 2087.74 | R12: =SUM(F12:Q12) -> 22753.76
B13: CASH EN EPSV KUTXA YOLANDA PRIMEROS DE MES | F13: =N2 -> 1905.37 | G13: =F19 -> 1939.24 | H13: =G19 -> 1974.09 | I13: =H19 -> 2008.94 | J13: =I19 -> 2043.79 | K13: =J19 -> 2078.64 | L13: =K19 -> 2113.49 | M13: =L19 -> 2148.34 | N13: =M19 -> 2183.19 | ... Q13: =P19 -> 2287.74 | R13: =SUM(F13:Q13) -> 25153.76
F14: =SUM(F9:F11) -> 9318.254 | G14: =SUM(G9:G11) -> 9529.814 | H14: =SUM(H9:H11) -> 9997.654 | I14: =SUM(I9:I11) -> 8509.664 | J14: =SUM(J9:J11) -> 7498.514 | K14: =SUM(K9:K11) -> 9780.494 | L14: =SUM(L9:L11) -> 8765.954 | M14: =SUM(M9:M11) -> 12312.044 | ... Q14: =SUM(Q9:Q11) -> 9237.064
B15: CASH EN SANTANDER FIN DE MES | F15: =F9+F150-F151 -> 5146.28 | G15: =G9+G150-G151 -> 6081.17 | H15: =H9+H150-H151 -> 4416.61 | I15: =I9+I150-I151 -> 5348.76 | J15: =J9+J150-J151 -> 5485.05 | K15: =K9+K150-K151 -> 3697.18 | L15: =L9+L150-L151 -> 7035.03 | M15: =M9+M150-M151 -> 4500.9 | ... Q15: =Q9+Q150-Q151 -> 3605.67 | R15: =SUM(F15:Q15) -> 56319.42 | S15: =R15-R9 -> -2464.35 | T15: =S15+S16+S17 -> 154.77 | U15: =T18+T15 -> 989.21
B16: CASH EN KUTXA FIN DE MES | F16: =F10+F153-F154 -> 3912.66 | G16: =G10+G153-G154 -> 3646.6 | H16: =H10+H153-H154 -> 3463.17 | I16: =I10+I153-I154 -> 1020.92 | J16: =J10+J153-J154 -> 2974.03 | K16: =K10+K153-K154 -> 3383.77 | L16: =L10+L153-L154 -> 3405.97 | M16: =M10+M153-M154 -> 1545.24 | ... Q16: =Q10+Q153-Q154 -> 3597.37 | R16: =SUM(F16:Q16) -> 35062.79 | S16: =R16-R10 -> 364.45
B17: CASH EN N26 A FIN DE MES | F17: =F11+F156-F157 -> 470.874 | G17: =G11+G156-G157 -> 269.884 | H17: =H11+H156-H157 -> 629.884 | I17: =I11+I156-I157 -> 1128.834 | J17: =J11+J156-J157 -> 1321.414 | K17: =K11+K156-K157 -> 1685.004 | L17: =L11+L156-L157 -> 1871.044 | M17: =M11+M156-M157 -> 2269.984 | ... Q17: =Q11+Q156-Q157 -> 2269.984 | R17: =SUM(F17:Q17) -> 18726.858 | S17: =R17-R11 -> 2254.67
B18: CASH EN EPSV KUTXA JULIO FIN DE MES | F18: =F12+F93+F117 -> 1739.24 | G18: =G12+G93+G117 -> 1774.09 | H18: =H12+H93+H117 -> 1808.94 | I18: =I12+I93+I117 -> 1843.79 | J18: =J12+J93+J117 -> 1878.64 | K18: =K12+K93+K117 -> 1913.49 | L18: =L12+L93+L117 -> 1948.34 | M18: =M12+M93+M117 -> 1983.19 | ... Q18: =Q12+Q93+Q117 -> 2122.59 | R18: =SUM(F18:Q18) -> 23170.98 | S18: =R18-R12 -> 417.22 | T18: =S18+S19 -> 834.44
B19: CASH EN EPSV KUTXA YOLANDA FIN DE MES | F19: =F13+F93+F118 -> 1939.24 | G19: =G13+G93+G118 -> 1974.09 | H19: =H13+H93+H118 -> 2008.94 | I19: =I13+I93+I118 -> 2043.79 | J19: =J13+J93+J118 -> 2078.64 | K19: =K13+K93+K118 -> 2113.49 | L19: =L13+L93+L118 -> 2148.34 | M19: =M13+M93+M118 -> 2183.19 | ... Q19: =Q13+Q93+Q118 -> 2322.59 | R19: =SUM(F19:Q19) -> 25570.98 | S19: =R19-R13 -> 417.22
F20: =SUM(F15:F17) -> 9529.814 | G20: =SUM(G15:G17) -> 9997.654 | H20: =SUM(H15:H17) -> 8509.664 | I20: =SUM(I15:I17) -> 7498.514 | J20: =SUM(J15:J17) -> 9780.494 | K20: =SUM(K15:K17) -> 8765.954 | L20: =SUM(L15:L17) -> 12312.044 | M20: =SUM(M15:M17) -> 8316.124 | ... Q20: =SUM(Q15:Q17) -> 9473.024
A21: BANCO | C21: CONCEPTO | D21: DIA | E21: OBSERVACIONES | F21: 2026 | R21: TOTAL
F23: ENERO | G23: FEBRERO | H23: MARZO | I23: ABRIL | J23: MAYO | K23: JUNIO | L23: JULIO | M23: AGOSTO | N23: SEPTIEMBRE | O23: OCTUBRE | P23: NOVIEMBRE | Q23: DICIEMBRE
F24: INGRESOS
A25: SANTANDER | B25: NOMINA JULIO | F25: 2277.03 | G25: 2295.28 | H25: 2330.61 | I25: 2365.91 | J25: 2365.91 | K25: 2348.24 | L25: 2365.91 | M25: 0 | N25: 2029.23 | O25: 2315.58 | P25: 2351.39 | Q25: 2055.39 | R25: =SUM(F25:Q25) -> 25100.48
A26: SANTANDER | B26: NOMINA JULIO 2 | H26: 214.96 | J26: 242.8 | L26: 2383.55 | P26: 0.19 | R26: =SUM(F26:Q26) -> 2841.5
A27: SANTANDER | B27: PAGA JULIO | J27: 0.2 | L27: 1965.82 | Q27: 1933.44 | R27: =SUM(F27:Q27) -> 3899.46
A28: SANTANDER | B28: OTROS INGRESOS | R28: =SUM(F28:Q28) -> 0
A29: SANTANDER | B29: DECLARACION JULIO | I29: 1963.96 | R29: =SUM(F29:Q29) -> 1963.96
A30: SANTANDER | B30: DECLARACION YOLANDA | I30: 1693.84 | R30: =SUM(F30:Q30) -> 1693.84
A31: SANTANDER | B31: GESTION COMUNIDAD | R31: =SUM(F31:Q31) -> 0
A32: SANTANDER | B32: TRASFERENCIA DESDE KUTXA | F32: =F119 -> 0 | G32: =G119 -> 0 | H32: =H119 -> 0 | I32: =I119 -> 0 | J32: =J119 -> 0 | K32: =K119 -> 0 | L32: =L119 -> 0 | M32: =M119 -> 0 | ... Q32: =Q119 -> 0 | R32: =SUM(F32:Q32) -> 0
A33: SANTANDER | B33: TRASFERENCIA DESDE N26 | F33: =F135 -> 0 | G33: =G135 -> 0 | H33: =H135 -> 0 | I33: =I135 -> 0 | J33: =J135 -> 0 | K33: =K135 -> 0 | L33: =L135 -> 0 | M33: =M135 -> 0 | ... Q33: =Q135 -> 0 | R33: =SUM(F33:Q33) -> 0 | S33: =SUM(R25:R33) -> 35499.24
A36: KUTXA | B36: NOMINA YOLANDA | F36: 0 | G36: 0 | H36: 0 | I36: 0 | J36: 4715 | K36: 0 | L36: 0 | M36: 0 | N36: 2357.5 | O36: 2357.5 | P36: 2357.5 | Q36: 2357.5 | R36: =SUM(F36:Q36) -> 14145
A37: KUTXA | B37: INGRESO OTROS. NOMINA COBRADA MES ANTERIOR | F37: 2357.5 | G37: 2357.5 | H37: 2357.5 | I37: 0 | J37: 0 | K37: 2357.5 | L37: 2357.5 | M37: 0 | N37: 0 | O37: 0 | P37: 0 | Q37: 0 | R37: =SUM(F37:Q37) -> 11787.5
A38: KUTXA | B38: TRASFERENCIA DESDE SANTANDER | F38: =F95 -> 0 | G38: =G95 -> 0 | H38: =H95 -> 500 | I38: =I95 -> 500 | J38: =J95 -> 500 | K38: =K95 -> 500 | L38: =L95 -> 500 | M38: =M95 -> 500 | ... Q38: =Q95 -> 500 | R38: =SUM(F38:Q38) -> 5000
A39: KUTXA | B39: TRASFERENCIA DESDE N26 | F39: =F136 -> 0 | G39: =G136 -> 0 | H39: =H136 -> 0 | I39: =I136 -> 0 | J39: =J136 -> 0 | K39: =K136 -> 0 | L39: =L136 -> 0 | M39: =M136 -> 0 | ... Q39: =Q136 -> 0 | R39: =SUM(F39:Q39) -> 0 | S39: =SUM(R36:R39) -> 30932.5
A41: N26 | B41: INGRESO OTROS | F41: 0 | G41: 0 | H41: 0 | I41: 0 | J41: 0 | K41: 0 | L41: 0 | M41: 0 | N41: 0 | O41: 0 | P41: 0 | Q41: 0 | R41: =SUM(F41:Q41) -> 0
A42: N26 | B42: TRASFERENCIA DESDE SANTANDER-1- IMPREVISTOS | F42: =F96 -> 1000 | G42: =G96 -> 0 | H42: =H96 -> 500 | I42: =I96 -> 500 | J42: =J96 -> 500 | K42: =K96 -> 500 | L42: =L96 -> 500 | M42: =M96 -> 500 | ... Q42: =Q96 -> 500 | R42: =SUM(F42:Q42) -> 6000
A43: N26 | B43: TRASFERENCIA DESDE SANTANDER-2-AHORROS | F43: =F97 -> 0 | G43: =G97 -> 0 | H43: =H97 -> 0 | I43: =I97 -> 0 | J43: =J97 -> 0 | K43: =K97 -> 0 | L43: =L97 -> 0 | M43: =M97 -> 0 | ... Q43: =Q97 -> 0 | R43: =SUM(F43:Q43) -> 0
A44: N26 | B44: TRASFERENCIA DESDE KUTXA | F44: =F120 -> 0 | G44: =G120 -> 0 | H44: =H120 -> 0 | I44: =I120 -> 0 | J44: =J120 -> 0 | K44: =K120 -> 0 | L44: =L120 -> 0 | M44: =M120 -> 0 | ... Q44: =Q120 -> 0 | R44: =SUM(F44:Q44) -> 0 | S44: =SUM(R41:R44) -> 6000
R45: =R25+R26+R27+R28+R29+R30+R31+R36+R37+R41 -> 61431.74 | S45: =S33+S39+S44 -> 72431.74 | T45: * INCLUYENDO INGRESOS DE OTRAS CUENTAS
F47: GASTOS
A48: SANTANDER | B48: GASTOS TIPO 1 | C48: GASTO | D48: 1 | F48: ='GASTOS '!F17 -> 504.37 | G48: ='GASTOS '!L17 -> 22.24 | H48: ='GASTOS '!R17 -> 1644.14 | I48: ='GASTOS '!X17 -> 2794.59 | J48: ='GASTOS '!AD17 -> 119.25 | K48: ='GASTOS '!AJ17 -> 1338.3 | L48: ='GASTOS '!AP17 -> 1188.09 | M48: ='GASTOS '!AV17 -> 193.62 | N48: ='GASTOS '!BB17 -> 0 | O48: ='GASTOS '!BH17 -> 0 | P48: ='GASTOS '!BN17 -> 0 | Q48: ='GASTOS '!BT17 -> 0 | R48: =SUM(F48:Q48) -> 7804.6
A49: SANTANDER | B49: HIPOTECA | C49: GASTO | D49: 1 | F49: 808.1 | G49: 802.79 | H49: 802.79 | I49: 802.79 | J49: 802.79 | K49: 802.79 | L49: 802.79 | M49: 802.79 | N49: 802.79 | O49: 802.79 | P49: 802.79 | Q49: 802.79 | R49: =SUM(F49:Q49) -> 9638.79
A50: SANTANDER | B50: COMUNIDAD | C50: GASTO | D50: 5 | F50: 43.83 | G50: 43.83 | H50: 43.83 | I50: 43.83 | J50: 43.83 | K50: 43.83 | L50: 43.83 | M50: 43.83 | N50: 43.83 | O50: 43.83 | P50: 43.83 | Q50: 43.83 | R50: =SUM(F50:Q50) -> 525.96
A51: SANTANDER | B51: EKILUZ CUOTA | C51: GASTO | F51: 9 | G51: 9 | H51: 9 | I51: 9 | J51: 9 | K51: 9 | L51: 9 | M51: 9 | N51: 9 | O51: 9 | P51: 9 | Q51: 9 | R51: =SUM(F51:Q51) -> 108
A52: SANTANDER | B52: IBERDROLA (CUNENERGIA) / EKILUZ / REPSOL | C52: GASTO | D52: 1-3 | F52: 51.5 | G52: 66.58 | I52: 18.84 | J52: 43.73 | K52: 27.04 | L52: 27.05 | M52: 34.15 | N52: 41.02 | O52: 43.22 | P52: 85.44 | Q52: 40 | R52: =SUM(F52:Q52) -> 478.57
A53: SANTANDER | B53: EUSKALTEL / DIGI | C53: GASTO | D53: 28 | F53: 37 | G53: 37 | H53: 37 | I53: 37 | J53: 37.93 | K53: 37 | L53: 37 | M53: 37 | N53: 37 | O53: 37 | P53: 33.43 | Q53: 37 | R53: =SUM(F53:Q53) -> 441.36
A54: SANTANDER | B54: GAS (Total Energies) | C54: GASTO | D54: 22-23 | F54: 170.01 | H54: 133.05 | I54: 30.79 | K54: 90.05 | M54: 72.41 | O54: 66.08 | Q54: 69.94 | R54: =SUM(F54:Q54) -> 632.33
A55: SANTANDER | B55: GIPUZKOAKO URAK | C55: GASTO | D55: 10 | G55: 106.94 | J55: 113.89 | M55: 102.81 | P55: 110.2 | R55: =SUM(F55:Q55) -> 433.84
A56: SANTANDER | B56: SEGURO VIDA 1 (SANTANDER SEG) | C56: GASTO | Q56: 124.35 | R56: =SUM(F56:Q56) -> 124.35
A57: SANTANDER | B57: SEGURO VIDA 2 (SANTANDER SEG) | C57: GASTO | Q57: 113.24 | R57: =SUM(F57:Q57) -> 113.24
A58: SANTANDER | B58: CONTRIBUCION.IBI URBANA (Eibarko udala) | C58: GASTO | K58: 352 | R58: 306.63
A59: SANTANDER | B59: ESTUDIOS AMAIA | C59: GASTO | N59: 427.89 | Q59: 621.81 | R59: =SUM(F59:Q59) -> 1049.7
A60: SANTANDER | B60: ESTUDIOS OLATZ | C60: GASTO | N60: 31.8 | Q60: 565.5 | R60: =SUM(F60:Q60) -> 597.3
A61: SANTANDER | B61: TRANSPORTE YOLI / OLATZ / AMAIA (MUGI/BARIK) | C61: GASTO | F61: 150 | G61: 100 | H61: 200 | I61: 140 | J61: 100 | K61: 150 | L61: 100 | M61: 0 | N61: 20 | O61: 100 | P61: 0 | Q61: 100 | R61: =SUM(F61:Q61) -> 1160
A62: SANTANDER | B62: LAB | C62: GASTO | D62: 1 | F62: 21.73 | G62: 21.73 | H62: 21.73 | I62: 21.73 | J62: 21.73 | K62: 21.73 | L62: 21.73 | M62: 21.73 | N62: 21.73 | O62: 21.73 | P62: 21.73 | Q62: 21.73 | R62: =SUM(F62:Q62) -> 260.76
A63: SANTANDER | B63: IMP.CIRCULACION (Eibarko udala) LEON | C63: GASTO | R63: =SUM(F63:Q63) -> 0
A64: SANTANDER | B64: ITV LEON | C64: GASTO | O64: 50 | R64: =SUM(F64:Q64) -> 50
A65: SANTANDER | B65: GASOLINA LEON | C65: GASTO | F65: 50 | G65: 50 | H65: 100 | I65: 30 | J65: 30 | K65: 88.31 | L65: 30 | M65: 75.1 | N65: 112.6 | O65: 60.02 | P65: 50 | Q65: 50 | R65: =SUM(F65:Q65) -> 726.03
A66: SANTANDER | B66: IBI GARAJE | C66: GASTO | K66: 58.34 | R66: =SUM(F66:Q66) -> 58.34
A67: SANTANDER | B67: CUOTA GARAJE (Cdad. Ubitxa n 22) | C67: GASTO | N67: 160 | R67: =SUM(F67:Q67) -> 160
A68: SANTANDER | B68: ABIATU/BIDEGI | C68: GASTO | D68: 20 | F68: 49.65 | G68: 31.8 | H68: 39.11 | I68: 48.51 | J68: 45.99 | K68: 36.24 | L68: 36.46 | M68: 55.22 | N68: 36.75 | O68: 38.78 | P68: 22.18 | Q68: 50 | R68: =SUM(F68:Q68) -> 490.69
A69: SANTANDER | B69: POLIDEPORTIVO | C69: GASTO | F69: 228.1 | R69: =SUM(F69:Q69) -> 228.1
A70: SANTANDER | B70: CD EIBAR JULIO | C70: GASTO | H70: 25 | R70: =SUM(F70:Q70) -> 25
A71: SANTANDER | B71: CD EIBAR YOLANDA | C71: GASTO | H71: 25 | R71: =SUM(F71:Q71) -> 25
A72: SANTANDER | B72: CD EIBAR OLATZ | C72: GASTO | H72: 25 | R72: =SUM(F72:Q72) -> 25
A73: SANTANDER | B73: CD EIBAR AMAIA | C73: GASTO | H73: 25 | R73: =SUM(F73:Q73) -> 25
A74: SANTANDER | B74: LICENCIA FEDERADO (LABORAL) | C74: GASTO | Q74: 350 | R74: =SUM(F74:Q74) -> 350
A75: SANTANDER | B75: SOCIEDAD OTARRA (KUTXA) | C75: GASTO | D75: 5 | F75: 30 | G75: 30 | H75: 30 | I75: 30 | J75: 30 | K75: 30 | L75: 30 | M75: 30 | N75: 30 | O75: 30 | P75: 30 | Q75: 30 | R75: =SUM(F75:Q75) -> 360
A76: SANTANDER | B76: HBO+SKYSHOWTIME (RICAR) | C76: GASTO | D76: 5 | E76: 7+9 (AMAZON) | F76: 7.5 | G76: 7.5 | H76: 7.5 | I76: 7.5 | J76: 7.5 | K76: 7.5 | L76: 7.5 | M76: 7.5 | N76: 7.5 | O76: 7.5 | P76: 7.5 | Q76: 7.5 | R76: =SUM(F76:Q76) -> 90
A77: SANTANDER | B77: MOVISTAR PLUS | C77: GASTO | E77: 4,99 | M77: 4.99 | N77: 4.99 | O77: 4.99
A78: SANTANDER | B78: DISNEY PLUS | C78: GASTO | E78: 7
A79: SANTANDER | B79: APPLE TV | C79: GASTO | E79: 10 (AMAZON)
A80: SANTANDER | B80: NETFLIX | C80: GASTO | D80: 9 | E80: 9 | F80: 6.99 | G80: 6.99 | H80: 6.99 | I80: 6.99 | J80: 6.99 | K80: 8.99 | L80: 8.99 | M80: 8.99 | N80: 8.99 | O80: 8.99 | P80: 8.99 | Q80: 8.99 | R80: =SUM(F80:Q80) -> 97.88
A81: SANTANDER | B81: OFFICE 365 | C81: GASTO | D81: 1-3 | E81: PAYPAL-SANTANDER | F81: 13 | G81: 13 | H81: 13 | I81: 13 | J81: 13 | K81: 13 | L81: 13 | M81: 13 | N81: 13 | O81: 13 | P81: 13 | Q81: 13 | R81: =SUM(F81:Q81) -> 156
A82: SANTANDER | B82: AMAZON MUSIC | C82: GASTO | D82: 13 | R82: =SUM(F82:Q82) -> 0
A83: SANTANDER | B83: DOMESTIKA | C83: GASTO | D83: 8 | R83: =SUM(F83:Q83) -> 0
A84: SANTANDER | B84: HP INSTANTK | C84: GASTO | D84: 7 | E84: PAYPAL-SANTANDER | R84: =SUM(F84:Q84) -> 0
A85: SANTANDER | B85: DAZN | C85: GASTO | D85: 2-7 | E85: PAYPAL-SANTANDER | R85: =SUM(F85:Q85) -> 0
A86: SANTANDER | B86: ADOBE CREATIVE CLOUD | C86: GASTO | D86: 27-30 | E86: PAYPAL-SANTANDER | R86: =SUM(F86:Q86) -> 0
A87: SANTANDER | B87: EUSKAL ARTZAIN TXAKURRA | C87: GASTO | J87: 25 | R87: =SUM(F87:Q87) -> 25
A88: SANTANDER | B88: AMAZON PREMIUM | C88: GASTO | E88: SANTANDER | O88: 49.9 | R88: =SUM(F88:Q88) -> 49.9
A89: SANTANDER | B89: CUOTA CONSUMO | C89: GASTO | I89: 35 | R89: =SUM(F89:Q89) -> 35
A90: SANTANDER | B90: GOOGLE ONE | C90: GASTO | E90: PAYPAL-SANTANDER | F90: 19.99 | G90: 10.99 | H90: 21.99 | I90: 21.99 | J90: 21.99 | K90: 21.99 | L90: 21.99 | M90: 21.99 | N90: 21.99 | O90: 21.99 | P90: 21.99 | Q90: 21.99 | R90: =SUM(F90:Q90) -> 250.88
A91: SANTANDER | B91: PRESTAMO OLATZ | C91: PRESTAMO / INVERSION | D91: 10 | R91: =SUM(F91:Q91) -> 0
A92: SANTANDER | B92: HIPOTECA AMORTIZACION EXTRA | C92: INVERSION | R92: =SUM(F92:Q92) -> 0
A93: SANTANDER | B93: TRASPASO DESDE SANTANDER A FONDO JBN | C93: INVERSION | R93: =SUM(F93:Q93) -> 0
A94: SANTANDER | B94: TRASPASO DESDE SANTANDER A FONDO YUG | C94: INVERSION | R94: =SUM(F94:Q94) -> 0
A95: SANTANDER | B95: TRASPASO DESDE SANTANDER A KUTXA | C95: TRASPASO | F95: 0 | G95: 0 | H95: 500 | I95: 500 | J95: 500 | K95: 500 | L95: 500 | M95: 500 | N95: 500 | O95: 500 | P95: 500 | Q95: 500 | R95: =SUM(F95:Q95) -> 5000
A96: SANTANDER | B96: TRASPASO DESDE SANTANDER A N26 -1-IMPREVISTOS | C96: TRASPASO | F96: 1000 | G96: 0 | H96: 500 | I96: 500 | J96: 500 | K96: 500 | L96: 500 | M96: 500 | N96: 500 | O96: 500 | P96: 500 | Q96: 500 | R96: =SUM(F96:Q96) -> 6000
A97: SANTANDER | B97: TRASPASO DESDE SANTANDER A N26 -2-AHORROS | C97: TRASPASO | R97: =SUM(F97:Q97) -> 0
A98: SANTANDER | B98: TRASPASO DESDE SANTANDER A INDEXA | C98: INVERSION | R98: =SUM(F98:Q98) -> 0
E99: GASTOS TIPO 2 | F99: =SUM(F49:F91)+F95+F96 -> 2696.4 | G99: =SUM(G49:G91)+G95+G96 -> 1338.15 | H99: =SUM(H49:H91)+H95+H96 -> 2565.99 | I99: =SUM(I49:I91)+I95+I96 -> 2296.97 | J99: =SUM(J49:J91)+J95+J96 -> 2353.37 | K99: =SUM(K49:K91)+K95+K96 -> 2797.81 | L99: =SUM(L49:L91)+L95+L96 -> 2189.34 | M99: =SUM(M49:M91)+M95+M96 -> 2340.51 | ... Q99: =SUM(Q49:Q91)+Q95+Q96 -> 4080.67 | R99: =SUM(F99:Q99) -> 30158.99
E100: GASTOS TIPO 1 + TIPO 2 | F100: =F99+F48 -> 3200.77 | G100: =G99+G48 -> 1360.39 | H100: =H99+H48 -> 4210.13 | I100: =I99+I48 -> 5091.56 | J100: =J99+J48 -> 2472.62 | K100: =K99+K48 -> 4136.11 | L100: =L99+L48 -> 3377.43 | M100: =M99+M48 -> 2534.13 | ... Q100: =Q99+Q48 -> 4080.67 | R100: =SUM(F100:Q100) -> 37963.59
A102: KUTXA | B102: GASTOS TIPO 1 | F102: =IF(MINIMOS!B2="Sí",'GASTOS '!F53,IF(AND(MINIMOS!B2="No",'GASTOS '!F53<1400),1400,'GASTOS '!F53)) -> 628.72 | G102: =IF(MINIMOS!C2="Sí",'GASTOS '!L53,IF(AND(MINIMOS!C2="No",'GASTOS '!L53<1400),1400,'GASTOS '!L53)) -> 1350.38 | H102: =IF(MINIMOS!D2="Sí",'GASTOS '!R53,IF(AND(MINIMOS!D2="No",'GASTOS '!R53<1400),1400,'GASTOS '!R53)) -> 2188.18 | I102: =IF(MINIMOS!E2="Sí",'GASTOS '!X53,IF(AND(MINIMOS!E2="No",'GASTOS '!X53<1400),1400,'GASTOS '!X53)) -> 1872.3 | J102: =IF(MINIMOS!F2="Sí",'GASTOS '!AD53,IF(AND(MINIMOS!F2="No",'GASTOS '!AD53<1400),1400,'GASTOS '!AD53)) -> 2173.43 | K102: =IF(MINIMOS!G2="Sí",'GASTOS '!AJ53,IF(AND(MINIMOS!G2="No",'GASTOS '!AJ53<1400),1400,'GASTOS '!AJ53)) -> 1503.24 | L102: =IF(MINIMOS!H2="Sí",'GASTOS '!AP53,IF(AND(MINIMOS!H2="No",'GASTOS '!AP53<1400),1400,'GASTOS '!AP53)) -> 1948.73 | M102: =IF(MINIMOS!I2="Sí",'GASTOS '!AV53,IF(AND(MINIMOS!I2="No",'GASTOS '!AV53<1400),1400,'GASTOS '!AV53)) -> 1406.57 | N102: =IF(MINIMOS!J2="Sí",'GASTOS '!BB53,IF(AND(MINIMOS!J2="No",'GASTOS '!BB53<1400),1400,'GASTOS '!BB53)) -> 1400 | O102: =IF(MINIMOS!K2="Sí",'GASTOS '!BH53,IF(AND(MINIMOS!K2="No",'GASTOS '!BH53<1400),1400,'GASTOS '!BH53)) -> 1400 | P102: =IF(MINIMOS!L2="Sí",'GASTOS '!BN53,IF(AND(MINIMOS!L2="No",'GASTOS '!BN53<1400),1400,'GASTOS '!BN53)) -> 1400 | Q102: =IF(MINIMOS!M2="Sí",'GASTOS '!BT53,IF(AND(MINIMOS!M2="No",'GASTOS '!BT53<1400),1400,'GASTOS '!BT53)) -> 1400 | R102: =SUM(F102:Q102) -> 18671.55
A103: KUTXA | B103: SEGURO COCHE SEAT | C103: GASTO | O103: 280.39 | R103: =SUM(F103:Q103) -> 280.39
A104: KUTXA | B104: SEGURO HOGAR | C104: GASTO | Q104: 350 | R104: =SUM(F104:Q104) -> 350
A105: KUTXA | B105: SEGURO URKI BAJO | C105: GASTO | D105: 6 | G105: 181.54 | R105: 159.08
A106: KUTXA | B106: AGUA URKI BAJO | C106: GASTO | D106: 6 | G106: 36.23 | J106: 36.97 | M106: 35.68 | P106: 28.68 | R106: =SUM(F106:Q106) -> 137.56
A107: KUTXA | B107: IBI URKI BAJO | C107: GASTO | K107: 57.91 | R107: =SUM(F107:Q107) -> 57.91
...

Sheet GASTOS 
A1: SANTANDER | B1: ENERO | H1: FEBRERO | N1: MARZO | T1: ABRIL | Z1: MAYO | AF1: JUNIO | AL1: JULIO | AR1: AGOSTO | AX1: SEPTIEMBRE | BD1: OCTUBRE | BJ1: NOVIEMBRE | BP1: DICIEMBRE
B2: DIA | C2: TIENDA | D2: CONCEPTO | E2: CATEGORIA | F2: CANTIDAD | G2: BANCO | H2: DIA | I2: TIENDA | J2: CONCEPTO | K2: CATEGORIA | L2: CANTIDAD | M2: BANCO | N2: DIA | O2: TIENDA | P2: CONCEPTO | Q2: CATEGORIA | R2: CANTIDAD | S2: BANCO | T2: DIA | U2: TIENDA | V2: CONCEPTO | W2: CATEGORIA | X2: CANTIDAD | Y2: BANCO | Z2: DIA | AA2: TIENDA | AB2: CONCEPTO | AC2: CATEGORIA | AD2: CANTIDAD | AE2: BANCO | AF2: DIA | AG2: TIENDA | AH2: CONCEPTO | AI2: CATEGORIA | AJ2: CANTIDAD | AK2: BANCO | AL2: DIA | AM2: TIENDA | AN2: CONCEPTO | AO2: CATEGORIA | AP2: CANTIDAD | AQ2: BANCO | AR2: DIA | AS2: TIENDA | AT2: CONCEPTO | AU2: CATEGORIA | AV2: CANTIDAD | AW2: BANCO | AX2: DIA | AY2: TIENDA | AZ2: CONCEPTO | BA2: CATEGORIA | BB2: CANTIDAD | BC2: BANCO | BD2: DIA | BE2: TIENDA | BF2: CONCEPTO | BG2: CATEGORIA | BH2: CANTIDAD | BI2: BANCO | BJ2: DIA | BK2: TIENDA | BL2: CONCEPTO | BM2: CATEGORIA | BN2: CANTIDAD | BO2: BANCO | BP2: DIA | BQ2: TIENDA | BR2: CONCEPTO | BS2: CATEGORIA | BT2: CANTIDAD | BU2: BANCO
B3: 10 | C3: LEROY MERLIN | D3: MUEBLE Y GRIFERIA BAÑO | F3: 353.96 | G3: S | T3: 46123 | U3: DIA | X3: 64.81 | Y3: K | Z3: 46147 | AA3: PAYPAL | AB3: SILLA ESCRITORIO | AD3: 36.42 | AE3: S | AL3: 46209 | AM3: DEPORVILLAGE | AN3: REGALO YOLI | AP3: 152.85 | AQ3: S | AR3: 46235 | AS3: ARRATE | AV3: 74.34
B4: 46038 | C4: GOOGLE ONE | D4: DEVOLUCION | F4: -19.71 | G4: S | I4: Aliexpress | L4: 0.99 | N4: 46091 | O4: Toogoogtogo | R4: 5.99 | S4: K | T4: 46129 | U4: TEMU | X4: 25.18 | Y4: K | Z4: 46153 | AA4: CLAUDE? | AD4: 23.1 | AE4: S | AF4: 46192 | AG4: PAYPAL | AH4: JUEGO EPIC | AJ4: 0.89 | AK4: S | AL4: 46226 | AM4: JUSTEAT | AP4: 25.25 | AQ4: S | AR4: 46237 | AS4: TEMU | AT4: CAMISETA | AV4: 11.64 | AW4: K
B5: 46038 | C5: GOOGLE ONE | D5: PRO | F5: 10.99 | G5: S | N5: 46092 | O5: Spotify | R5: 6 | S5: S | T5: 46130 | U5: BUENOS AIRES | X5: 4.6 | Y5: K | Z5: 46157 | AA5: AMAZON | AB5: GEL DECAPANTE | AD5: 35.99 | AE5: S | AF5: 46202 | AG5: PAYPAL | AH5: SILLA TIK TOK | AJ5: 37.41 | AK5: S | AL5: 46228 | AM5: WIKILOC | AP5: 9.99 | AQ5: S | AR5: 46238 | AS5: JUSTEAT | AV5: 16.71 | AW5: K
B6: 46041 | C6: TEMU | D6: PARAGUAS Y PARCHES | F6: 23.09 | G6: K | I6: just eat | L6: 21.25 | N6: 46105 | O6: JustEat | R6: 32.15 | S6: K | T6: 46139 | U6: RETIRADA | V6: RIFF | X6: 900 | Y6: S | Z6: 46160 | AA6: AMAZON | AB6: PELICULA DEMOLICION | AD6: 3.99 | AE6: S | AR6: 46247 | AS6: TIK TOK SHOP | AT6: TOALLA | AV6: 9.94 | AW6: K
B7: 46048 | C7: TRASPASO A REVOLUT | F7: 136.04 | G7: K | T7: 46140 | U7: RETIRADA | V7: RIFF | X7: 900 | Y7: S | Z7: 46168 | AA7: JUST-EAT | AD7: 19.75 | AE7: S | AR7: 46248 | AS7: EROSKI | AV7: 35.25 | AW7: K
T8: 46141 | U8: RETIRADA | V8: RIFF | X8: 900 | Y8: S | AR8: 46259 | AS8: JUSTEAT | AV8: 19.75 | AW8: K
AR9: 46260 | AS9: PARFOIS | AV9: 25.99 | AW9: K
AF14: 46178 | AG14: JUANCAR | AH14: ADELANTO RIFF | AI14: RETIRADA EFECTIVO | AJ14: 800 | AK14: S
O15: REONOR | P15: PLADUR | R15: 1600 | S15: S | AF15: 46182 | AG15: JUANCAR | AH15: ADELANTO RIFF | AI15: RETIRADA EFECTIVO | AJ15: 500 | AK15: S | AN15: RIFF | AO15: RETIRADAS EFECTIVO | AP15: 1000 | AQ15: S
F17: =SUM(F2:F16) -> 504.37 | L17: =SUM(L3:L16) -> 22.24 | R17: =SUM(R3:R16) -> 1644.14 | X17: =SUM(X3:X16) -> 2794.59 | AD17: =SUM(AD3:AD16) -> 119.25 | AJ17: =SUM(AJ3:AJ16) -> 1338.3 | AP17: =SUM(AP2:AP16) -> 1188.09 | AV17: =SUM(AV2:AV16) -> 193.62 | BB17: =SUM(BB2:BB16) -> 0 | BH17: =SUM(BH3:BH16) -> 0 | BN17: =SUM(BN2:BN16) -> 0 | BT17: =SUM(BT2:BT16) -> 0
AD19: =X19+AD18 -> 0
A20: KUTXA | B20: ENERO | H20: FEBRERO | N20: MARZO | T20: ABRIL | Z20: MAYO | AF20: JUNIO | AL20: JULIO | AR20: AGOSTO | AX20: SEPTIEMBRE | BD20: OCTUBRE | BJ20: NOVIEMBRE | BP20: DICIEMBRE
B21: DIA | C21: TIENDA | D21: CONCEPTO | E21: CATEGORIA | F21: CANTIDAD | G21: BANCO | H21: DIA | I21: TIENDA | J21: CONCEPTO | K21: CATEGORIA | L21: CANTIDAD | M21: BANCO | N21: DIA | O21: TIENDA | P21: CONCEPTO | Q21: CATEGORIA | R21: CANTIDAD | S21: BANCO | T21: DIA | U21: TIENDA | V21: CONCEPTO | W21: CATEGORIA | X21: CANTIDAD | Y21: BANCO | Z21: DIA | AA21: TIENDA | AB21: CONCEPTO | AC21: CATEGORIA | AD21: CANTIDAD | AE21: BANCO | AF21: DIA | AG21: TIENDA | AH21: CONCEPTO | AI21: CATEGORIA | AJ21: CANTIDAD | AK21: BANCO | AL21: DIA | AM21: TIENDA | AN21: CONCEPTO | AO21: CATEGORIA | AP21: CANTIDAD | AQ21: BANCO | AR21: DIA | AS21: TIENDA | AT21: CONCEPTO | AU21: CATEGORIA | AV21: CANTIDAD | AW21: BANCO | AX21: DIA | AY21: TIENDA | AZ21: CONCEPTO | BA21: CATEGORIA | BB21: CANTIDAD | BC21: BANCO | BD21: DIA | BE21: TIENDA | BF21: CONCEPTO | BG21: CATEGORIA | BH21: CANTIDAD | BI21: BANCO | BJ21: DIA | BK21: TIENDA | BL21: CONCEPTO | BM21: CATEGORIA | BN21: CANTIDAD | BO21: BANCO | BP21: DIA | BQ21: TIENDA | BR21: CONCEPTO | BS21: CATEGORIA | BT21: CANTIDAD | BU21: BANCO
B22: 46024 | C22: BIZUM | D22: PELUQUERIA | F22: 87 | G22: K | H22: 46054 | I22: GASTOS TARJETA | L22: 585.13 | N22: 46082 | O22: GASTOS TARJETA | R22: 559.1 | T22: 46113 | U22: PAGO CAJERO | X22: 100 | Y22: K | Z22: 46143 | AA22: GASTOS TARJETA | AD22: 26.74 | AF22: 46174 | AG22: GASTOS TARJETA | AJ22: 94.77 | AL22: 46204 | AM22: GASTOS TARJETA | AP22: 109.82 | AR22: 46235 | AS22: PAGO CAJERO | AV22: 150 | AW22: K
B23: 46025 | C23: PAGO CAJERO | F23: 50 | G23: K | H23: 46054 | I23: PAGO CAJERO | L23: 50 | M23: K | N23: 46085 | O23: PAGO CAJERO | R23: 50 | S23: K | T23: 46119 | U23: PAGO CAJERO | X23: 100 | Y23: K | Z23: 46143 | AA23: PAGO CAJERO | AD23: 100 | AE23: K | AF23: 46174 | AG23: GASTOS TARJETA | AJ23: 155.28 | AL23: 46206 | AM23: GASTOS TARJETA | AP23: 264.08 | AR23: 46238 | AS23: PAGO CAJERO | AV23: 50 | AW23: K
B24: 46031 | C24: PAGO CAJERO | F24: 100 | G24: K | H24: 46058 | I24: PAGO CAJERO | L24: 50 | M24: K | N24: 46085 | O24: AMAIA | R24: 54.45 | S24: K | T24: 46121 | U24: IMPUESTO CIRCULACION | X24: 88 | Y24: K | Z24: 46146 | AA24: BIZUM | AB24: IBUR ERREKA | AD24: 70 | AE24: K | AF24: 46175 | AG24: op.net | AJ24: 16.4 | AK24: K | AL24: 46209 | AM24: GASTOS TARJETA | AP24: 182.79 | AR24: 46242 | AS24: PAGO CAJERO | AV24: 100 | AW24: K
B25: 46032 | C25: GASTOS TARJETA | F25: 271.72 | H25: 46060 | I25: BIZUM | J25: BAR VITORIA | L25: 4.9 | M25: K | N25: 46086 | O25: AMAIA | R25: 15.55 | S25: K | T25: 46122 | U25: BIZUM | X25: 10 | Y25: K | Z25: 46147 | AA25: PAGO CAJERO | AD25: 50 | AE25: K | AF25: 46176 | AG25: PAGO CAJERO | AJ25: 50 | AK25: K | AL25: 46213 | AM25: COCHE | AN25: PUESTA A PUNTO | AP25: 646.06 | AQ25: K | AR25: 46244 | AS25: GASTOS TARJETA | AV25: 122.08
B26: 46033 | C26: PAGO CAJERO | F26: 50 | G26: K | H26: 46061 | I26: PAGO CAJERO | L26: 50 | M26: K | N26: 46088 | O26: PAGO CAJERO | R26: 120 | S26: K | T26: 46123 | U26: EUSKALTEGI C2 | X26: 50 | Y26: K | Z26: 46147 | AA26: BIZUM | AB26: COMPRA DOS SEMANAS | AD26: 30 | AE26: K | AF26: 46178 | AG26: PAGO CAJERO | AJ26: 100 | AK26: K | AL26: 46214 | AM26: PAGO CAJERO | AP26: 100 | AQ26: K | AR26: 46244 | AS26: PAGO CAJERO | AV26: 50 | AW26: K
B27: 46039 | C27: PAGO CAJERO | F27: 100 | G27: K | H27: 46064 | I27: PAGO CAJERO | L27: 300 | M27: K | N27: 46090 | O27: PAGO CAJERO | R27: 50 | S27: K | T27: 46125 | U27: PAGO CAJERO | X27: 50 | Y27: K | Z27: 46149 | AA27: PAGO CAJERO | AD27: 50 | AE27: K | AF27: 46181 | AG27: PAGO CAJERO | AJ27: 50 | AK27: K | AL27: 46217 | AM27: PAGO CAJERO | AP27: 50 | AQ27: K | AR27: 46248 | AS27: PAGO CAJERO | AV27: 50 | AW27: K
B28: 46040 | C28: PAGO CAJERO | F28: 50 | G28: K | H28: 46068 | I28: FACTURA LUZ | L28: 12.9 | M28: K | N28: 46091 | O28: GALLETAS | R28: -3 | S28: K | T28: 46126 | U28: BIZUM | X28: 8 | Y28: K | Z28: 46149 | AA28: BIZUM | AB28: TOALLAS EVA | AD28: -12 | AE28: K | AF28: 46185 | AG28: PAGO CAJERO | AJ28: 50 | AK28: K | AL28: 46222 | AM28: COMIDA ZARAUTZ | AP28: 60 | AQ28: K | AR28: 46250 | AS28: GASTOS TARJETA | AV28: 133.22
B29: 46041 | C29: LUZ AMAIA | D29: PISO VITORIA | F29: 10 | G29: K | H29: 46070 | I29: PAGO CAJERO | L29: 40 | M29: K | N29: 46093 | O29: AMAIA | R29: 17 | S29: K | T29: 46129 | U29: PAGO CAJERO | X29: 100 | Y29: K | Z29: 46150 | AA29: TRASFERENCIA | AB29: DERRAMA URKI BAJO 9 | AD29: 549.95 | AE29: K | AF29: 46186 | AG29: PAGO CAJERO | AJ29: 100 | AK29: K | AL29: 46222 | AM29: GASTOS TARJETA | AP29: 343.96 | AR29: 46251 | AS29: PAGO CAJERO | AV29: 50 | AW29: K
B30: 46042 | C30: INGRESO NIÑAS LONDRES | F30: -140 | G30: K | H30: 46077 | I30: FACTURA AGUA | L30: 5.45 | M30: K | N30: 46094 | O30: PAGO CAJERO | R30: 100 | S30: K | T30: 46131 | U30: PAGO CAJERO | X30: 100 | Y30: K | Z30: 46150 | AA30: PAGO CAJERO | AD30: 50 | AE30: K | AF30: 46189 | AG30: PAGO CAJERO | AJ30: 100 | AK30: K | AL30: 46224 | AM30: PAGO CAJERO | AP30: 50 | AQ30: K | AR30: 46252 | AS30: PAGO CAJERO | AV30: 50 | AW30: K
B31: 46050 | C31: PAGO CAJERO | F31: 50 | G31: K | H31: 46080 | I31: PAGO CAJERO | L31: 50 | M31: K | N31: 46068 | O31: GASTOS TARJETA | R31: 566.11 | T31: 46134 | U31: BIZUM | X31: 18 | Y31: K | Z31: 46154 | AA31: BIZUM | AB31: ORLA | AD31: 15 | AE31: K | AF31: 46191 | AG31: TRASFERENCIA | AJ31: 50 | AK31: K | AL31: 46230 | AM31: GASTOS TARJETA | AP31: 25.13 | AR31: 46255 | AS31: GASTOS TARJETA | AV31: 168.92
H32: 46081 | I32: COMPRA | L32: 20 | M32: K | N32: 46097 | O32: PAGO CAJERO | R32: 50 | S32: K | T32: 46135 | U32: BIZUM | V32: LONDRES | X32: 100 | Y32: K | Z32: 46154 | AA32: BIZUM | AB32: PASTILLAS KALA | AD32: 54 | AE32: K | AF32: 46193 | AG32: PAGO CAJERO | AJ32: 50 | AK32: K | AL32: 46232 | AM32: PAGO CAJERO | AP32: 30 | AQ32: K | AR32: 46255 | AS32: PAGO CAJERO | AV32: 100 | AW32: K
H33: 46081 | I33: PAGO CAJERO | L33: 100 | M33: K | N33: 46099 | O33: PAGO CAJERO | R33: 250 | S33: K | T33: 46135 | U33: BIZUM | V33: LONDRES | X33: 100 | Y33: K | Z33: 46157 | AA33: PAGO CAJERO | AD33: 50 | AE33: K | AF33: 46196 | AG33: BIZUM | AH33: CAFES | AJ33: 3.4 | AK33: K | AL33: 46233 | AM33: GASTOS TARJETA | AP33: 54.99 | AR33: 46255 | AS33: GASTOS TARJETA | AV33: 35.65
H34: 46081 | I34: BIZUM | L34: 82 | M34: K | N34: 46104 | O34: MUGI | R34: 20 | S34: K | T34: 46136 | U34: PAGO CAJERO | X34: 50 | Y34: K | Z34: 46158 | AA34: GASTOS TARJETA | AD34: 446.76 | AF34: 46196 | AG34: BIZUM | AH34: CAMARA | AJ34: -155 | AK34: K | AL34: 46234 | AM34: GASTOS TARJETA | AP34: 31.9 | AR34: 46255 | AS34: BIZUM MILBY | AV34: -18.99 | AW34: K
N35: 46105 | O35: PAGO CAJERO | R35: 100 | S35: K | T35: 46137 | U35: OP.NET | X35: 10.8 | Y35: K | Z35: 46162 | AA35: PAGO CAJERO | AD35: 20 | AE35: K | AF35: 46197 | AG35: GASTOS TARJETA | AJ35: 788.39 | AR35: 46257 | AS35: PAGO CAJERO | AV35: 50 | AW35: K
N36: 46106 | O36: AMAIA | R36: 10 | S36: K | T36: 46138 | U36: GASTOS TARJETA | X36: 848.51 | Z36: 46163 | AA36: BIZUM COMPRA | AD36: 10 | AE36: K | AF36: 46203 | AG36: PAGO CAJERO | AJ36: 50 | AK36: K | AR36: 46259 | AS36: PAGO CAJERO | AV36: 50 | AW36: K
N37: 46110 | O37: PAGO CAJERO | R37: 50 | S37: K | T37: 46138 | U37: PAGO CAJERO | X37: 100 | Y37: K | Z37: 46164 | AA37: PAGO CAJERO | AD37: 70 | AE37: K | AR37: 46259 | AS37: PAGO CAJERO | AV37: 50 | AW37: K
N38: 46111 | O38: AMAIA | R38: 11.49 | S38: K | T38: 46138 | U38: BIZUM | V38: BOKATA | X38: 10 | Y38: K | Z38: 46166 | AA38: BIZUM COMPRA | AD38: 20 | AE38: K | AR38: 46261 | AS38: GASTOS TARJETA | AV38: 92.25
N39: 46111 | O39: GASTOS TARJETA | R39: 167.48 | T39: 46140 | U39: GASTOS TARJETA | X39: 28.99 | Z39: 46168 | AA39: BIZUM COMPRA | AD39: 14 | AE39: K | AR39: 46262 | AS39: GASTOS TARJETA | AV39: 17.01
Z40: 46171 | AA40: PAGO CAJERO | AD40: 50 | AE40: K | AR40: 46262 | AS40: PAGO CAJERO | AV40: 50 | AW40: K
Z41: 46172 | AA41: GASTOS TARJETA | AD41: 458.98 | AR41: 46263 | AS41: PAGO CAJERO | AV41: 20 | AW41: K
Z42: 46172 | AA42: PAGO CAJERO | AD42: 50 | AE42: K | AR42: 46264 | AS42: GASTOS TARJETA | AV42: 36.43
F53: =SUM(F22:F52) -> 628.72 | L53: =SUM(L22:L52) -> 1350.38 | R53: =SUM(R22:R52) -> 2188.18 | X53: =SUM(X22:X52) -> 1872.3 | AD53: =SUM(AD22:AD52) -> 2173.43 | AJ53: =SUM(AJ22:AJ52) -> 1503.24 | AP53: =SUM(AP22:AP52) -> 1948.73 | AV53: =SUM(AV22:AV52) -> 1406.57 | BB53: =SUM(BB22:BB52) -> 0 | BH53: =SUM(BH22:BH52) -> 0 | BN53: =SUM(BN22:BN52) -> 0 | BT53: =SUM(BT22:BT52) -> 0
F54: =F53 -> 628.72 | L54: =L53-L38 -> 1350.38 | R54: =R53-R33-R34 -> 1918.18
A56: N26 | B56: ENERO | H56: FEBRERO | N56: MARZO | T56: ABRIL | Z56: MAYO | AF56: JUNIO | AL56: JULIO | AR56: AGOSTO | AX56: SEPTIEMBRE | BD56: OCTUBRE | BJ56: NOVIEMBRE | BP56: DICIEMBRE
B57: DIA | C57: TIENDA | D57: CONCEPTO | E57: CATEGORIA | F57: CANTIDAD | G57: BANCO | H57: DIA | I57: TIENDA | J57: CONCEPTO | K57: CATEGORIA | L57: CANTIDAD | M57: BANCO | N57: DIA | O57: TIENDA | P57: CONCEPTO | Q57: CATEGORIA | R57: CANTIDAD | S57: BANCO | T57: DIA | U57: TIENDA | V57: CONCEPTO | W57: CATEGORIA | X57: CANTIDAD | Y57: BANCO | Z57: DIA | AA57: TIENDA | AB57: CONCEPTO | AC57: CATEGORIA | AD57: CANTIDAD | AE57: BANCO | AF57: DIA | AG57: TIENDA | AH57: CONCEPTO | AI57: CATEGORIA | AJ57: CANTIDAD | AK57: BANCO | AL57: DIA | AM57: TIENDA | AN57: CONCEPTO | AO57: CATEGORIA | AP57: CANTIDAD | AQ57: BANCO | AR57: DIA | AS57: TIENDA | AT57: CONCEPTO | AU57: CATEGORIA | AV57: CANTIDAD | AW57: BANCO | AX57: DIA | AY57: TIENDA | AZ57: CONCEPTO | BA57: CATEGORIA | BB57: CANTIDAD | BC57: BANCO | BD57: DIA | BE57: TIENDA | BF57: CONCEPTO | BG57: CATEGORIA | BH57: CANTIDAD | BI57: BANCO | BJ57: DIA | BK57: TIENDA | BL57: CONCEPTO | BM57: CATEGORIA | BN57: CANTIDAD | BO57: BANCO | BP57: DIA | BQ57: TIENDA | BR57: CONCEPTO | BS57: CATEGORIA | BT57: CANTIDAD | BU57: BANCO
B58: 46038 | C58: MINERVA | D58: PLANTILLAS PODOLOGO YOLI | F58: 145 | G58: N | M58: N | S58: N | Y58: N | AK58: N | AQ58: N | AW58: N | BB58: 500 | BC58: N | BH58: 500 | BI58: N | BN58: 500 | BO58: N | BT58: 500 | BU58: N
B59: 46042 | C59: AMAZON | D59: ENCHUFE UK | F59: 11.99 | G59: K | H59: 46057 | I59: MULTOPTICAS | L59: 94.5 | M59: N | N59: 46104 | O59: OLATZ | R59: 140 | S59: N | T59: 46137 | U59: DELIKIA | X59: 1.05 | Y59: K | Z59: 46148 | AA59: LEROY MERLIN | AD59: 90.62 | AE59: K | AF59: 46179 | AG59: KUTXA | AJ59: 50 | AK59: K | AL59: 46205 | AM59: CAJERO | AP59: 30 | AQ59: K | AR59: 46242 | AS59: EROSKI | AV59: 12.95 | AW59: K
B60: 46045 | C60: TRASPASO REVOLUT | D60: GASTOS LONDRES | F60: 132.34 | G60: K | H60: 46070 | I60: MULTOPTICAS | L60: 97.5 | M60: N | Z60: 46170 | AA60: ARAT | AD60: 185 | AE60: N | AF60: 46182 | AG60: LEROY MERLIN | AJ60: 25.98 | AK60: K | AL60: 46219 | AM60: LEROY MERLIN | AP60: 19.99 | AQ60: K | AR60: 46242 | AS60: ALCAMPO | AV60: 8.26 | AW60: K
B61: 46045 | C61: ARKUPE | F61: 7.8 | G61: K | H61: 46073 | I61: AMAZON | L61: 8.99 | M61: K | Z61: 46171 | AA61: KONTENT | AD61: 31.8 | AE61: K | AF61: 46182 | AG61: DECATHLON | AJ61: 9.99 | AK61: K | AL61: 46222 | AM61: LOOMISP | AN61: ZARAUTZ. DIA GETARIA-ZARAUTZ | AP61: 6.4 | AQ61: K | AR61: 46245 | AS61: CAJERO | AV61: 50 | AW61: K
B62: 46047 | C62: COMIDA INDIO LONDRES | F62: 99.95 | G62: K | AF62: 46184 | AG62: DECATHLON | AJ62: 42.94 | AK62: K | AL62: 46224 | AM62: ALBIE. | AN62: HOSPITAL DONOSTI | AP62: 5.55 | AQ62: K | AR62: 46255 | AS62: CINESA | AV62: 25.8 | AW62: K
B63: 46048 | C63: GAIL´S LONDRES | D63: CAFES | F63: 20.68 | G63: K | AF63: 46184 | AG63: DEPOR | AJ63: 7.5 | AK63: K | AL63: 46224 | AM63: ALBIE. | AN63: HOSPITAL DONOSTI | AP63: 1.6 | AQ63: K | AR63: 46259 | AS63: EROSKI | AV63: 4.05 | AW63: K
B64: 46048 | C64: HONEST BURGUERS | F64: 91.31 | G64: K | AL64: 46225 | AM64: VETERINARIO | AP64: 127 | AQ64: N
B65: 46049 | C65: PRET A MANGER | F65: 23.83 | G65: K | AL65: 46226 | AM65: CAJERO | AP65: 50 | AQ65: K
B66: 46049 | C66: TRASPASO REVOLUT | F66: 11.54 | G66: K | AL66: 46228 | AM66: ALBIE. | AN66: HOSPITAL DONOSTI | AP66: 1.6 | AQ66: K
AL67: 46228 | AM67: ALBIE. | AN67: HOSPITAL DONOSTI | AP67: 1.1 | AQ67: K
AL68: 46229 | AM68: ALBIE. | AN68: HOSPITAL DONOSTI | AP68: 0.95 | AQ68: K
AL69: 46232 | AM69: AMAZON | AP69: 17.77 | AQ69: K
AL70: 46232 | AM70: CAJERO | AP70: 52 | AQ70: K
F75: =SUM(F58:F74) -> 544.44 | L75: =SUM(L58:L74) -> 200.99 | R75: =SUM(R58:R74) -> 140 | X75: =SUM(X58:X74) -> 1.05 | AD75: =SUM(AD58:AD74) -> 307.42 | AJ75: =SUM(AJ58:AJ74) -> 136.41 | AP75: =SUM(AP58:AP74) -> 313.96 | AV75: =SUM(AV58:AV74) -> 101.06 | BB75: =SUM(BB58:BB74) -> 500 | BH75: =SUM(BH58:BH74) -> 500 | BN75: =SUM(BN58:BN74) -> 500 | BT75: =SUM(BT58:BT74) -> 500
F78: =F17+F75+F53 -> 1677.53 | L78: =L17+L75+L53 -> 1573.61 | R78: =R17+R75+R53 -> 3972.32 | X78: =X17+X75+X53 -> 4667.94 | AD78: =AD17+AD75+AD53 -> 2600.1 | AJ78: =AJ17+AJ75+AJ53 -> 2977.95 | AP78: =AP17+AP75+AP53 -> 3450.78 | AV78: =AV17+AV75+AV53 -> 1701.25 | BB78: =BB17+BB75+BB53 -> 500 | BH78: =BH17+BH75+BH53 -> 500 | BN78: =BN17+BN75+BN53 -> 500 | BT78: =BT17+BT75+BT53 -> 500 | BV78: =SUM(F78:BT78) -> 24621.48 | BW78: GASTADO
B81: 46024 | C81: SIMPLY | F81: 16.29 | G81: K | H81: 46032 | I81: BOULEVARD PRIMARK | L81: 40.6 | M81: K | N81: 46083 | O81: PIERRE&VACANCES | R81: 339 | S81: K | T81: 46112 | U81: PIERRE&VACANCES | X81: 13.95 | Y81: K | Z81: 46141 | AA81: BOSSA | AD81: 20.2 | AE81: K | AF81: 46172 | AG81: LIDL | AI81: 94.77 | AJ81: 94.77 | AK81: K | AR81: 46235 | AS81: EROSKI | AV81: 46.74 | AW81: K
B82: 46024 | C82: EROSKI | D82: BALIZA | F82: 39.9 | G82: K | H82: 46032 | I82: DGT MULTA JUANTXO | L82: 50 | M82: K | N82: 46085 | O82: ANCHUSTEGUI | R82: 34.82 | S82: K | T82: 46113 | U82: DIA | X82: 43.23 | Y82: K | Z82: 46142 | AA82: ELORTZA | AC82: 26.74 | AD82: 6.54 | AE82: K | AF82: 46173 | AG82: SHEIN | AJ82: 60.51 | AK82: K | AR82: 46237 | AS82: KULTU | AV82: 5.9 | AW82: K
B83: 46025 | C83: EROSKI | F83: 36.49 | G83: K | H83: 46038 | I83: LEROY MERLIN | L83: 24.28 | M83: K | N83: 46086 | O83: FISIOARIMA | R83: 60 | S83: K | T83: 46113 | U83: FORUM | X83: 39.58 | Y83: K | Z83: 46143 | AA83: MERCACHINA | AD83: 15.85 | AE83: K | AF83: 46175 | AG83: NIRE ORDAINKETA | AJ83: 6.1 | AK83: K | AR83: 46239 | AS83: ÑAM MEGAPARK | AV83: 13.9 | AW83: K
B84: 46025 | C84: ARENAL | F84: 51.9 | G84: K | H84: 46038 | I84: LIDL | L84: 50.87 | M84: K | N84: 46086 | O84: MANGO | R84: 29.93 | S84: K | T84: 46113 | U84: MUNKUKUONA | X84: 9.35 | Y84: K | Z84: 46143 | AA84: ARKUPE | AD84: 11.5 | AE84: K | AF84: 46177 | AG84: PRIMAPRIX | AJ84: 16.95 | AK84: K | AR84: 46239 | AS84: TRAMAS | AV84: 10.98 | AW84: K
B85: 46027 | C85: ASADOR IBAI-ONDO | F85: 38.8 | G85: K | H85: 46043 | I85: LEROY MERLIN | J85: PREMARCO | L85: 34.78 | M85: K | N85: 46091 | O85: ALDI | R85: 19.67 | S85: K | T85: 46113 | U85: EROSKI | X85: 53.88 | Y85: K | Z85: 46144 | AA85: EROSKI | AD85: 49.19 | AE85: K | AF85: 46179 | AG85: LIDL | AJ85: 56.5 | AK85: K | AR85: 46239 | AS85: IKEA | AV85: 27.4 | AW85: K
B86: 46027 | C86: 4X4 | F86: 33.9 | G86: K | H86: 46044 | I86: PRIMAPRIX | L86: 17.95 | M86: K | N86: 46094 | O86: AMAZON | R86: 6.69 | S86: K | T86: 46113 | U86: RKS GARBERA | X86: 50.1 | Y86: K | Z86: 46144 | AA86: PRIMAPRIX | AD86: 10.65 | AE86: K | AF86: 46183 | AG86: EROSKI | AJ86: 13.74 | AK86: K | AR86: 46239 | AS86: MERCADONA | AU86: 122.08 | AV86: 17.16 | AW86: K
B87: 46031 | C87: MERCERIA TXUKUNA | F87: 37 | G87: K | H87: 46045 | I87: EROSKI | L87: 11.71 | M87: K | N87: 46094 | O87: PRIMAPRIX | R87: 24.75 | S87: K | T87: 46114 | U87: SAS MOLIDIS | X87: 62.5 | Y87: K | Z87: 46149 | AA87: GASOLINA | AD87: 50 | AE87: K | AF87: 46186 | AG87: LIDL | AJ87: 39.6 | AK87: K | AR87: 46244 | AS87: FAN ARREGLOS | AT87: PANTALONES OLATZ | AV87: 26 | AW87: K
H88: 46045 | I88: PFOTOPRIX | L88: 29.95 | M88: K | N88: 46095 | O88: DIA | Q88: 566.11 | R88: 51.25 | S88: K | T88: 46114 | U88: AMAZON | X88: 10.99 | Y88: K | Z88: 46150 | AA88: CLAUDE | AD88: 21.78 | AE88: K | AF88: 46188 | AG88: AMAZON | AJ88: 13.66 | AK88: K | AO88: 109.82 | AR88: 46247 | AS88: LIDL | AV88: 31.54 | AW88: K
H89: 46046 | I89: AEROPUERTO BILBO | L89: 16.55 | M89: K | N89: 46095 | O89: VINTED | R89: 15.15 | S89: K | T89: 46116 | U89: CARREFOUR | X89: 35.12 | Y89: K | Z89: 46150 | AA89: ELORTZA | AD89: 60 | AE89: K | AF89: 46190 | AG89: PARFOIS | AJ89: 28.09 | AK89: K | AL89: 46199 | AM89: ZARA | AP89: 36.29 | AQ89: K | AR89: 46248 | AS89: LIDL | AV89: 42.13 | AW89: K
H90: 46049 | I90: BOSSA | L90: 13.8 | M90: K | N90: 46102 | O90: DECATHLON | R90: 71.96 | S90: K | T90: 46117 | U90: FLM023 | X90: 20.08 | Y90: K | Z90: 46151 | AA90: LEROY MERLIN | AD90: 38.52 | AE90: K | AF90: 46190 | AG90: BOSANOVA | AJ90: 47.95 | AK90: K | AL90: 46203 | AM90: MANOMANO | AN90: VENTILADOR | AP90: 129 | AQ90: K | AR90: 46249 | AS90: CINESA | AV90: 22.8 | AW90: K
H91: 46049 | I91: PRIMAPRIX | L91: 12 | M91: K | N91: 46102 | O91: LEROY MERLIN | R91: 18.79 | S91: K | T91: 46117 | U91: AMAZONE CAFÉ | X91: 11.5 | Y91: K | Z91: 46151 | AA91: SIMPLY | AD91: 43.49 | AE91: K | AF91: 46191 | AG91: PRIMAPRIX | AJ91: 40.55 | AK91: K | AL91: 46205 | AM91: AMAZON | AN91: ZAPATILLAS YOLI | AP91: 44.99 | AQ91: K | AR91: 46249 | AS91: C.BOULEVARD | AT91: PINTXOS, CAFÉ Y MOSTO | AU91: 133.22 | AV91: 10.75 | AW91: K
H92: 46049 | I92: EROSKI | L92: 12.86 | M92: K | N92: 46104 | O92: AZKENA | R92: 5.6 | S92: K | T92: 46117 | U92: KARINGA | X92: 26 | Y92: K | Z92: 46151 | AA92: LIDL | AD92: 30.68 | AE92: K | AF92: 46191 | AG92: BURGER HUB | AJ92: 28.58 | AK92: K | AL92: 46206 | AM92: IXUA | AO92: 264.08 | AP92: 53.8 | AQ92: K | AR92: 46250 | AS92: RESTAURANTE LUISA | AV92: 10.2 | AW92: K
H93: 46050 | I93: NUVOLA | L93: 13.1 | M93: K | N93: 46104 | O93: ALDI | R93: 6.05 | S93: K | T93: 46118 | U93: EUSKALDUNA TABERNA | X93: 10.4 | Y93: K | Z93: 46152 | AA93: IXUA | AD93: 10 | AE93: K | AF93: 46192 | AG93: ARTOLA | AJ93: 89.1 | AK93: K | AL93: 46207 | AM93: PRIMARK | AP93: 40.3 | AQ93: K | AR93: 46251 | AS93: BIDE-BIDE | AV93: 8.5 | AW93: K
H94: 46052 | I94: LEROY MERLIN | L94: 121.03 | M94: K | N94: 46108 | O94: FARMACIA CASTAÑO | R94: 21.95 | S94: K | T94: 46118 | U94: ITXAS-LUR | X94: 19.2 | Y94: K | Z94: 46156 | AA94: FARMALUR | AD94: 44.5 | AE94: K | AF94: 46193 | AG94: EROSKI | AJ94: 58.75 | AK94: K | AL94: 46207 | AM94: IKEA | AP94: 25.4 | AQ94: K | AR94: 46251 | AS94: EROSKI | AV94: 7.25 | AW94: K
H95: 46052 | I95: FOTOPRIX | L95: 21.65 | M95: K | N95: 46110 | O95: AMAZON | Q95: 167.48 | R95: 27.98 | S95: K | T95: 46120 | U95: SUSCRIPCION CLAUDE | X95: 21.78 | Y95: K | Z95: 46156 | AA95: PRIMAPRIX | AD95: 41.9 | AE95: K | AF95: 46193 | AG95: MERKAL | AJ95: 62.97 | AK95: K | AL95: 46207 | AM95: LEROY MERLIN | AP95: 26.78 | AQ95: K | AR95: 46252 | AS95: LEROY MERLIN | AV95: 83.9 | AW95: K
H96: 46053 | I96: EROSKI | L96: 51.4 | M96: K | T96: 46123 | U96: LURRE. TIENDA CALBETON | X96: 21 | Y96: K | Z96: 46157 | AA96: AKARA | AC96: 446.76 | AD96: 18.7 | AE96: K | AF96: 46193 | AG96: CALZADOS RIVERO | AJ96: 18 | AK96: K | AL96: 46207 | AM96: MERCADONA | AP96: 53.03 | AQ96: K | AR96: 46252 | AS96: ARBELAITZ | AV96: 9.3 | AW96: K
H97: 46053 | I97: BASQUE STREET FOOD | L97: 24 | M97: K | T97: 46124 | U97: BAZAR MERCACHINA | X97: 6.4 | Y97: K | Z97: 46158 | AA97: LEROY MERLIN | AD97: 28.41 | AE97: K | AF97: 46195 | AG97: AMAZON | AJ97: 158.49 | AK97: K | AL97: 46207 | AM97: ANTHROPIC | AP97: 21.78 | AQ97: K | AR97: 46253 | AS97: AZKENA | AV97: 12.3 | AW97: K
H98: 46053 | I98: LRORY MERLIN | L98: 15.59 | M98: K | T98: 46124 | U98: ARKUPE | X98: 5.1 | Y98: K | Z98: 46158 | AA98: IKEA | AD98: 28.96 | AE98: K | AF98: 46195 | AG98: ALDI | AJ98: 36.36 | AK98: K | AL98: 46208 | AM98: AMAZON | AO98: 182.79 | AP98: 15.5 | AQ98: K | AR98: 46254 | AS98: EROSKI | AU98: 168.92 | AV98: 37.47 | AW98: K
H99: 46053 | I99: BRICO DEPOT | L99: 4.85 | M99: K | T99: 46124 | U99: FARMACIA CASTAÑO | X99: 9.48 | Y99: K | Z99: 46158 | AA99: DONGA | AD99: 24.48 | AE99: K | AF99: 46196 | AG99: PELUQUERIA KALA | AJ99: 75 | AK99: K | AL99: 46211 | AM99: LEROY MERLIN | AP99: 45.87 | AQ99: K | AR99: 46255 | AS99: VIPS GARBERA | AU99: 35.65 | AV99: 35.65 | AW99: K
H100: 46053 | I100: CLAIRE | L100: 10.49 | M100: K | T100: 46134 | U100: AMAZON | X100: 24.79 | Y100: K | Z100: 46158 | AA100: ZARA | AD100: 71.7 | AE100: K | AF100: 46197 | AG100: AMAZON | AJ100: 9.99 | AK100: K | AL100: 46211 | AM100: DECATHLON | AP100: 51.96 | AQ100: K | AR100: 46256 | AS100: LIDL | AV100: 20.72 | AW100: K
H101: 46053 | I101: EROSKI | K101: 585.13 | L101: 7.67 | M101: K | T101: 46136 | U101: ANCHUSTEGUI | X101: 47.94 | Y101: K | Z101: 46158 | AA101: LIDL | AD101: 47.01 | AE101: K | AF101: 46197 | AG101: NIRE ORDAINKETA | AJ101: 3 | AK101: K | AL101: 46211 | AM101: SIMPLY | AP101: 32.42 | AQ101: K | AR101: 46258 | AS101: HOSPITAL | AV101: 0.95 | AW101: K
H102: 46053 | I102: PRIMARK | L102: 30.65 | M102: K | T102: 46136 | U102: TXOKO | X102: 3.8 | Y102: K | Z102: 46158 | AA102: MERCADONA | AD102: 28.9 | AE102: K | AF102: 46197 | AG102: NIRE ORDAINKETA | AJ102: 3 | AK102: K | AL102: 46215 | AM102: HOSPITAL | AN102: COMIDA | AP102: 16.65 | AQ102: K | AR102: 46258 | AS102: HOSPITAL | AV102: 1.2 | AW102: K
H103: 46056 | I103: FARMACIA CASTAÑO | L103: 5.79 | M103: K | T103: 46137 | U103: DIA | X103: 39.63 | Y103: K | Z103: 46159 | AA103: DEPOR | AD103: 20.3 | AE103: K | AF103: 46198 | AG103: OSATE | AH103: CAMPING OCHAGABIA | AJ103: 143 | AK103: K | AL103: 46220 | AM103: IZADI LORADENDA | AP103: 43.5 | AQ103: K | AR103: 46259 | AS103: TXOKO | AV103: 11.15 | AW103: K
H104: 46056 | I104: RESTAURANTE TXINPARTA | L104: 9.85 | M104: K | T104: 46137 | U104: LEROY MERLIN | W104: 848.51 | X104: 262.71 | Y104: K | Z104: 46164 | AA104: ALDI | AD104: 23.19 | AE104: K | AF104: 46198 | AG104: OSATE | AH104: CAMPING OCHAGABIA | AI104: 155.28 | AJ104: 32.1 | AK104: K | AL104: 46221 | AM104: EXPRESS CAFETERIA | AP104: 10.9 | AQ104: K | AR104: 46259 | AS104: EROSKI | AU104: 92.25 | AV104: 58.23 | AW104: K
H105: 46056 | I105: EROSKI | L105: 10.27 | M105: K | T105: 46139 | U105: AMAZON | X105: 28.99 | Y105: K | Z105: 46164 | AA105: FRUTERIA ZELAIA | AD105: 12.11 | AE105: K | AF105: 46201 | AG105: REST IRU.BIDE | AH105: ALSASUA | AI105: 788.39 | AJ105: 11.5 | AK105: K | AL105: 46221 | AM105: FNAC | AP105: 33.99 | AQ105: K | AR105: 46261 | AS105: ANCHUSTEGUI | AU105: 17.01 | AV105: 17.01 | AW105: K
H106: 46057 | I106: DIA | L106: 17.06 | M106: K | Z106: 46165 | AA106: LIDL | AD106: 63.82 | AE106: K | AL106: 46221 | AM106: CASA DEL LIBRO | AP106: 34.15 | AQ106: K | AR106: 46262 | AS106: KIOSKO UNZAGA | AV106: 12 | AW106: K
H107: 46060 | I107: NATURA | L107: 22 | M107: K | Z107: 46168 | AA107: WOMEN SECRET | AD107: 31.35 | AE107: K | AL107: 46221 | AM107: BAR TOLOSA | AP107: 50 | AQ107: K | AR107: 46263 | AS107: EROSKI | AV107: 16.38 | AW107: K
H108: 46060 | I108: KRUNCH | L108: 26.9 | M108: K | Z108: 46169 | AA108: TEMU | AD108: 54.25 | AE108: K | AL108: 46221 | AM108: LIDL | AO108: 343.96 | AP108: 24.52 | AQ108: K | AR108: 46263 | AS108: EROSKI | AU108: 36.43 | AV108: 8.05 | AW108: K
H109: 46060 | I109: BM | L109: 5.71 | M109: K | Z109: 46170 | AA109: PRIMAPRIX | AC109: 458.98 | AD109: 24.5 | AE109: K | AL109: 46222 | AM109: CLAUDE | AN109: DEVOLUCION | AP109: -21.78 | AQ109: K
H110: 46060 | I110: LEROY MERLIN | L110: 12.54 | M110: K | AL110: 46223 | AM110: FOTOPRIX | AP110: 24.96 | AQ110: K
H111: 46060 | I111: LIDL | L111: 26.4 | M111: K | AL111: 46224 | AM111: PRIMAPRIX | AP111: 11.15 | AQ111: K
H112: 46061 | I112: KRONOAK | L112: 110 | M112: K | AL112: 46228 | AM112: MERCATO | AP112: 7.8 | AQ112: K
H113: 46064 | I113: ANCHUSTEGUI | L113: 39.2 | M113: K | AL113: 46229 | AM113: PARKING LUMBIER | AO113: 25.13 | AP113: 3 | AQ113: K
H114: 46071 | I114: LIDL | L114: 8.53 | M114: K | AL114: 46231 | AM114: EROSKI | AO114: 54.99 | AP114: 54.99 | AQ114: K
H115: 46075 | I115: KRONOAK | L115: 55 | M115: K | AL115: 46233 | AM115: PRIMAPRIX | AO115: 31.9 | AP115: 31.9 | AQ115: K
H116: 46081 | I116: EROSKI | L116: 62.16 | M116: K
H117: 46081 | I117: MILBBY | L117: 30.77 | M117: K
H118: 46081 | I118: KOROSHI | K118: 559.1 | L118: 86.27 | M118: K
E119: =SUM(E81:E118) -> 0 | K119: =SUM(K81:K118) -> 1144.23 | Q119: =SUM(Q81:Q117) -> 733.59 | W119: =SUM(W81:W117) -> 848.51 | AC119: =SUM(AC81:AC117) -> 932.48 | AI119: =SUM(AI113:AI118) -> 0 | AO119: =SUM(AO92:AO118) -> 902.85 | AU119: =SUM(AU81:AU118) -> 605.56
C124: GASTOS TARJETA | E124: =SUMIF(C22:C50,C124,F22:F50) -> 271.72 | I124: GASTOS TARJETA | K124: =SUMIF(I22:I50,I124,L22:L50) -> 585.13 | O124: GASTOS TARJETA | Q124: =SUMIF(O22:O50,O124,R22:R50) -> 1292.69 | U124: GASTOS TARJETA | W124: =SUMIF(U22:U52,U124,X22:X52) -> 877.5 | AA124: GASTOS TARJETA | AC124: =SUMIF(AA22:AA52,AA124,AD22:AD52) -> 932.48 | AG124: GASTOS TARJETA | AI124: =SUMIF(AG22:AG52,AG124,AJ22:AJ52) -> 1038.44 | AM124: GASTOS TARJETA | AO124: =SUMIF(AM22:AM52,AM124,AP22:AP52) -> 1012.67 | AS124: GASTOS TARJETA | AU124: =SUMIF(AS22:AS52,AS124,AV22:AV52) -> 605.56 | AY124: GASTOS TARJETA | BA124: =SUMIF(AY22:AY52,AY124,BB22:BB52) -> 0 | BE124: GASTOS TARJETA | BG124: =SUMIF(BE22:BE52,BE124,BH22:BH52) -> 0 | BK124: GASTOS TARJETA | BM124: =SUMIF(BK22:BK52,BK124,BN22:BN52) -> 0 | BQ124: GASTOS TARJETA | BS124: =SUMIF(BQ22:BQ52,BQ124,BT22:BT52) -> 0
C125: AMAZON | E125: =SUMIF(C81:C117,"AMAZON",E81:E117) -> 0 | I125: AMAZON | K125: =SUMIF(I81:I117,"AMAZON",K81:K117) -> 0 | O125: AMAZON | Q125: =SUMIF(O81:O117,"AMAZON",Q81:Q117) -> 167.48 | U125: AMAZON | W125: =SUMIF(U81:U117,"AMAZON",W81:W117) -> 0 | AA125: AMAZON | AC125: =SUMIF(AA81:AA117,"AMAZON",AC81:AC117) -> 0 | AG125: AMAZON | AI125: =SUMIF(AG81:AG117,"AMAZON",AI81:AI117) -> 0 | AM125: AMAZON | AO125: =SUMIF(AM81:AM117,"AMAZON",AO81:AO117) -> 182.79 | AS125: AMAZON | AU125: =SUMIF(AS81:AS117,"AMAZON",AU81:AU117) -> 0 | AY125: AMAZON | BA125: =SUMIF(AY81:AY117,"AMAZON",BA81:BA117) -> 0 | BE125: AMAZON | BG125: =SUMIF(BE81:BE117,"AMAZON",BG81:BG117) -> 0 | BK125: AMAZON | BM125: =SUMIF(BK81:BK117,"AMAZON",BM81:BM117) -> 0 | BQ125: AMAZON | BS125: =SUMIF(BQ81:BQ117,"AMAZON",BS81:BS117) -> 0
C126: G.TARJETA SIN AMAZON | E126: =E124-E125 -> 271.72 | I126: G.TARJETA SIN AMAZON | K126: =K124-K125 -> 585.13 | O126: G.TARJETA SIN AMAZON | Q126: =Q124-Q125 -> 1125.21 | U126: G.TARJETA SIN AMAZON | W126: =W124-W125 -> 877.5 | AA126: G.TARJETA SIN AMAZON | AC126: =AC124-AC125 -> 932.48
C127: PAGO CAJERO | E127: =SUMIF(C22:C52,"PAGO CAJERO",F22:F52) -> 400 | I127: PAGO CAJERO | K127: =SUMIF(I22:I52,"PAGO CAJERO",L22:L52) -> 640 | O127: PAGO CAJERO | Q127: =SUMIF(O22:O52,"PAGO CAJERO",R22:R52) -> 770 | U127: PAGO CAJERO | W127: =SUMIF(U22:U52,"PAGO CAJERO",X22:X52) -> 600 | AA127: PAGO CAJERO | AC127: =SUMIF(AA22:AA52,"PAGO CAJERO",AD22:AD52) -> 490 | AG127: PAGO CAJERO | AI127: =SUMIF(AG22:AG52,"PAGO CAJERO",AJ22:AJ52) -> 550 | AM127: PAGO CAJERO | AO127: =SUMIF(AM22:AM52,"PAGO CAJERO",AP22:AP52) -> 230 | AS127: PAGO CAJERO | AU127: =SUMIF(AS22:AS52,"PAGO CAJERO",AV22:AV52) -> 820 | AY127: PAGO CAJERO | BA127: =SUMIF(AY22:AY52,"PAGO CAJERO",BB22:BB52) -> 0 | BE127: PAGO CAJERO | BG127: =SUMIF(BE22:BE52,"PAGO CAJERO",BH22:BH52) -> 0 | BK127: PAGO CAJERO | BM127: =SUMIF(BK22:BK52,"PAGO CAJERO",BN22:BN52) -> 0 | BQ127: PAGO CAJERO | BS127: =SUMIF(BQ22:BQ52,"PAGO CAJERO",BT22:BT52) -> 0
C129: GASTOS PARA N26 | E129: =SUMIF(G:G,"N",F:F)-F58 -> 0 | I129: GASTOS PARA N26 | K129: =SUMIF(M:M,"N",L:L) -> 192 | O129: GASTOS PARA N26 | Q129: =SUMIF(S:S,"N",R:R) -> 140 | U129: GASTOS PARA N26 | W129: =SUMIF(Y:Y,"N",X:X) -> 0 | AA129: GASTOS PARA N26 | AC129: =SUMIF(AE:AE,"N",AD:AD) -> 185 | AG129: GASTOS PARA N26 | AI129: =SUMIF(AK:AK,"N",AJ:AJ) -> 0 | AM129: GASTOS PARA N26 | AO129: =SUMIF(AQ:AQ,"N",AP:AP) -> 127 | AS129: GASTOS PARA N26 | AU129: =SUMIF(AW:AW,"N",AV:AV) -> 0 | AY129: GASTOS PARA N26 | BA129: =SUMIF(BC:BC,"N",BB:BB) -> 500 | BE129: GASTOS PARA N26 | BG129: =SUMIF(BI:BI,"N",BH:BH) -> 500 | BK129: GASTOS PARA N26 | BM129: =SUMIF(BO:BO,"N",BN:BN) -> 500 | BQ129: GASTOS PARA N26 | BS129: =SUMIF(BU:BU,"N",BT:BT) -> 500 | BV129: =BS129+BM129+BG129+BA129+AU129+AO129+AI129+AC129+W129+Q129+K129+E129 -> 2644
C130: GASTOS PARA KUTXA | E130: =SUMIF(G:G,"K",F:F) -> 1169.85 | I130: GASTOS PARA KUTXA | K130: =SUMIF(M:M,"K",L:L) -> 1918.47 | O130: GASTOS PARA KUTXA | Q130: =SUMIF(S:S,"K",R:R) -> 1667.22 | U130: GASTOS PARA KUTXA | W130: =SUMIF(Y:Y,"K",X:X) -> 1967.94 | AA130: GASTOS PARA KUTXA | AC130: =SUMIF(AE:AE,"K",AD:AD) -> 2295.85 | AG130: GASTOS PARA KUTXA | AI130: =SUMIF(AK:AK,"K",AJ:AJ) -> 1749.47 | AM130: GASTOS PARA KUTXA | AO130: =SUMIF(AQ:AQ,"K",AP:AP) -> 2025.87 | AS130: GASTOS PARA KUTXA | AU130: =SUMIF(AW:AW,"K",AV:AV) -> 1626.91 | AY130: GASTOS PARA KUTXA | BA130: =SUMIF(BC:BC,"K",BB:BB) -> 0 | BE130: GASTOS PARA KUTXA | BG130: =SUMIF(BI:BI,"K",BH:BH) -> 0 | BK130: GASTOS PARA KUTXA | BM130: =SUMIF(BO:BO,"K",BN:BN) -> 0 | BQ130: GASTOS PARA KUTXA | BS130: =SUMIF(BU:BU,"K",BT:BT) -> 0 | BV130: =BS130+BM130+BG130+BA130+AU130+AO130+AI130+AC130+W130+Q130+K130+E130 -> 14421.58
...

Sheet ESCENARIOS
H1: 2025 | I1: 2026 | J1: 2027
H2: CON HIPOTECA SIN PRESTAMO CON LOCAL URKI BAJO CON ALQUILER VITORIA | K2: CON HIPOTECA CON PRESTAMO CON LOCAL URKI BAJO SIN ALQUILER VITORIA SIN TRASPORTE/SIN MATRICULAS | N2: SIN HIPOTECA SIN PRESTAMO CON LOCAL URKI BAJO SIN ALQUILER VITORIA SIN TRASPORTE/SIN MATRICULAS | Q2: CON HIPOTECA SIN PRESTAMO SIN LOCAL URKI BAJO CON ALQUILER VITORIA | T2: CON HIPOTECA SIN PRESTAMO SIN LOCAL URKI BAJO SIN ALQUILER VITORIA
A7: NOMINA JULIO | D7: 2300 | E7: MENSUAL | F7: =IF($E7="MENSUAL",$D7,IF($E7="TRIMESTRAL",$D7/3,IF($E7="SEMESTRAL",$D7/2,IF($E7="ANUAL",$D7/12,IF($E7="BIMENSUAL",$D7/2))))) -> 2300 | I7: =IF($E7="MENSUAL",$D7,IF($E7="TRIMESTRAL",$D7/3,IF($E7="SEMESTRAL",$D7/2,IF($E7="ANUAL",$D7/12,IF($E7="BIMENSUAL",$D7/2))))) -> 2300 | L7: =IF($E7="MENSUAL",$D7,IF($E7="TRIMESTRAL",$D7/3,IF($E7="SEMESTRAL",$D7/2,IF($E7="ANUAL",$D7/12,IF($E7="BIMENSUAL",$D7/2))))) -> 2300 | O7: =IF($E7="MENSUAL",$D7,IF($E7="TRIMESTRAL",$D7/3,IF($E7="SEMESTRAL",$D7/2,IF($E7="ANUAL",$D7/12,IF($E7="BIMENSUAL",$D7/2))))) -> 2300 | R7: =IF($E7="MENSUAL",$D7,IF($E7="TRIMESTRAL",$D7/3,IF($E7="SEMESTRAL",$D7/2,IF($E7="ANUAL",$D7/12,IF($E7="BIMENSUAL",$D7/2))))) -> 2300 | U7: =IF($E7="MENSUAL",$D7,IF($E7="TRIMESTRAL",$D7/3,IF($E7="SEMESTRAL",$D7/2,IF($E7="ANUAL",$D7/12,IF($E7="BIMENSUAL",$D7/2))))) -> 2300
A8: PAGA VERANO | D8: 1900 | E8: ANUAL | F8: =IF($E8="MENSUAL",$D8,IF($E8="TRIMESTRAL",$D8/3,IF($E8="SEMESTRAL",$D8/2,IF($E8="ANUAL",$D8/12,IF($E8="BIMENSUAL",$D8/2))))) -> 158.33333 | I8: =IF($E8="MENSUAL",$D8,IF($E8="TRIMESTRAL",$D8/3,IF($E8="SEMESTRAL",$D8/2,IF($E8="ANUAL",$D8/12,IF($E8="BIMENSUAL",$D8/2))))) -> 158.33333 | L8: =IF($E8="MENSUAL",$D8,IF($E8="TRIMESTRAL",$D8/3,IF($E8="SEMESTRAL",$D8/2,IF($E8="ANUAL",$D8/12,IF($E8="BIMENSUAL",$D8/2))))) -> 158.33333 | O8: =IF($E8="MENSUAL",$D8,IF($E8="TRIMESTRAL",$D8/3,IF($E8="SEMESTRAL",$D8/2,IF($E8="ANUAL",$D8/12,IF($E8="BIMENSUAL",$D8/2))))) -> 158.33333 | R8: =IF($E8="MENSUAL",$D8,IF($E8="TRIMESTRAL",$D8/3,IF($E8="SEMESTRAL",$D8/2,IF($E8="ANUAL",$D8/12,IF($E8="BIMENSUAL",$D8/2))))) -> 158.33333 | U8: =IF($E8="MENSUAL",$D8,IF($E8="TRIMESTRAL",$D8/3,IF($E8="SEMESTRAL",$D8/2,IF($E8="ANUAL",$D8/12,IF($E8="BIMENSUAL",$D8/2))))) -> 158.33333
A9: PAGA NAVIDAD | D9: 1900 | E9: ANUAL | F9: =IF($E9="MENSUAL",$D9,IF($E9="TRIMESTRAL",$D9/3,IF($E9="SEMESTRAL",$D9/2,IF($E9="ANUAL",$D9/12,IF($E9="BIMENSUAL",$D9/2))))) -> 158.33333 | I9: =IF($E9="MENSUAL",$D9,IF($E9="TRIMESTRAL",$D9/3,IF($E9="SEMESTRAL",$D9/2,IF($E9="ANUAL",$D9/12,IF($E9="BIMENSUAL",$D9/2))))) -> 158.33333 | L9: =IF($E9="MENSUAL",$D9,IF($E9="TRIMESTRAL",$D9/3,IF($E9="SEMESTRAL",$D9/2,IF($E9="ANUAL",$D9/12,IF($E9="BIMENSUAL",$D9/2))))) -> 158.33333 | O9: =IF($E9="MENSUAL",$D9,IF($E9="TRIMESTRAL",$D9/3,IF($E9="SEMESTRAL",$D9/2,IF($E9="ANUAL",$D9/12,IF($E9="BIMENSUAL",$D9/2))))) -> 158.33333 | R9: =IF($E9="MENSUAL",$D9,IF($E9="TRIMESTRAL",$D9/3,IF($E9="SEMESTRAL",$D9/2,IF($E9="ANUAL",$D9/12,IF($E9="BIMENSUAL",$D9/2))))) -> 158.33333 | U9: =IF($E9="MENSUAL",$D9,IF($E9="TRIMESTRAL",$D9/3,IF($E9="SEMESTRAL",$D9/2,IF($E9="ANUAL",$D9/12,IF($E9="BIMENSUAL",$D9/2))))) -> 158.33333
A10: NOMINA YOLI | D10: 2350 | E10: MENSUAL | F10: =IF($E10="MENSUAL",$D10,IF($E10="TRIMESTRAL",$D10/3,IF($E10="SEMESTRAL",$D10/2,IF($E10="ANUAL",$D10/12,IF($E10="BIMENSUAL",$D10/2))))) -> 2350 | I10: =IF($E10="MENSUAL",$D10,IF($E10="TRIMESTRAL",$D10/3,IF($E10="SEMESTRAL",$D10/2,IF($E10="ANUAL",$D10/12,IF($E10="BIMENSUAL",$D10/2))))) -> 2350 | L10: =IF($E10="MENSUAL",$D10,IF($E10="TRIMESTRAL",$D10/3,IF($E10="SEMESTRAL",$D10/2,IF($E10="ANUAL",$D10/12,IF($E10="BIMENSUAL",$D10/2))))) -> 2350 | O10: =IF($E10="MENSUAL",$D10,IF($E10="TRIMESTRAL",$D10/3,IF($E10="SEMESTRAL",$D10/2,IF($E10="ANUAL",$D10/12,IF($E10="BIMENSUAL",$D10/2))))) -> 2350 | R10: =IF($E10="MENSUAL",$D10,IF($E10="TRIMESTRAL",$D10/3,IF($E10="SEMESTRAL",$D10/2,IF($E10="ANUAL",$D10/12,IF($E10="BIMENSUAL",$D10/2))))) -> 2350 | U10: =IF($E10="MENSUAL",$D10,IF($E10="TRIMESTRAL",$D10/3,IF($E10="SEMESTRAL",$D10/2,IF($E10="ANUAL",$D10/12,IF($E10="BIMENSUAL",$D10/2))))) -> 2350
A11: HACIENDA | D11: 4000 | E11: ANUAL | F11: =IF($E11="MENSUAL",$D11,IF($E11="TRIMESTRAL",$D11/3,IF($E11="SEMESTRAL",$D11/2,IF($E11="ANUAL",$D11/12,IF($E11="BIMENSUAL",$D11/2))))) -> 333.33333 | I11: =IF($E11="MENSUAL",$D11,IF($E11="TRIMESTRAL",$D11/3,IF($E11="SEMESTRAL",$D11/2,IF($E11="ANUAL",$D11/12,IF($E11="BIMENSUAL",$D11/2))))) -> 333.33333 | L11: =IF($E11="MENSUAL",$D11,IF($E11="TRIMESTRAL",$D11/3,IF($E11="SEMESTRAL",$D11/2,IF($E11="ANUAL",$D11/12,IF($E11="BIMENSUAL",$D11/2))))) -> 333.33333 | O11: =IF($E11="MENSUAL",$D11,IF($E11="TRIMESTRAL",$D11/3,IF($E11="SEMESTRAL",$D11/2,IF($E11="ANUAL",$D11/12,IF($E11="BIMENSUAL",$D11/2))))) -> 333.33333 | R11: =IF($E11="MENSUAL",$D11,IF($E11="TRIMESTRAL",$D11/3,IF($E11="SEMESTRAL",$D11/2,IF($E11="ANUAL",$D11/12,IF($E11="BIMENSUAL",$D11/2))))) -> 333.33333 | U11: =IF($E11="MENSUAL",$D11,IF($E11="TRIMESTRAL",$D11/3,IF($E11="SEMESTRAL",$D11/2,IF($E11="ANUAL",$D11/12,IF($E11="BIMENSUAL",$D11/2))))) -> 333.33333
A12: GESTION COMUNIDAD | D12: 0 | E12: ANUAL | F12: =IF($E12="MENSUAL",$D12,IF($E12="TRIMESTRAL",$D12/3,IF($E12="SEMESTRAL",$D12/2,IF($E12="ANUAL",$D12/12,IF($E12="BIMENSUAL",$D12/2))))) -> 0 | I12: =IF($E12="MENSUAL",$D12,IF($E12="TRIMESTRAL",$D12/3,IF($E12="SEMESTRAL",$D12/2,IF($E12="ANUAL",$D12/12,IF($E12="BIMENSUAL",$D12/2))))) -> 0 | L12: =IF($E12="MENSUAL",$D12,IF($E12="TRIMESTRAL",$D12/3,IF($E12="SEMESTRAL",$D12/2,IF($E12="ANUAL",$D12/12,IF($E12="BIMENSUAL",$D12/2))))) -> 0 | O12: =IF($E12="MENSUAL",$D12,IF($E12="TRIMESTRAL",$D12/3,IF($E12="SEMESTRAL",$D12/2,IF($E12="ANUAL",$D12/12,IF($E12="BIMENSUAL",$D12/2))))) -> 0 | R12: =IF($E12="MENSUAL",$D12,IF($E12="TRIMESTRAL",$D12/3,IF($E12="SEMESTRAL",$D12/2,IF($E12="ANUAL",$D12/12,IF($E12="BIMENSUAL",$D12/2))))) -> 0 | U12: =IF($E12="MENSUAL",$D12,IF($E12="TRIMESTRAL",$D12/3,IF($E12="SEMESTRAL",$D12/2,IF($E12="ANUAL",$D12/12,IF($E12="BIMENSUAL",$D12/2))))) -> 0
F13: =SUM(F7:F12) -> 5300 | I13: =SUM(I7:I12) -> 5300 | J13: =I13*12 -> 63600 | L13: =SUM(L7:L12) -> 5300 | M13: =L13*12 -> 63600 | O13: =SUM(O7:O12) -> 5300 | P13: =O13*12 -> 63600 | R13: =SUM(R7:R12) -> 5300 | S13: =R13*12 -> 63600 | U13: =SUM(U7:U12) -> 5300 | V13: =U13*12 -> 63600
C15: GASTOS | I15: =SUMIF($C$41:$C$126,$C15,$I$41:$I$126) -> 1400 | J15: =-(F15-I15) -> 1400 | L15: =SUMIF($C$41:$C$126,$C15,$L$41:$L$126) -> 1400 | M15: =-(I15-L15) -> 0 | O15: =SUMIF($C$41:$C$126,$C15,$O$41:$O$126) -> 1400 | P15: =-(I15-O15) -> 0 | R15: =SUMIF($C$41:$C$126,$C15,$R$41:$R$126) -> 1400 | S15: =-(I15-R15) -> 0 | U15: =SUMIF($C$41:$C$126,$C15,$U$41:$U$126) -> 1400 | V15: =-(I15-U15) -> 0
C16: HIPOTECA | I16: =SUMIF($C$41:$C$126,$C16,$I$41:$I$126) -> 810 | J16: =-(F16-I16) -> 810 | L16: =SUMIF($C$41:$C$126,$C16,$L$41:$L$126) -> 810 | M16: =-(I16-L16) -> 0 | O16: =SUMIF($C$41:$C$126,$C16,$O$41:$O$126) -> 0 | P16: =-(I16-O16) -> -810 | R16: =SUMIF($C$41:$C$126,$C16,$R$41:$R$126) -> 810 | S16: =-(I16-R16) -> 0 | U16: =SUMIF($C$41:$C$126,$C16,$U$41:$U$126) -> 810 | V16: =-(I16-U16) -> 0
C17: AHORRO | I17: =SUMIF($C$41:$C$126,$C17,$I$41:$I$126) -> 0 | J17: =-(F17-I17) -> 0 | L17: =SUMIF($C$41:$C$126,$C17,$L$41:$L$126) -> 0 | M17: =-(I17-L17) -> 0 | O17: =SUMIF($C$41:$C$126,$C17,$O$41:$O$126) -> 0 | P17: =-(I17-O17) -> 0 | R17: =SUMIF($C$41:$C$126,$C17,$R$41:$R$126) -> 0 | S17: =-(I17-R17) -> 0 | U17: =SUMIF($C$41:$C$126,$C17,$U$41:$U$126) -> 0 | V17: =-(I17-U17) -> 0
C18: PRESTAMO | I18: =SUMIF($C$41:$C$126,$C18,$I$41:$I$126) -> 500 | J18: =-(F18-I18) -> 500 | L18: =SUMIF($C$41:$C$126,$C18,$L$41:$L$126) -> 500 | M18: =-(I18-L18) -> 0 | O18: =SUMIF($C$41:$C$126,$C18,$O$41:$O$126) -> 0 | P18: =-(I18-O18) -> -500 | R18: =SUMIF($C$41:$C$126,$C18,$R$41:$R$126) -> 0 | S18: =-(I18-R18) -> -500 | U18: =SUMIF($C$41:$C$126,$C18,$U$41:$U$126) -> 0 | V18: =-(I18-U18) -> -500
C19: CASA | I19: =SUMIF($C$41:$C$126,$C19,$I$41:$I$126) -> 391.58 | J19: =-(F19-I19) -> 391.58 | L19: =SUMIF($C$41:$C$126,$C19,$L$41:$L$126) -> 391.58 | M19: =-(I19-L19) -> 0 | O19: =SUMIF($C$41:$C$126,$C19,$O$41:$O$126) -> 391.58 | P19: =-(I19-O19) -> 0 | R19: =SUMIF($C$41:$C$126,$C19,$R$41:$R$126) -> 391.58 | S19: =-(I19-R19) -> 0 | U19: =SUMIF($C$41:$C$126,$C19,$U$41:$U$126) -> 391.58 | V19: =-(I19-U19) -> 0
C20: ESTUDIOS | I20: =SUMIF($C$41:$C$126,$C20,$I$41:$I$126) -> 258.33333 | J20: =-(F20-I20) -> 258.33333 | L20: =SUMIF($C$41:$C$126,$C20,$L$41:$L$126) -> 258.33333 | M20: =-(I20-L20) -> 0 | O20: =SUMIF($C$41:$C$126,$C20,$O$41:$O$126) -> 0 | P20: =-(I20-O20) -> -258.33333 | R20: =SUMIF($C$41:$C$126,$C20,$R$41:$R$126) -> 258.33333 | S20: =-(I20-R20) -> 0 | U20: =SUMIF($C$41:$C$126,$C20,$U$41:$U$126) -> 258.33333 | V20: =-(I20-U20) -> 0
C21: SINDICATO | I21: =SUMIF($C$41:$C$126,$C21,$I$41:$I$126) -> 20.58 | J21: =-(F21-I21) -> 20.58 | L21: =SUMIF($C$41:$C$126,$C21,$L$41:$L$126) -> 20.58 | M21: =-(I21-L21) -> 0 | O21: =SUMIF($C$41:$C$126,$C21,$O$41:$O$126) -> 20.58 | P21: =-(I21-O21) -> 0 | R21: =SUMIF($C$41:$C$126,$C21,$R$41:$R$126) -> 20.58 | S21: =-(I21-R21) -> 0 | U21: =SUMIF($C$41:$C$126,$C21,$U$41:$U$126) -> 20.58 | V21: =-(I21-U21) -> 0
C22: COCHE | I22: =SUMIF($C$41:$C$126,$C22,$I$41:$I$126) -> 149.16667 | J22: =-(F22-I22) -> 149.16667 | L22: =SUMIF($C$41:$C$126,$C22,$L$41:$L$126) -> 149.16667 | M22: =-(I22-L22) -> 0 | O22: =SUMIF($C$41:$C$126,$C22,$O$41:$O$126) -> 149.16667 | P22: =-(I22-O22) -> 0 | R22: =SUMIF($C$41:$C$126,$C22,$R$41:$R$126) -> 149.16667 | S22: =-(I22-R22) -> 0 | U22: =SUMIF($C$41:$C$126,$C22,$U$41:$U$126) -> 149.16667 | V22: =-(I22-U22) -> 0
C23: TRANSPORTE | I23: =SUMIF($C$41:$C$126,$C23,$I$41:$I$126) -> 250 | J23: =-(F23-I23) -> 250 | L23: =SUMIF($C$41:$C$126,$C23,$L$41:$L$126) -> 250 | M23: =-(I23-L23) -> 0 | O23: =SUMIF($C$41:$C$126,$C23,$O$41:$O$126) -> 50 | P23: =-(I23-O23) -> -200 | R23: =SUMIF($C$41:$C$126,$C23,$R$41:$R$126) -> 250 | S23: =-(I23-R23) -> 0 | U23: =SUMIF($C$41:$C$126,$C23,$U$41:$U$126) -> 250 | V23: =-(I23-U23) -> 0
C24: OCIO | I24: =SUMIF($C$41:$C$126,$C24,$I$41:$I$126) -> 113.41667 | J24: =-(F24-I24) -> 113.41667 | L24: =SUMIF($C$41:$C$126,$C24,$L$41:$L$126) -> 113.41667 | M24: =-(I24-L24) -> 0 | O24: =SUMIF($C$41:$C$126,$C24,$O$41:$O$126) -> 98.75 | P24: =-(I24-O24) -> -14.666667 | R24: =SUMIF($C$41:$C$126,$C24,$R$41:$R$126) -> 113.41667 | S24: =-(I24-R24) -> 0 | U24: =SUMIF($C$41:$C$126,$C24,$U$41:$U$126) -> 113.41667 | V24: =-(I24-U24) -> 0
C25: LOCALES | I25: =SUMIF($C$41:$C$126,$C25,$I$41:$I$126) -> 58.083333 | J25: =-(F25-I25) -> 58.083333 | L25: =SUMIF($C$41:$C$126,$C25,$L$41:$L$126) -> 58.083333 | M25: =-(I25-L25) -> 0 | O25: =SUMIF($C$41:$C$126,$C25,$O$41:$O$126) -> 58.083333 | P25: =-(I25-O25) -> 0 | R25: =SUMIF($C$41:$C$126,$C25,$R$41:$R$126) -> 0 | S25: =-(I25-R25) -> -58.083333 | U25: =SUMIF($C$41:$C$126,$C25,$U$41:$U$126) -> 0 | V25: =-(I25-U25) -> -58.083333
C26: INVERSION | I26: =SUMIF($C$41:$C$126,$C26,$I$41:$I$126) -> 64 | J26: =-(F26-I26) -> 64 | L26: =SUMIF($C$41:$C$126,$C26,$L$41:$L$126) -> 64 | M26: =-(I26-L26) -> 0 | O26: =SUMIF($C$41:$C$126,$C26,$O$41:$O$126) -> 64 | P26: =-(I26-O26) -> 0 | R26: =SUMIF($C$41:$C$126,$C26,$R$41:$R$126) -> 64 | S26: =-(I26-R26) -> 0 | U26: =SUMIF($C$41:$C$126,$C26,$U$41:$U$126) -> 64 | V26: =-(I26-U26) -> 0
... C34: SALUD | I34: =SUMIF($C$41:$C$126,$C34,$I$41:$I$126) -> 83.333333 | J34: =-(F34-I34) -> 83.333333 | L34: =SUMIF($C$41:$C$126,$C34,$L$41:$L$126) -> 83.333333 | M34: =-(I34-L34) -> 0 | O34: =SUMIF($C$41:$C$126,$C34,$O$41:$O$126) -> 83.333333 | P34: =-(I34-O34) -> 0 | R34: =SUMIF($C$41:$C$126,$C34,$R$41:$R$126) -> 83.333333 | S34: =-(I34-R34) -> 0 | U34: =SUMIF($C$41:$C$126,$C34,$U$41:$U$126) -> 83.333333 | V34: =-(I34-U34) -> 0
I35: =SUBTOTAL(9,I15:I34) -> 4973.4933 | J35: =I35*12 -> 59681.92 | L35: =SUBTOTAL(9,L15:L34) -> 4973.4933 | M35: =L35*12 -> 59681.92 | O35: =SUBTOTAL(9,O15:O34) -> 2915.4933 | P35: =O35*12 -> 34985.92 | R35: =SUBTOTAL(9,R15:R34) -> 4415.41 | S35: =R35*12 -> 52984.92 | U35: =SUBTOTAL(9,U15:U34) -> 4140.41 | V35: =U35*12 -> 49684.92
A37: AHORRO | I37: =I13-I35 -> 326.50667 | L37: =L13-L35 -> 326.50667 | O37: =O13-O35 -> 2384.5067 | R37: =R13-R35 -> 884.59 | U37: =U13-U35 -> 1159.59
A40: CONCEPTO | B40: BANCO | C40: CATEGORIA | D40: COSTE | E40: TIPO | F40: AL MES | H40: PRESCINDIBLE | I40: AL MES | K40: PRESCINDIBLE | L40: AL MES | N40: PRESCINDIBLE | O40: AL MES | Q40: PRESCINDIBLE | R40: AL MES | T40: PRESCINDIBLE | U40: AL MES
A41: HIPOTECA | B41: SANTANDER | C41: HIPOTECA | D41: 810 | E41: MENSUAL | F41: =IF($E41="MENSUAL",$D41,IF($E41="TRIMESTRAL",$D41/3,IF($E41="SEMESTRAL",$D41/2,IF($E41="ANUAL",$D41/12,IF($E41="BIMENSUAL",$D41/2))))) -> 810 | H41: NO | I41: =IF($H41="NO",IF($E41="MENSUAL",$D41,IF($E41="TRIMESTRAL",$D41/3,IF($E41="SEMESTRAL",$D41/2,IF($E41="ANUAL",$D41/12,IF($E41="BIMENSUAL",$D41/2))))),0) -> 810 | K41: NO | L41: =IF($H41="NO",IF($E41="MENSUAL",$D41,IF($E41="TRIMESTRAL",$D41/3,IF($E41="SEMESTRAL",$D41/2,IF($E41="ANUAL",$D41/12,IF($E41="BIMENSUAL",$D41/2))))),0) -> 810 | N41: SI | O41: =IF($N41="NO",IF($E41="MENSUAL",$D41,IF($E41="TRIMESTRAL",$D41/3,IF($E41="SEMESTRAL",$D41/2,IF($E41="ANUAL",$D41/12,IF($E41="BIMENSUAL",$D41/2))))),0) -> 0 | Q41: NO | R41: =IF($Q41="NO",IF($E41="MENSUAL",$D41,IF($E41="TRIMESTRAL",$D41/3,IF($E41="SEMESTRAL",$D41/2,IF($E41="ANUAL",$D41/12,IF($E41="BIMENSUAL",$D41/2))))),0) -> 810 | T41: NO | U41: =IF($T41="NO",IF($E41="MENSUAL",$D41,IF($E41="TRIMESTRAL",$D41/3,IF($E41="SEMESTRAL",$D41/2,IF($E41="ANUAL",$D41/12,IF($E41="BIMENSUAL",$D41/2))))),0) -> 810
A42: AHORRO | B42: SANTANDER | C42: AHORRO | D42: 0 | E42: ANUAL | F42: =IF($E42="MENSUAL",$D42,IF($E42="TRIMESTRAL",$D42/3,IF($E42="SEMESTRAL",$D42/2,IF($E42="ANUAL",$D42/12,IF($E42="BIMENSUAL",$D42/2))))) -> 0 | H42: NO | I42: =IF($H42="NO",IF($E42="MENSUAL",$D42,IF($E42="TRIMESTRAL",$D42/3,IF($E42="SEMESTRAL",$D42/2,IF($E42="ANUAL",$D42/12,IF($E42="BIMENSUAL",$D42/2))))),0) -> 0 | K42: NO | L42: =IF($H42="NO",IF($E42="MENSUAL",$D42,IF($E42="TRIMESTRAL",$D42/3,IF($E42="SEMESTRAL",$D42/2,IF($E42="ANUAL",$D42/12,IF($E42="BIMENSUAL",$D42/2))))),0) -> 0 | N42: NO | O42: =IF($N42="NO",IF($E42="MENSUAL",$D42,IF($E42="TRIMESTRAL",$D42/3,IF($E42="SEMESTRAL",$D42/2,IF($E42="ANUAL",$D42/12,IF($E42="BIMENSUAL",$D42/2))))),0) -> 0 | Q42: NO | R42: =IF($Q42="NO",IF($E42="MENSUAL",$D42,IF($E42="TRIMESTRAL",$D42/3,IF($E42="SEMESTRAL",$D42/2,IF($E42="ANUAL",$D42/12,IF($E42="BIMENSUAL",$D42/2))))),0) -> 0 | T42: NO | U42: =IF($T42="NO",IF($E42="MENSUAL",$D42,IF($E42="TRIMESTRAL",$D42/3,IF($E42="SEMESTRAL",$D42/2,IF($E42="ANUAL",$D42/12,IF($E42="BIMENSUAL",$D42/2))))),0) -> 0
A43: COMUNIDAD | B43: SANTANDER | C43: CASA | D43: 43.83 | E43: MENSUAL | F43: =IF($E43="MENSUAL",$D43,IF($E43="TRIMESTRAL",$D43/3,IF($E43="SEMESTRAL",$D43/2,IF($E43="ANUAL",$D43/12,IF($E43="BIMENSUAL",$D43/2))))) -> 43.83 | H43: NO | I43: =IF($H43="NO",IF($E43="MENSUAL",$D43,IF($E43="TRIMESTRAL",$D43/3,IF($E43="SEMESTRAL",$D43/2,IF($E43="ANUAL",$D43/12,IF($E43="BIMENSUAL",$D43/2))))),0) -> 43.83 | K43: NO | L43: =IF($H43="NO",IF($E43="MENSUAL",$D43,IF($E43="TRIMESTRAL",$D43/3,IF($E43="SEMESTRAL",$D43/2,IF($E43="ANUAL",$D43/12,IF($E43="BIMENSUAL",$D43/2))))),0) -> 43.83 | N43: NO | O43: =IF($N43="NO",IF($E43="MENSUAL",$D43,IF($E43="TRIMESTRAL",$D43/3,IF($E43="SEMESTRAL",$D43/2,IF($E43="ANUAL",$D43/12,IF($E43="BIMENSUAL",$D43/2))))),0) -> 43.83 | Q43: NO | R43: =IF($Q43="NO",IF($E43="MENSUAL",$D43,IF($E43="TRIMESTRAL",$D43/3,IF($E43="SEMESTRAL",$D43/2,IF($E43="ANUAL",$D43/12,IF($E43="BIMENSUAL",$D43/2))))),0) -> 43.83 | T43: NO | U43: =IF($T43="NO",IF($E43="MENSUAL",$D43,IF($E43="TRIMESTRAL",$D43/3,IF($E43="SEMESTRAL",$D43/2,IF($E43="ANUAL",$D43/12,IF($E43="BIMENSUAL",$D43/2))))),0) -> 43.83
A44: SOCIEDAD OTARRA (KUTXA) | B44: SANTANDER | C44: OCIO | D44: 30 | E44: MENSUAL | F44: =IF($E44="MENSUAL",$D44,IF($E44="TRIMESTRAL",$D44/3,IF($E44="SEMESTRAL",$D44/2,IF($E44="ANUAL",$D44/12,IF($E44="BIMENSUAL",$D44/2))))) -> 30 | G44: X | H44: NO | I44: =IF($H44="NO",IF($E44="MENSUAL",$D44,IF($E44="TRIMESTRAL",$D44/3,IF($E44="SEMESTRAL",$D44/2,IF($E44="ANUAL",$D44/12,IF($E44="BIMENSUAL",$D44/2))))),0) -> 30 | K44: NO | L44: =IF($H44="NO",IF($E44="MENSUAL",$D44,IF($E44="TRIMESTRAL",$D44/3,IF($E44="SEMESTRAL",$D44/2,IF($E44="ANUAL",$D44/12,IF($E44="BIMENSUAL",$D44/2))))),0) -> 30 | N44: NO | O44: =IF($N44="NO",IF($E44="MENSUAL",$D44,IF($E44="TRIMESTRAL",$D44/3,IF($E44="SEMESTRAL",$D44/2,IF($E44="ANUAL",$D44/12,IF($E44="BIMENSUAL",$D44/2))))),0) -> 30 | Q44: NO | R44: =IF($Q44="NO",IF($E44="MENSUAL",$D44,IF($E44="TRIMESTRAL",$D44/3,IF($E44="SEMESTRAL",$D44/2,IF($E44="ANUAL",$D44/12,IF($E44="BIMENSUAL",$D44/2))))),0) -> 30 | T44: NO | U44: =IF($T44="NO",IF($E44="MENSUAL",$D44,IF($E44="TRIMESTRAL",$D44/3,IF($E44="SEMESTRAL",$D44/2,IF($E44="ANUAL",$D44/12,IF($E44="BIMENSUAL",$D44/2))))),0) -> 30
A45: NETFLIX+HBO | B45: SANTANDER | C45: OCIO | D45: 7.5 | E45: MENSUAL | F45: =IF($E45="MENSUAL",$D45,IF($E45="TRIMESTRAL",$D45/3,IF($E45="SEMESTRAL",$D45/2,IF($E45="ANUAL",$D45/12,IF($E45="BIMENSUAL",$D45/2))))) -> 7.5 | H45: NO | I45: =IF($H45="NO",IF($E45="MENSUAL",$D45,IF($E45="TRIMESTRAL",$D45/3,IF($E45="SEMESTRAL",$D45/2,IF($E45="ANUAL",$D45/12,IF($E45="BIMENSUAL",$D45/2))))),0) -> 7.5 | K45: NO | L45: =IF($H45="NO",IF($E45="MENSUAL",$D45,IF($E45="TRIMESTRAL",$D45/3,IF($E45="SEMESTRAL",$D45/2,IF($E45="ANUAL",$D45/12,IF($E45="BIMENSUAL",$D45/2))))),0) -> 7.5 | N45: NO | O45: =IF($N45="NO",IF($E45="MENSUAL",$D45,IF($E45="TRIMESTRAL",$D45/3,IF($E45="SEMESTRAL",$D45/2,IF($E45="ANUAL",$D45/12,IF($E45="BIMENSUAL",$D45/2))))),0) -> 7.5 | Q45: NO | R45: =IF($Q45="NO",IF($E45="MENSUAL",$D45,IF($E45="TRIMESTRAL",$D45/3,IF($E45="SEMESTRAL",$D45/2,IF($E45="ANUAL",$D45/12,IF($E45="BIMENSUAL",$D45/2))))),0) -> 7.5 | T45: NO | U45: =IF($T45="NO",IF($E45="MENSUAL",$D45,IF($E45="TRIMESTRAL",$D45/3,IF($E45="SEMESTRAL",$D45/2,IF($E45="ANUAL",$D45/12,IF($E45="BIMENSUAL",$D45/2))))),0) -> 7.5
A46: LOCAL AMAIA/OLATZ | B46: SANTANDER | C46: OCIO | D46: 30 | E46: MENSUAL | F46: =IF($E46="MENSUAL",$D46,IF($E46="TRIMESTRAL",$D46/3,IF($E46="SEMESTRAL",$D46/2,IF($E46="ANUAL",$D46/12,IF($E46="BIMENSUAL",$D46/2))))) -> 30 | H46: SI | I46: =IF($H46="NO",IF($E46="MENSUAL",$D46,IF($E46="TRIMESTRAL",$D46/3,IF($E46="SEMESTRAL",$D46/2,IF($E46="ANUAL",$D46/12,IF($E46="BIMENSUAL",$D46/2))))),0) -> 0 | K46: SI | L46: =IF($H46="NO",IF($E46="MENSUAL",$D46,IF($E46="TRIMESTRAL",$D46/3,IF($E46="SEMESTRAL",$D46/2,IF($E46="ANUAL",$D46/12,IF($E46="BIMENSUAL",$D46/2))))),0) -> 0 | N46: SI | O46: =IF($N46="NO",IF($E46="MENSUAL",$D46,IF($E46="TRIMESTRAL",$D46/3,IF($E46="SEMESTRAL",$D46/2,IF($E46="ANUAL",$D46/12,IF($E46="BIMENSUAL",$D46/2))))),0) -> 0 | Q46: SI | R46: =IF($Q46="NO",IF($E46="MENSUAL",$D46,IF($E46="TRIMESTRAL",$D46/3,IF($E46="SEMESTRAL",$D46/2,IF($E46="ANUAL",$D46/12,IF($E46="BIMENSUAL",$D46/2))))),0) -> 0 | T46: SI | U46: =IF($T46="NO",IF($E46="MENSUAL",$D46,IF($E46="TRIMESTRAL",$D46/3,IF($E46="SEMESTRAL",$D46/2,IF($E46="ANUAL",$D46/12,IF($E46="BIMENSUAL",$D46/2))))),0) -> 0
A47: SEGURO VIDA 1 (SANTANDER SEG) | B47: SANTANDER | C47: CASA | D47: 217 | E47: ANUAL | F47: =IF($E47="MENSUAL",$D47,IF($E47="TRIMESTRAL",$D47/3,IF($E47="SEMESTRAL",$D47/2,IF($E47="ANUAL",$D47/12,IF($E47="BIMENSUAL",$D47/2))))) -> 18.083333 | H47: NO | I47: =IF($H47="NO",IF($E47="MENSUAL",$D47,IF($E47="TRIMESTRAL",$D47/3,IF($E47="SEMESTRAL",$D47/2,IF($E47="ANUAL",$D47/12,IF($E47="BIMENSUAL",$D47/2))))),0) -> 18.083333 | K47: NO | L47: =IF($H47="NO",IF($E47="MENSUAL",$D47,IF($E47="TRIMESTRAL",$D47/3,IF($E47="SEMESTRAL",$D47/2,IF($E47="ANUAL",$D47/12,IF($E47="BIMENSUAL",$D47/2))))),0) -> 18.083333 | N47: NO | O47: =IF($N47="NO",IF($E47="MENSUAL",$D47,IF($E47="TRIMESTRAL",$D47/3,IF($E47="SEMESTRAL",$D47/2,IF($E47="ANUAL",$D47/12,IF($E47="BIMENSUAL",$D47/2))))),0) -> 18.083333 | Q47: NO | R47: =IF($Q47="NO",IF($E47="MENSUAL",$D47,IF($E47="TRIMESTRAL",$D47/3,IF($E47="SEMESTRAL",$D47/2,IF($E47="ANUAL",$D47/12,IF($E47="BIMENSUAL",$D47/2))))),0) -> 18.083333 | T47: NO | U47: =IF($T47="NO",IF($E47="MENSUAL",$D47,IF($E47="TRIMESTRAL",$D47/3,IF($E47="SEMESTRAL",$D47/2,IF($E47="ANUAL",$D47/12,IF($E47="BIMENSUAL",$D47/2))))),0) -> 18.083333
A48: SEGURO VIDA 2 (SANTANDER SEG) | B48: SANTANDER | C48: CASA | D48: 200 | E48: ANUAL | F48: =IF($E48="MENSUAL",$D48,IF($E48="TRIMESTRAL",$D48/3,IF($E48="SEMESTRAL",$D48/2,IF($E48="ANUAL",$D48/12,IF($E48="BIMENSUAL",$D48/2))))) -> 16.666667 | H48: NO | I48: =IF($H48="NO",IF($E48="MENSUAL",$D48,IF($E48="TRIMESTRAL",$D48/3,IF($E48="SEMESTRAL",$D48/2,IF($E48="ANUAL",$D48/12,IF($E48="BIMENSUAL",$D48/2))))),0) -> 16.666667 | K48: NO | L48: =IF($H48="NO",IF($E48="MENSUAL",$D48,IF($E48="TRIMESTRAL",$D48/3,IF($E48="SEMESTRAL",$D48/2,IF($E48="ANUAL",$D48/12,IF($E48="BIMENSUAL",$D48/2))))),0) -> 16.666667 | N48: NO | O48: =IF($N48="NO",IF($E48="MENSUAL",$D48,IF($E48="TRIMESTRAL",$D48/3,IF($E48="SEMESTRAL",$D48/2,IF($E48="ANUAL",$D48/12,IF($E48="BIMENSUAL",$D48/2))))),0) -> 16.666667 | Q48: NO | R48: =IF($Q48="NO",IF($E48="MENSUAL",$D48,IF($E48="TRIMESTRAL",$D48/3,IF($E48="SEMESTRAL",$D48/2,IF($E48="ANUAL",$D48/12,IF($E48="BIMENSUAL",$D48/2))))),0) -> 16.666667 | T48: NO | U48: =IF($T48="NO",IF($E48="MENSUAL",$D48,IF($E48="TRIMESTRAL",$D48/3,IF($E48="SEMESTRAL",$D48/2,IF($E48="ANUAL",$D48/12,IF($E48="BIMENSUAL",$D48/2))))),0) -> 16.666667
A49: CONTRIBUCION.IBI URBANA (Eibarko udala) | B49: SANTANDER | C49: CASA | D49: 310 | E49: ANUAL | F49: =IF($E49="MENSUAL",$D49,IF($E49="TRIMESTRAL",$D49/3,IF($E49="SEMESTRAL",$D49/2,IF($E49="ANUAL",$D49/12,IF($E49="BIMENSUAL",$D49/2))))) -> 25.833333 | H49: NO | I49: =IF($H49="NO",IF($E49="MENSUAL",$D49,IF($E49="TRIMESTRAL",$D49/3,IF($E49="SEMESTRAL",$D49/2,IF($E49="ANUAL",$D49/12,IF($E49="BIMENSUAL",$D49/2))))),0) -> 25.833333 | K49: NO | L49: =IF($H49="NO",IF($E49="MENSUAL",$D49,IF($E49="TRIMESTRAL",$D49/3,IF($E49="SEMESTRAL",$D49/2,IF($E49="ANUAL",$D49/12,IF($E49="BIMENSUAL",$D49/2))))),0) -> 25.833333 | N49: NO | O49: =IF($N49="NO",IF($E49="MENSUAL",$D49,IF($E49="TRIMESTRAL",$D49/3,IF($E49="SEMESTRAL",$D49/2,IF($E49="ANUAL",$D49/12,IF($E49="BIMENSUAL",$D49/2))))),0) -> 25.833333 | Q49: NO | R49: =IF($Q49="NO",IF($E49="MENSUAL",$D49,IF($E49="TRIMESTRAL",$D49/3,IF($E49="SEMESTRAL",$D49/2,IF($E49="ANUAL",$D49/12,IF($E49="BIMENSUAL",$D49/2))))),0) -> 25.833333 | T49: NO | U49: =IF($T49="NO",IF($E49="MENSUAL",$D49,IF($E49="TRIMESTRAL",$D49/3,IF($E49="SEMESTRAL",$D49/2,IF($E49="ANUAL",$D49/12,IF($E49="BIMENSUAL",$D49/2))))),0) -> 25.833333
A50: GIPUZKOAKO URAK | B50: SANTANDER | C50: CASA | D50: 120 | E50: TRIMESTRAL | F50: =IF($E50="MENSUAL",$D50,IF($E50="TRIMESTRAL",$D50/3,IF($E50="SEMESTRAL",$D50/2,IF($E50="ANUAL",$D50/12,IF($E50="BIMENSUAL",$D50/2))))) -> 40 | H50: NO | I50: =IF($H50="NO",IF($E50="MENSUAL",$D50,IF($E50="TRIMESTRAL",$D50/3,IF($E50="SEMESTRAL",$D50/2,IF($E50="ANUAL",$D50/12,IF($E50="BIMENSUAL",$D50/2))))),0) -> 40 | K50: NO | L50: =IF($H50="NO",IF($E50="MENSUAL",$D50,IF($E50="TRIMESTRAL",$D50/3,IF($E50="SEMESTRAL",$D50/2,IF($E50="ANUAL",$D50/12,IF($E50="BIMENSUAL",$D50/2))))),0) -> 40 | N50: NO | O50: =IF($N50="NO",IF($E50="MENSUAL",$D50,IF($E50="TRIMESTRAL",$D50/3,IF($E50="SEMESTRAL",$D50/2,IF($E50="ANUAL",$D50/12,IF($E50="BIMENSUAL",$D50/2))))),0) -> 40 | Q50: NO | R50: =IF($Q50="NO",IF($E50="MENSUAL",$D50,IF($E50="TRIMESTRAL",$D50/3,IF($E50="SEMESTRAL",$D50/2,IF($E50="ANUAL",$D50/12,IF($E50="BIMENSUAL",$D50/2))))),0) -> 40 | T50: NO | U50: =IF($T50="NO",IF($E50="MENSUAL",$D50,IF($E50="TRIMESTRAL",$D50/3,IF($E50="SEMESTRAL",$D50/2,IF($E50="ANUAL",$D50/12,IF($E50="BIMENSUAL",$D50/2))))),0) -> 40
A51: GAS (Total Energies) | B51: SANTANDER | C51: CASA | D51: 150 | E51: BIMENSUAL | F51: =IF($E51="MENSUAL",$D51,IF($E51="TRIMESTRAL",$D51/3,IF($E51="SEMESTRAL",$D51/2,IF($E51="ANUAL",$D51/12,IF($E51="BIMENSUAL",$D51/2))))) -> 75 | H51: NO | I51: =IF($H51="NO",IF($E51="MENSUAL",$D51,IF($E51="TRIMESTRAL",$D51/3,IF($E51="SEMESTRAL",$D51/2,IF($E51="ANUAL",$D51/12,IF($E51="BIMENSUAL",$D51/2))))),0) -> 75 | K51: NO | L51: =IF($H51="NO",IF($E51="MENSUAL",$D51,IF($E51="TRIMESTRAL",$D51/3,IF($E51="SEMESTRAL",$D51/2,IF($E51="ANUAL",$D51/12,IF($E51="BIMENSUAL",$D51/2))))),0) -> 75 | N51: NO | O51: =IF($N51="NO",IF($E51="MENSUAL",$D51,IF($E51="TRIMESTRAL",$D51/3,IF($E51="SEMESTRAL",$D51/2,IF($E51="ANUAL",$D51/12,IF($E51="BIMENSUAL",$D51/2))))),0) -> 75 | Q51: NO | R51: =IF($Q51="NO",IF($E51="MENSUAL",$D51,IF($E51="TRIMESTRAL",$D51/3,IF($E51="SEMESTRAL",$D51/2,IF($E51="ANUAL",$D51/12,IF($E51="BIMENSUAL",$D51/2))))),0) -> 75 | T51: NO | U51: =IF($T51="NO",IF($E51="MENSUAL",$D51,IF($E51="TRIMESTRAL",$D51/3,IF($E51="SEMESTRAL",$D51/2,IF($E51="ANUAL",$D51/12,IF($E51="BIMENSUAL",$D51/2))))),0) -> 75
A52: IBERDROLA (CUNENERGIA) | B52: SANTANDER | C52: CASA | D52: 70 | E52: MENSUAL | F52: =IF($E52="MENSUAL",$D52,IF($E52="TRIMESTRAL",$D52/3,IF($E52="SEMESTRAL",$D52/2,IF($E52="ANUAL",$D52/12,IF($E52="BIMENSUAL",$D52/2))))) -> 70 | H52: NO | I52: =IF($H52="NO",IF($E52="MENSUAL",$D52,IF($E52="TRIMESTRAL",$D52/3,IF($E52="SEMESTRAL",$D52/2,IF($E52="ANUAL",$D52/12,IF($E52="BIMENSUAL",$D52/2))))),0) -> 70 | K52: NO | L52: =IF($H52="NO",IF($E52="MENSUAL",$D52,IF($E52="TRIMESTRAL",$D52/3,IF($E52="SEMESTRAL",$D52/2,IF($E52="ANUAL",$D52/12,IF($E52="BIMENSUAL",$D52/2))))),0) -> 70 | N52: NO | O52: =IF($N52="NO",IF($E52="MENSUAL",$D52,IF($E52="TRIMESTRAL",$D52/3,IF($E52="SEMESTRAL",$D52/2,IF($E52="ANUAL",$D52/12,IF($E52="BIMENSUAL",$D52/2))))),0) -> 70 | Q52: NO | R52: =IF($Q52="NO",IF($E52="MENSUAL",$D52,IF($E52="TRIMESTRAL",$D52/3,IF($E52="SEMESTRAL",$D52/2,IF($E52="ANUAL",$D52/12,IF($E52="BIMENSUAL",$D52/2))))),0) -> 70 | T52: NO | U52: =IF($T52="NO",IF($E52="MENSUAL",$D52,IF($E52="TRIMESTRAL",$D52/3,IF($E52="SEMESTRAL",$D52/2,IF($E52="ANUAL",$D52/12,IF($E52="BIMENSUAL",$D52/2))))),0) -> 70
A53: EUSKALTEL | B53: SANTANDER | C53: CASA | D53: 80 | E53: MENSUAL | F53: =IF($E53="MENSUAL",$D53,IF($E53="TRIMESTRAL",$D53/3,IF($E53="SEMESTRAL",$D53/2,IF($E53="ANUAL",$D53/12,IF($E53="BIMENSUAL",$D53/2))))) -> 80 | H53: NO | I53: =IF($H53="NO",IF($E53="MENSUAL",$D53,IF($E53="TRIMESTRAL",$D53/3,IF($E53="SEMESTRAL",$D53/2,IF($E53="ANUAL",$D53/12,IF($E53="BIMENSUAL",$D53/2))))),0) -> 80 | K53: NO | L53: =IF($H53="NO",IF($E53="MENSUAL",$D53,IF($E53="TRIMESTRAL",$D53/3,IF($E53="SEMESTRAL",$D53/2,IF($E53="ANUAL",$D53/12,IF($E53="BIMENSUAL",$D53/2))))),0) -> 80 | N53: NO | O53: =IF($N53="NO",IF($E53="MENSUAL",$D53,IF($E53="TRIMESTRAL",$D53/3,IF($E53="SEMESTRAL",$D53/2,IF($E53="ANUAL",$D53/12,IF($E53="BIMENSUAL",$D53/2))))),0) -> 80 | Q53: NO | R53: =IF($Q53="NO",IF($E53="MENSUAL",$D53,IF($E53="TRIMESTRAL",$D53/3,IF($E53="SEMESTRAL",$D53/2,IF($E53="ANUAL",$D53/12,IF($E53="BIMENSUAL",$D53/2))))),0) -> 80 | T53: NO | U53: =IF($T53="NO",IF($E53="MENSUAL",$D53,IF($E53="TRIMESTRAL",$D53/3,IF($E53="SEMESTRAL",$D53/2,IF($E53="ANUAL",$D53/12,IF($E53="BIMENSUAL",$D53/2))))),0) -> 80
A54: ESTUDIOS AMAIA | B54: SANTANDER | C54: ESTUDIOS | D54: 1300 | E54: ANUAL | F54: =IF($E54="MENSUAL",$D54,IF($E54="TRIMESTRAL",$D54/3,IF($E54="SEMESTRAL",$D54/2,IF($E54="ANUAL",$D54/12,IF($E54="BIMENSUAL",$D54/2))))) -> 108.33333 | H54: NO | I54: =IF($H54="NO",IF($E54="MENSUAL",$D54,IF($E54="TRIMESTRAL",$D54/3,IF($E54="SEMESTRAL",$D54/2,IF($E54="ANUAL",$D54/12,IF($E54="BIMENSUAL",$D54/2))))),0) -> 108.33333 | K54: NO | L54: =IF($H54="NO",IF($E54="MENSUAL",$D54,IF($E54="TRIMESTRAL",$D54/3,IF($E54="SEMESTRAL",$D54/2,IF($E54="ANUAL",$D54/12,IF($E54="BIMENSUAL",$D54/2))))),0) -> 108.33333 | N54: SI | O54: =IF($N54="NO",IF($E54="MENSUAL",$D54,IF($E54="TRIMESTRAL",$D54/3,IF($E54="SEMESTRAL",$D54/2,IF($E54="ANUAL",$D54/12,IF($E54="BIMENSUAL",$D54/2))))),0) -> 0 | Q54: NO | R54: =IF($Q54="NO",IF($E54="MENSUAL",$D54,IF($E54="TRIMESTRAL",$D54/3,IF($E54="SEMESTRAL",$D54/2,IF($E54="ANUAL",$D54/12,IF($E54="BIMENSUAL",$D54/2))))),0) -> 108.33333 | T54: NO | U54: =IF($T54="NO",IF($E54="MENSUAL",$D54,IF($E54="TRIMESTRAL",$D54/3,IF($E54="SEMESTRAL",$D54/2,IF($E54="ANUAL",$D54/12,IF($E54="BIMENSUAL",$D54/2))))),0) -> 108.33333
A55: ESTUDIOS OLATZ | B55: SANTANDER | C55: ESTUDIOS | D55: 1800 | E55: ANUAL | F55: =IF($E55="MENSUAL",$D55,IF($E55="TRIMESTRAL",$D55/3,IF($E55="SEMESTRAL",$D55/2,IF($E55="ANUAL",$D55/12,IF($E55="BIMENSUAL",$D55/2))))) -> 150 | H55: NO | I55: =IF($H55="NO",IF($E55="MENSUAL",$D55,IF($E55="TRIMESTRAL",$D55/3,IF($E55="SEMESTRAL",$D55/2,IF($E55="ANUAL",$D55/12,IF($E55="BIMENSUAL",$D55/2))))),0) -> 150 | K55: NO | L55: =IF($H55="NO",IF($E55="MENSUAL",$D55,IF($E55="TRIMESTRAL",$D55/3,IF($E55="SEMESTRAL",$D55/2,IF($E55="ANUAL",$D55/12,IF($E55="BIMENSUAL",$D55/2))))),0) -> 150 | N55: SI | O55: =IF($N55="NO",IF($E55="MENSUAL",$D55,IF($E55="TRIMESTRAL",$D55/3,IF($E55="SEMESTRAL",$D55/2,IF($E55="ANUAL",$D55/12,IF($E55="BIMENSUAL",$D55/2))))),0) -> 0 | Q55: NO | R55: =IF($Q55="NO",IF($E55="MENSUAL",$D55,IF($E55="TRIMESTRAL",$D55/3,IF($E55="SEMESTRAL",$D55/2,IF($E55="ANUAL",$D55/12,IF($E55="BIMENSUAL",$D55/2))))),0) -> 150 | T55: NO | U55: =IF($T55="NO",IF($E55="MENSUAL",$D55,IF($E55="TRIMESTRAL",$D55/3,IF($E55="SEMESTRAL",$D55/2,IF($E55="ANUAL",$D55/12,IF($E55="BIMENSUAL",$D55/2))))),0) -> 150
A56: TRANSPORTE AMAIA | B56: SANTANDER | C56: TRANSPORTE | D56: 100 | E56: MENSUAL | F56: =IF($E56="MENSUAL",$D56,IF($E56="TRIMESTRAL",$D56/3,IF($E56="SEMESTRAL",$D56/2,IF($E56="ANUAL",$D56/12,IF($E56="BIMENSUAL",$D56/2))))) -> 100 | G56: X | H56: NO | I56: =IF($H56="NO",IF($E56="MENSUAL",$D56,IF($E56="TRIMESTRAL",$D56/3,IF($E56="SEMESTRAL",$D56/2,IF($E56="ANUAL",$D56/12,IF($E56="BIMENSUAL",$D56/2))))),0) -> 100 | K56: NO | L56: =IF($H56="NO",IF($E56="MENSUAL",$D56,IF($E56="TRIMESTRAL",$D56/3,IF($E56="SEMESTRAL",$D56/2,IF($E56="ANUAL",$D56/12,IF($E56="BIMENSUAL",$D56/2))))),0) -> 100 | N56: SI | O56: =IF($N56="NO",IF($E56="MENSUAL",$D56,IF($E56="TRIMESTRAL",$D56/3,IF($E56="SEMESTRAL",$D56/2,IF($E56="ANUAL",$D56/12,IF($E56="BIMENSUAL",$D56/2))))),0) -> 0 | Q56: NO | R56: =IF($Q56="NO",IF($E56="MENSUAL",$D56,IF($E56="TRIMESTRAL",$D56/3,IF($E56="SEMESTRAL",$D56/2,IF($E56="ANUAL",$D56/12,IF($E56="BIMENSUAL",$D56/2))))),0) -> 100 | T56: NO | U56: =IF($T56="NO",IF($E56="MENSUAL",$D56,IF($E56="TRIMESTRAL",$D56/3,IF($E56="SEMESTRAL",$D56/2,IF($E56="ANUAL",$D56/12,IF($E56="BIMENSUAL",$D56/2))))),0) -> 100
A57: TRANSPORTE OLATZ | B57: SANTANDER | C57: TRANSPORTE | D57: 100 | E57: MENSUAL | F57: =IF($E57="MENSUAL",$D57,IF($E57="TRIMESTRAL",$D57/3,IF($E57="SEMESTRAL",$D57/2,IF($E57="ANUAL",$D57/12,IF($E57="BIMENSUAL",$D57/2))))) -> 100 | H57: NO | I57: =IF($H57="NO",IF($E57="MENSUAL",$D57,IF($E57="TRIMESTRAL",$D57/3,IF($E57="SEMESTRAL",$D57/2,IF($E57="ANUAL",$D57/12,IF($E57="BIMENSUAL",$D57/2))))),0) -> 100 | K57: NO | L57: =IF($H57="NO",IF($E57="MENSUAL",$D57,IF($E57="TRIMESTRAL",$D57/3,IF($E57="SEMESTRAL",$D57/2,IF($E57="ANUAL",$D57/12,IF($E57="BIMENSUAL",$D57/2))))),0) -> 100 | N57: SI | O57: =IF($N57="NO",IF($E57="MENSUAL",$D57,IF($E57="TRIMESTRAL",$D57/3,IF($E57="SEMESTRAL",$D57/2,IF($E57="ANUAL",$D57/12,IF($E57="BIMENSUAL",$D57/2))))),0) -> 0 | Q57: NO | R57: =IF($Q57="NO",IF($E57="MENSUAL",$D57,IF($E57="TRIMESTRAL",$D57/3,IF($E57="SEMESTRAL",$D57/2,IF($E57="ANUAL",$D57/12,IF($E57="BIMENSUAL",$D57/2))))),0) -> 100 | T57: NO | U57: =IF($T57="NO",IF($E57="MENSUAL",$D57,IF($E57="TRIMESTRAL",$D57/3,IF($E57="SEMESTRAL",$D57/2,IF($E57="ANUAL",$D57/12,IF($E57="BIMENSUAL",$D57/2))))),0) -> 100
A58: TRANSPORTE YOLI | B58: SANTANDER | C58: TRANSPORTE | D58: 50 | E58: MENSUAL | F58: =IF($E58="MENSUAL",$D58,IF($E58="TRIMESTRAL",$D58/3,IF($E58="SEMESTRAL",$D58/2,IF($E58="ANUAL",$D58/12,IF($E58="BIMENSUAL",$D58/2))))) -> 50 | H58: NO | I58: =IF($H58="NO",IF($E58="MENSUAL",$D58,IF($E58="TRIMESTRAL",$D58/3,IF($E58="SEMESTRAL",$D58/2,IF($E58="ANUAL",$D58/12,IF($E58="BIMENSUAL",$D58/2))))),0) -> 50 | K58: NO | L58: =IF($H58="NO",IF($E58="MENSUAL",$D58,IF($E58="TRIMESTRAL",$D58/3,IF($E58="SEMESTRAL",$D58/2,IF($E58="ANUAL",$D58/12,IF($E58="BIMENSUAL",$D58/2))))),0) -> 50 | N58: NO | O58: =IF($N58="NO",IF($E58="MENSUAL",$D58,IF($E58="TRIMESTRAL",$D58/3,IF($E58="SEMESTRAL",$D58/2,IF($E58="ANUAL",$D58/12,IF($E58="BIMENSUAL",$D58/2))))),0) -> 50 | Q58: NO | R58: =IF($Q58="NO",IF($E58="MENSUAL",$D58,IF($E58="TRIMESTRAL",$D58/3,IF($E58="SEMESTRAL",$D58/2,IF($E58="ANUAL",$D58/12,IF($E58="BIMENSUAL",$D58/2))))),0) -> 50 | T58: NO | U58: =IF($T58="NO",IF($E58="MENSUAL",$D58,IF($E58="TRIMESTRAL",$D58/3,IF($E58="SEMESTRAL",$D58/2,IF($E58="ANUAL",$D58/12,IF($E58="BIMENSUAL",$D58/2))))),0) -> 50
A59: MARGO ESKOLA (Eibarko udala) | B59: SANTANDER | C59: ESTUDIOS | D59: 200 | E59: ANUAL | F59: =IF($E59="MENSUAL",$D59,IF($E59="TRIMESTRAL",$D59/3,IF($E59="SEMESTRAL",$D59/2,IF($E59="ANUAL",$D59/12,IF($E59="BIMENSUAL",$D59/2))))) -> 16.666667 | H59: SI | I59: =IF($H59="NO",IF($E59="MENSUAL",$D59,IF($E59="TRIMESTRAL",$D59/3,IF($E59="SEMESTRAL",$D59/2,IF($E59="ANUAL",$D59/12,IF($E59="BIMENSUAL",$D59/2))))),0) -> 0 | K59: SI | L59: =IF($H59="NO",IF($E59="MENSUAL",$D59,IF($E59="TRIMESTRAL",$D59/3,IF($E59="SEMESTRAL",$D59/2,IF($E59="ANUAL",$D59/12,IF($E59="BIMENSUAL",$D59/2))))),0) -> 0 | N59: SI | O59: =IF($N59="NO",IF($E59="MENSUAL",$D59,IF($E59="TRIMESTRAL",$D59/3,IF($E59="SEMESTRAL",$D59/2,IF($E59="ANUAL",$D59/12,IF($E59="BIMENSUAL",$D59/2))))),0) -> 0 | Q59: SI | R59: =IF($Q59="NO",IF($E59="MENSUAL",$D59,IF($E59="TRIMESTRAL",$D59/3,IF($E59="SEMESTRAL",$D59/2,IF($E59="ANUAL",$D59/12,IF($E59="BIMENSUAL",$D59/2))))),0) -> 0 | T59: SI | U59: =IF($T59="NO",IF($E59="MENSUAL",$D59,IF($E59="TRIMESTRAL",$D59/3,IF($E59="SEMESTRAL",$D59/2,IF($E59="ANUAL",$D59/12,IF($E59="BIMENSUAL",$D59/2))))),0) -> 0
A60: VIAJES Y GASTOS ASOCIADOS ESCUELA | B60: SANTANDER | C60: ESTUDIOS | D60: 0 | E60: ANUAL | F60: =IF($E60="MENSUAL",$D60,IF($E60="TRIMESTRAL",$D60/3,IF($E60="SEMESTRAL",$D60/2,IF($E60="ANUAL",$D60/12,IF($E60="BIMENSUAL",$D60/2))))) -> 0 | H60: SI | I60: =IF($H60="NO",IF($E60="MENSUAL",$D60,IF($E60="TRIMESTRAL",$D60/3,IF($E60="SEMESTRAL",$D60/2,IF($E60="ANUAL",$D60/12,IF($E60="BIMENSUAL",$D60/2))))),0) -> 0 | K60: SI | L60: =IF($H60="NO",IF($E60="MENSUAL",$D60,IF($E60="TRIMESTRAL",$D60/3,IF($E60="SEMESTRAL",$D60/2,IF($E60="ANUAL",$D60/12,IF($E60="BIMENSUAL",$D60/2))))),0) -> 0 | N60: SI | O60: =IF($N60="NO",IF($E60="MENSUAL",$D60,IF($E60="TRIMESTRAL",$D60/3,IF($E60="SEMESTRAL",$D60/2,IF($E60="ANUAL",$D60/12,IF($E60="BIMENSUAL",$D60/2))))),0) -> 0 | Q60: SI | R60: =IF($Q60="NO",IF($E60="MENSUAL",$D60,IF($E60="TRIMESTRAL",$D60/3,IF($E60="SEMESTRAL",$D60/2,IF($E60="ANUAL",$D60/12,IF($E60="BIMENSUAL",$D60/2))))),0) -> 0 | T60: SI | U60: =IF($T60="NO",IF($E60="MENSUAL",$D60,IF($E60="TRIMESTRAL",$D60/3,IF($E60="SEMESTRAL",$D60/2,IF($E60="ANUAL",$D60/12,IF($E60="BIMENSUAL",$D60/2))))),0) -> 0
A61: LAB | B61: SANTANDER | C61: SINDICATO | D61: 20.58 | E61: MENSUAL | F61: =IF($E61="MENSUAL",$D61,IF($E61="TRIMESTRAL",$D61/3,IF($E61="SEMESTRAL",$D61/2,IF($E61="ANUAL",$D61/12,IF($E61="BIMENSUAL",$D61/2))))) -> 20.58 | G61: X | H61: NO | I61: =IF($H61="NO",IF($E61="MENSUAL",$D61,IF($E61="TRIMESTRAL",$D61/3,IF($E61="SEMESTRAL",$D61/2,IF($E61="ANUAL",$D61/12,IF($E61="BIMENSUAL",$D61/2))))),0) -> 20.58 | K61: NO | L61: =IF($H61="NO",IF($E61="MENSUAL",$D61,IF($E61="TRIMESTRAL",$D61/3,IF($E61="SEMESTRAL",$D61/2,IF($E61="ANUAL",$D61/12,IF($E61="BIMENSUAL",$D61/2))))),0) -> 20.58 | N61: NO | O61: =IF($N61="NO",IF($E61="MENSUAL",$D61,IF($E61="TRIMESTRAL",$D61/3,IF($E61="SEMESTRAL",$D61/2,IF($E61="ANUAL",$D61/12,IF($E61="BIMENSUAL",$D61/2))))),0) -> 20.58 | Q61: NO | R61: =IF($Q61="NO",IF($E61="MENSUAL",$D61,IF($E61="TRIMESTRAL",$D61/3,IF($E61="SEMESTRAL",$D61/2,IF($E61="ANUAL",$D61/12,IF($E61="BIMENSUAL",$D61/2))))),0) -> 20.58 | T61: NO | U61: =IF($T61="NO",IF($E61="MENSUAL",$D61,IF($E61="TRIMESTRAL",$D61/3,IF($E61="SEMESTRAL",$D61/2,IF($E61="ANUAL",$D61/12,IF($E61="BIMENSUAL",$D61/2))))),0) -> 20.58
A62: SEGURO COCHE ZAFIRA | B62: SANTANDER | C62: COCHE | D62: 0 | E62: ANUAL | F62: =IF($E62="MENSUAL",$D62,IF($E62="TRIMESTRAL",$D62/3,IF($E62="SEMESTRAL",$D62/2,IF($E62="ANUAL",$D62/12,IF($E62="BIMENSUAL",$D62/2))))) -> 0 | H62: SI | I62: =IF($H62="NO",IF($E62="MENSUAL",$D62,IF($E62="TRIMESTRAL",$D62/3,IF($E62="SEMESTRAL",$D62/2,IF($E62="ANUAL",$D62/12,IF($E62="BIMENSUAL",$D62/2))))),0) -> 0 | K62: SI | L62: =IF($H62="NO",IF($E62="MENSUAL",$D62,IF($E62="TRIMESTRAL",$D62/3,IF($E62="SEMESTRAL",$D62/2,IF($E62="ANUAL",$D62/12,IF($E62="BIMENSUAL",$D62/2))))),0) -> 0 | N62: SI | O62: =IF($N62="NO",IF($E62="MENSUAL",$D62,IF($E62="TRIMESTRAL",$D62/3,IF($E62="SEMESTRAL",$D62/2,IF($E62="ANUAL",$D62/12,IF($E62="BIMENSUAL",$D62/2))))),0) -> 0 | Q62: SI | R62: =IF($Q62="NO",IF($E62="MENSUAL",$D62,IF($E62="TRIMESTRAL",$D62/3,IF($E62="SEMESTRAL",$D62/2,IF($E62="ANUAL",$D62/12,IF($E62="BIMENSUAL",$D62/2))))),0) -> 0 | T62: SI | U62: =IF($T62="NO",IF($E62="MENSUAL",$D62,IF($E62="TRIMESTRAL",$D62/3,IF($E62="SEMESTRAL",$D62/2,IF($E62="ANUAL",$D62/12,IF($E62="BIMENSUAL",$D62/2))))),0) -> 0
A63: IMP.CIRCULACION (Eibarko udala) ZAFIRA | B63: SANTANDER | C63: COCHE | D63: 0 | E63: ANUAL | F63: =IF($E63="MENSUAL",$D63,IF($E63="TRIMESTRAL",$D63/3,IF($E63="SEMESTRAL",$D63/2,IF($E63="ANUAL",$D63/12,IF($E63="BIMENSUAL",$D63/2))))) -> 0 | H63: SI | I63: =IF($H63="NO",IF($E63="MENSUAL",$D63,IF($E63="TRIMESTRAL",$D63/3,IF($E63="SEMESTRAL",$D63/2,IF($E63="ANUAL",$D63/12,IF($E63="BIMENSUAL",$D63/2))))),0) -> 0 | K63: SI | L63: =IF($H63="NO",IF($E63="MENSUAL",$D63,IF($E63="TRIMESTRAL",$D63/3,IF($E63="SEMESTRAL",$D63/2,IF($E63="ANUAL",$D63/12,IF($E63="BIMENSUAL",$D63/2))))),0) -> 0 | N63: SI | O63: =IF($N63="NO",IF($E63="MENSUAL",$D63,IF($E63="TRIMESTRAL",$D63/3,IF($E63="SEMESTRAL",$D63/2,IF($E63="ANUAL",$D63/12,IF($E63="BIMENSUAL",$D63/2))))),0) -> 0 | Q63: SI | R63: =IF($Q63="NO",IF($E63="MENSUAL",$D63,IF($E63="TRIMESTRAL",$D63/3,IF($E63="SEMESTRAL",$D63/2,IF($E63="ANUAL",$D63/12,IF($E63="BIMENSUAL",$D63/2))))),0) -> 0 | T63: SI | U63: =IF($T63="NO",IF($E63="MENSUAL",$D63,IF($E63="TRIMESTRAL",$D63/3,IF($E63="SEMESTRAL",$D63/2,IF($E63="ANUAL",$D63/12,IF($E63="BIMENSUAL",$D63/2))))),0) -> 0
A64: ITV ZAFIRA | B64: SANTANDER | C64: COCHE | D64: 0 | E64: ANUAL | F64: =IF($E64="MENSUAL",$D64,IF($E64="TRIMESTRAL",$D64/3,IF($E64="SEMESTRAL",$D64/2,IF($E64="ANUAL",$D64/12,IF($E64="BIMENSUAL",$D64/2))))) -> 0 | H64: SI | I64: =IF($H64="NO",IF($E64="MENSUAL",$D64,IF($E64="TRIMESTRAL",$D64/3,IF($E64="SEMESTRAL",$D64/2,IF($E64="ANUAL",$D64/12,IF($E64="BIMENSUAL",$D64/2))))),0) -> 0 | K64: SI | L64: =IF($H64="NO",IF($E64="MENSUAL",$D64,IF($E64="TRIMESTRAL",$D64/3,IF($E64="SEMESTRAL",$D64/2,IF($E64="ANUAL",$D64/12,IF($E64="BIMENSUAL",$D64/2))))),0) -> 0 | N64: SI | O64: =IF($N64="NO",IF($E64="MENSUAL",$D64,IF($E64="TRIMESTRAL",$D64/3,IF($E64="SEMESTRAL",$D64/2,IF($E64="ANUAL",$D64/12,IF($E64="BIMENSUAL",$D64/2))))),0) -> 0 | Q64: SI | R64: =IF($Q64="NO",IF($E64="MENSUAL",$D64,IF($E64="TRIMESTRAL",$D64/3,IF($E64="SEMESTRAL",$D64/2,IF($E64="ANUAL",$D64/12,IF($E64="BIMENSUAL",$D64/2))))),0) -> 0 | T64: SI | U64: =IF($T64="NO",IF($E64="MENSUAL",$D64,IF($E64="TRIMESTRAL",$D64/3,IF($E64="SEMESTRAL",$D64/2,IF($E64="ANUAL",$D64/12,IF($E64="BIMENSUAL",$D64/2))))),0) -> 0
A65: GASOLINA ZAFIRA | B65: SANTANDER | C65: COCHE | D65: 0 | E65: MENSUAL | F65: =IF($E65="MENSUAL",$D65,IF($E65="TRIMESTRAL",$D65/3,IF($E65="SEMESTRAL",$D65/2,IF($E65="ANUAL",$D65/12,IF($E65="BIMENSUAL",$D65/2))))) -> 0 | H65: SI | I65: =IF($H65="NO",IF($E65="MENSUAL",$D65,IF($E65="TRIMESTRAL",$D65/3,IF($E65="SEMESTRAL",$D65/2,IF($E65="ANUAL",$D65/12,IF($E65="BIMENSUAL",$D65/2))))),0) -> 0 | K65: SI | L65: =IF($H65="NO",IF($E65="MENSUAL",$D65,IF($E65="TRIMESTRAL",$D65/3,IF($E65="SEMESTRAL",$D65/2,IF($E65="ANUAL",$D65/12,IF($E65="BIMENSUAL",$D65/2))))),0) -> 0 | N65: SI | O65: =IF($N65="NO",IF($E65="MENSUAL",$D65,IF($E65="TRIMESTRAL",$D65/3,IF($E65="SEMESTRAL",$D65/2,IF($E65="ANUAL",$D65/12,IF($E65="BIMENSUAL",$D65/2))))),0) -> 0 | Q65: SI | R65: =IF($Q65="NO",IF($E65="MENSUAL",$D65,IF($E65="TRIMESTRAL",$D65/3,IF($E65="SEMESTRAL",$D65/2,IF($E65="ANUAL",$D65/12,IF($E65="BIMENSUAL",$D65/2))))),0) -> 0 | T65: SI | U65: =IF($T65="NO",IF($E65="MENSUAL",$D65,IF($E65="TRIMESTRAL",$D65/3,IF($E65="SEMESTRAL",$D65/2,IF($E65="ANUAL",$D65/12,IF($E65="BIMENSUAL",$D65/2))))),0) -> 0
A66: GASTOS COCHE ZAFIRA | B66: SANTANDER | C66: COCHE | D66: 0 | E66: ANUAL | F66: =IF($E66="MENSUAL",$D66,IF($E66="TRIMESTRAL",$D66/3,IF($E66="SEMESTRAL",$D66/2,IF($E66="ANUAL",$D66/12,IF($E66="BIMENSUAL",$D66/2))))) -> 0 | H66: SI | I66: =IF($H66="NO",IF($E66="MENSUAL",$D66,IF($E66="TRIMESTRAL",$D66/3,IF($E66="SEMESTRAL",$D66/2,IF($E66="ANUAL",$D66/12,IF($E66="BIMENSUAL",$D66/2))))),0) -> 0 | K66: SI | L66: =IF($H66="NO",IF($E66="MENSUAL",$D66,IF($E66="TRIMESTRAL",$D66/3,IF($E66="SEMESTRAL",$D66/2,IF($E66="ANUAL",$D66/12,IF($E66="BIMENSUAL",$D66/2))))),0) -> 0 | N66: SI | O66: =IF($N66="NO",IF($E66="MENSUAL",$D66,IF($E66="TRIMESTRAL",$D66/3,IF($E66="SEMESTRAL",$D66/2,IF($E66="ANUAL",$D66/12,IF($E66="BIMENSUAL",$D66/2))))),0) -> 0 | Q66: SI | R66: =IF($Q66="NO",IF($E66="MENSUAL",$D66,IF($E66="TRIMESTRAL",$D66/3,IF($E66="SEMESTRAL",$D66/2,IF($E66="ANUAL",$D66/12,IF($E66="BIMENSUAL",$D66/2))))),0) -> 0 | T66: SI | U66: =IF($T66="NO",IF($E66="MENSUAL",$D66,IF($E66="TRIMESTRAL",$D66/3,IF($E66="SEMESTRAL",$D66/2,IF($E66="ANUAL",$D66/12,IF($E66="BIMENSUAL",$D66/2))))),0) -> 0
A67: IMP.CIRCULACION (Eibarko udala) LEON | B67: SANTANDER | C67: COCHE | D67: 80 | E67: ANUAL | F67: =IF($E67="MENSUAL",$D67,IF($E67="TRIMESTRAL",$D67/3,IF($E67="SEMESTRAL",$D67/2,IF($E67="ANUAL",$D67/12,IF($E67="BIMENSUAL",$D67/2))))) -> 6.6666667 | H67: NO | I67: =IF($H67="NO",IF($E67="MENSUAL",$D67,IF($E67="TRIMESTRAL",$D67/3,IF($E67="SEMESTRAL",$D67/2,IF($E67="ANUAL",$D67/12,IF($E67="BIMENSUAL",$D67/2))))),0) -> 6.6666667 | K67: NO | L67: =IF($H67="NO",IF($E67="MENSUAL",$D67,IF($E67="TRIMESTRAL",$D67/3,IF($E67="SEMESTRAL",$D67/2,IF($E67="ANUAL",$D67/12,IF($E67="BIMENSUAL",$D67/2))))),0) -> 6.6666667 | N67: NO | O67: =IF($N67="NO",IF($E67="MENSUAL",$D67,IF($E67="TRIMESTRAL",$D67/3,IF($E67="SEMESTRAL",$D67/2,IF($E67="ANUAL",$D67/12,IF($E67="BIMENSUAL",$D67/2))))),0) -> 6.6666667 | Q67: NO | R67: =IF($Q67="NO",IF($E67="MENSUAL",$D67,IF($E67="TRIMESTRAL",$D67/3,IF($E67="SEMESTRAL",$D67/2,IF($E67="ANUAL",$D67/12,IF($E67="BIMENSUAL",$D67/2))))),0) -> 6.6666667 | T67: NO | U67: =IF($T67="NO",IF($E67="MENSUAL",$D67,IF($E67="TRIMESTRAL",$D67/3,IF($E67="SEMESTRAL",$D67/2,IF($E67="ANUAL",$D67/12,IF($E67="BIMENSUAL",$D67/2))))),0) -> 6.6666667
A68: ITV LEON | B68: SANTANDER | C68: COCHE | D68: 50 | E68: ANUAL | F68: =IF($E68="MENSUAL",$D68,IF($E68="TRIMESTRAL",$D68/3,IF($E68="SEMESTRAL",$D68/2,IF($E68="ANUAL",$D68/12,IF($E68="BIMENSUAL",$D68/2))))) -> 4.1666667 | H68: NO | I68: =IF($H68="NO",IF($E68="MENSUAL",$D68,IF($E68="TRIMESTRAL",$D68/3,IF($E68="SEMESTRAL",$D68/2,IF($E68="ANUAL",$D68/12,IF($E68="BIMENSUAL",$D68/2))))),0) -> 4.1666667 | K68: NO | L68: =IF($H68="NO",IF($E68="MENSUAL",$D68,IF($E68="TRIMESTRAL",$D68/3,IF($E68="SEMESTRAL",$D68/2,IF($E68="ANUAL",$D68/12,IF($E68="BIMENSUAL",$D68/2))))),0) -> 4.1666667 | N68: NO | O68: =IF($N68="NO",IF($E68="MENSUAL",$D68,IF($E68="TRIMESTRAL",$D68/3,IF($E68="SEMESTRAL",$D68/2,IF($E68="ANUAL",$D68/12,IF($E68="BIMENSUAL",$D68/2))))),0) -> 4.1666667 | Q68: NO | R68: =IF($Q68="NO",IF($E68="MENSUAL",$D68,IF($E68="TRIMESTRAL",$D68/3,IF($E68="SEMESTRAL",$D68/2,IF($E68="ANUAL",$D68/12,IF($E68="BIMENSUAL",$D68/2))))),0) -> 4.1666667 | T68: NO | U68: =IF($T68="NO",IF($E68="MENSUAL",$D68,IF($E68="TRIMESTRAL",$D68/3,IF($E68="SEMESTRAL",$D68/2,IF($E68="ANUAL",$D68/12,IF($E68="BIMENSUAL",$D68/2))))),0) -> 4.1666667
A69: GASOLINA LEON | B69: SANTANDER | C69: COCHE | D69: 50 | E69: MENSUAL | F69: =IF($E69="MENSUAL",$D69,IF($E69="TRIMESTRAL",$D69/3,IF($E69="SEMESTRAL",$D69/2,IF($E69="ANUAL",$D69/12,IF($E69="BIMENSUAL",$D69/2))))) -> 50 | H69: NO | I69: =IF($H69="NO",IF($E69="MENSUAL",$D69,IF($E69="TRIMESTRAL",$D69/3,IF($E69="SEMESTRAL",$D69/2,IF($E69="ANUAL",$D69/12,IF($E69="BIMENSUAL",$D69/2))))),0) -> 50 | K69: NO | L69: =IF($H69="NO",IF($E69="MENSUAL",$D69,IF($E69="TRIMESTRAL",$D69/3,IF($E69="SEMESTRAL",$D69/2,IF($E69="ANUAL",$D69/12,IF($E69="BIMENSUAL",$D69/2))))),0) -> 50 | N69: NO | O69: =IF($N69="NO",IF($E69="MENSUAL",$D69,IF($E69="TRIMESTRAL",$D69/3,IF($E69="SEMESTRAL",$D69/2,IF($E69="ANUAL",$D69/12,IF($E69="BIMENSUAL",$D69/2))))),0) -> 50 | Q69: NO | R69: =IF($Q69="NO",IF($E69="MENSUAL",$D69,IF($E69="TRIMESTRAL",$D69/3,IF($E69="SEMESTRAL",$D69/2,IF($E69="ANUAL",$D69/12,IF($E69="BIMENSUAL",$D69/2))))),0) -> 50 | T69: NO | U69: =IF($T69="NO",IF($E69="MENSUAL",$D69,IF($E69="TRIMESTRAL",$D69/3,IF($E69="SEMESTRAL",$D69/2,IF($E69="ANUAL",$D69/12,IF($E69="BIMENSUAL",$D69/2))))),0) -> 50
A70: IBI GARAJE | B70: SANTANDER | C70: COCHE | D70: 50 | E70: ANUAL | F70: =IF($E70="MENSUAL",$D70,IF($E70="TRIMESTRAL",$D70/3,IF($E70="SEMESTRAL",$D70/2,IF($E70="ANUAL",$D70/12,IF($E70="BIMENSUAL",$D70/2))))) -> 4.1666667 | H70: NO | I70: =IF($H70="NO",IF($E70="MENSUAL",$D70,IF($E70="TRIMESTRAL",$D70/3,IF($E70="SEMESTRAL",$D70/2,IF($E70="ANUAL",$D70/12,IF($E70="BIMENSUAL",$D70/2))))),0) -> 4.1666667 | K70: NO | L70: =IF($H70="NO",IF($E70="MENSUAL",$D70,IF($E70="TRIMESTRAL",$D70/3,IF($E70="SEMESTRAL",$D70/2,IF($E70="ANUAL",$D70/12,IF($E70="BIMENSUAL",$D70/2))))),0) -> 4.1666667 | N70: NO | O70: =IF($N70="NO",IF($E70="MENSUAL",$D70,IF($E70="TRIMESTRAL",$D70/3,IF($E70="SEMESTRAL",$D70/2,IF($E70="ANUAL",$D70/12,IF($E70="BIMENSUAL",$D70/2))))),0) -> 4.1666667 | Q70: NO | R70: =IF($Q70="NO",IF($E70="MENSUAL",$D70,IF($E70="TRIMESTRAL",$D70/3,IF($E70="SEMESTRAL",$D70/2,IF($E70="ANUAL",$D70/12,IF($E70="BIMENSUAL",$D70/2))))),0) -> 4.1666667 | T70: NO | U70: =IF($T70="NO",IF($E70="MENSUAL",$D70,IF($E70="TRIMESTRAL",$D70/3,IF($E70="SEMESTRAL",$D70/2,IF($E70="ANUAL",$D70/12,IF($E70="BIMENSUAL",$D70/2))))),0) -> 4.1666667
A71: CUOTA GARAJE (Cdad. Ubitxa n 22) | B71: SANTANDER | C71: COCHE | D71: 160 | E71: ANUAL | F71: =IF($E71="MENSUAL",$D71,IF($E71="TRIMESTRAL",$D71/3,IF($E71="SEMESTRAL",$D71/2,IF($E71="ANUAL",$D71/12,IF($E71="BIMENSUAL",$D71/2))))) -> 13.333333 | H71: NO | I71: =IF($H71="NO",IF($E71="MENSUAL",$D71,IF($E71="TRIMESTRAL",$D71/3,IF($E71="SEMESTRAL",$D71/2,IF($E71="ANUAL",$D71/12,IF($E71="BIMENSUAL",$D71/2))))),0) -> 13.333333 | K71: NO | L71: =IF($H71="NO",IF($E71="MENSUAL",$D71,IF($E71="TRIMESTRAL",$D71/3,IF($E71="SEMESTRAL",$D71/2,IF($E71="ANUAL",$D71/12,IF($E71="BIMENSUAL",$D71/2))))),0) -> 13.333333 | N71: NO | O71: =IF($N71="NO",IF($E71="MENSUAL",$D71,IF($E71="TRIMESTRAL",$D71/3,IF($E71="SEMESTRAL",$D71/2,IF($E71="ANUAL",$D71/12,IF($E71="BIMENSUAL",$D71/2))))),0) -> 13.333333 | Q71: NO | R71: =IF($Q71="NO",IF($E71="MENSUAL",$D71,IF($E71="TRIMESTRAL",$D71/3,IF($E71="SEMESTRAL",$D71/2,IF($E71="ANUAL",$D71/12,IF($E71="BIMENSUAL",$D71/2))))),0) -> 13.333333 | T71: NO | U71: =IF($T71="NO",IF($E71="MENSUAL",$D71,IF($E71="TRIMESTRAL",$D71/3,IF($E71="SEMESTRAL",$D71/2,IF($E71="ANUAL",$D71/12,IF($E71="BIMENSUAL",$D71/2))))),0) -> 13.333333
A72: ABIATU/BIDEGI | B72: SANTANDER | C72: COCHE | D72: 50 | E72: MENSUAL | F72: =IF($E72="MENSUAL",$D72,IF($E72="TRIMESTRAL",$D72/3,IF($E72="SEMESTRAL",$D72/2,IF($E72="ANUAL",$D72/12,IF($E72="BIMENSUAL",$D72/2))))) -> 50 | H72: NO | I72: =IF($H72="NO",IF($E72="MENSUAL",$D72,IF($E72="TRIMESTRAL",$D72/3,IF($E72="SEMESTRAL",$D72/2,IF($E72="ANUAL",$D72/12,IF($E72="BIMENSUAL",$D72/2))))),0) -> 50 | K72: NO | L72: =IF($H72="NO",IF($E72="MENSUAL",$D72,IF($E72="TRIMESTRAL",$D72/3,IF($E72="SEMESTRAL",$D72/2,IF($E72="ANUAL",$D72/12,IF($E72="BIMENSUAL",$D72/2))))),0) -> 50 | N72: NO | O72: =IF($N72="NO",IF($E72="MENSUAL",$D72,IF($E72="TRIMESTRAL",$D72/3,IF($E72="SEMESTRAL",$D72/2,IF($E72="ANUAL",$D72/12,IF($E72="BIMENSUAL",$D72/2))))),0) -> 50 | Q72: NO | R72: =IF($Q72="NO",IF($E72="MENSUAL",$D72,IF($E72="TRIMESTRAL",$D72/3,IF($E72="SEMESTRAL",$D72/2,IF($E72="ANUAL",$D72/12,IF($E72="BIMENSUAL",$D72/2))))),0) -> 50 | T72: NO | U72: =IF($T72="NO",IF($E72="MENSUAL",$D72,IF($E72="TRIMESTRAL",$D72/3,IF($E72="SEMESTRAL",$D72/2,IF($E72="ANUAL",$D72/12,IF($E72="BIMENSUAL",$D72/2))))),0) -> 50
A73: POLIDEPORTIVO | B73: SANTANDER | C73: OCIO | D73: 230 | E73: ANUAL | F73: =IF($E73="MENSUAL",$D73,IF($E73="TRIMESTRAL",$D73/3,IF($E73="SEMESTRAL",$D73/2,IF($E73="ANUAL",$D73/12,IF($E73="BIMENSUAL",$D73/2))))) -> 19.166667 | H73: NO | I73: =IF($H73="NO",IF($E73="MENSUAL",$D73,IF($E73="TRIMESTRAL",$D73/3,IF($E73="SEMESTRAL",$D73/2,IF($E73="ANUAL",$D73/12,IF($E73="BIMENSUAL",$D73/2))))),0) -> 19.166667 | K73: NO | L73: =IF($H73="NO",IF($E73="MENSUAL",$D73,IF($E73="TRIMESTRAL",$D73/3,IF($E73="SEMESTRAL",$D73/2,IF($E73="ANUAL",$D73/12,IF($E73="BIMENSUAL",$D73/2))))),0) -> 19.166667 | N73: NO | O73: =IF($N73="NO",IF($E73="MENSUAL",$D73,IF($E73="TRIMESTRAL",$D73/3,IF($E73="SEMESTRAL",$D73/2,IF($E73="ANUAL",$D73/12,IF($E73="BIMENSUAL",$D73/2))))),0) -> 19.166667 | Q73: NO | R73: =IF($Q73="NO",IF($E73="MENSUAL",$D73,IF($E73="TRIMESTRAL",$D73/3,IF($E73="SEMESTRAL",$D73/2,IF($E73="ANUAL",$D73/12,IF($E73="BIMENSUAL",$D73/2))))),0) -> 19.166667 | T73: NO | U73: =IF($T73="NO",IF($E73="MENSUAL",$D73,IF($E73="TRIMESTRAL",$D73/3,IF($E73="SEMESTRAL",$D73/2,IF($E73="ANUAL",$D73/12,IF($E73="BIMENSUAL",$D73/2))))),0) -> 19.166667
... A91: XBOX GAME PASS ULTIMATE | B91: SANTANDER | C91: OCIO | D91: 0 | E91: MENSUAL | F91: =IF($E91="MENSUAL",$D91,IF($E91="TRIMESTRAL",$D91/3,IF($E91="SEMESTRAL",$D91/2,IF($E91="ANUAL",$D91/12,IF($E91="BIMENSUAL",$D91/2))))) -> 0 | H91: SI | I91: =IF($H91="NO",IF($E91="MENSUAL",$D91,IF($E91="TRIMESTRAL",$D91/3,IF($E91="SEMESTRAL",$D91/2,IF($E91="ANUAL",$D91/12,IF($E91="BIMENSUAL",$D91/2))))),0) -> 0 | K91: SI | L91: =IF($H91="NO",IF($E91="MENSUAL",$D91,IF($E91="TRIMESTRAL",$D91/3,IF($E91="SEMESTRAL",$D91/2,IF($E91="ANUAL",$D91/12,IF($E91="BIMENSUAL",$D91/2))))),0) -> 0 | N91: SI | O91: =IF($N91="NO",IF($E91="MENSUAL",$D91,IF($E91="TRIMESTRAL",$D91/3,IF($E91="SEMESTRAL",$D91/2,IF($E91="ANUAL",$D91/12,IF($E91="BIMENSUAL",$D91/2))))),0) -> 0 | Q91: SI | R91: =IF($Q91="NO",IF($E91="MENSUAL",$D91,IF($E91="TRIMESTRAL",$D91/3,IF($E91="SEMESTRAL",$D91/2,IF($E91="ANUAL",$D91/12,IF($E91="BIMENSUAL",$D91/2))))),0) -> 0 | T91: SI | U91: =IF($T91="NO",IF($E91="MENSUAL",$D91,IF($E91="TRIMESTRAL",$D91/3,IF($E91="SEMESTRAL",$D91/2,IF($E91="ANUAL",$D91/12,IF($E91="BIMENSUAL",$D91/2))))),0) -> 0
A92: OFFICE 365 | B92: SANTANDER | C92: OCIO | D92: 13 | E92: MENSUAL | F92: =IF($E92="MENSUAL",$D92,IF($E92="TRIMESTRAL",$D92/3,IF($E92="SEMESTRAL",$D92/2,IF($E92="ANUAL",$D92/12,IF($E92="BIMENSUAL",$D92/2))))) -> 13 | G92: X | H92: NO | I92: =IF($H92="NO",IF($E92="MENSUAL",$D92,IF($E92="TRIMESTRAL",$D92/3,IF($E92="SEMESTRAL",$D92/2,IF($E92="ANUAL",$D92/12,IF($E92="BIMENSUAL",$D92/2))))),0) -> 13 | K92: NO | L92: =IF($H92="NO",IF($E92="MENSUAL",$D92,IF($E92="TRIMESTRAL",$D92/3,IF($E92="SEMESTRAL",$D92/2,IF($E92="ANUAL",$D92/12,IF($E92="BIMENSUAL",$D92/2))))),0) -> 13 | N92: SI | O92: =IF($N92="NO",IF($E92="MENSUAL",$D92,IF($E92="TRIMESTRAL",$D92/3,IF($E92="SEMESTRAL",$D92/2,IF($E92="ANUAL",$D92/12,IF($E92="BIMENSUAL",$D92/2))))),0) -> 0 | Q92: NO | R92: =IF($Q92="NO",IF($E92="MENSUAL",$D92,IF($E92="TRIMESTRAL",$D92/3,IF($E92="SEMESTRAL",$D92/2,IF($E92="ANUAL",$D92/12,IF($E92="BIMENSUAL",$D92/2))))),0) -> 13 | T92: NO | U92: =IF($T92="NO",IF($E92="MENSUAL",$D92,IF($E92="TRIMESTRAL",$D92/3,IF($E92="SEMESTRAL",$D92/2,IF($E92="ANUAL",$D92/12,IF($E92="BIMENSUAL",$D92/2))))),0) -> 13
A93: ADOBE CREATIVE CLOUD | B93: SANTANDER | C93: OCIO | D93: 0 | E93: MENSUAL | F93: =IF($E93="MENSUAL",$D93,IF($E93="TRIMESTRAL",$D93/3,IF($E93="SEMESTRAL",$D93/2,IF($E93="ANUAL",$D93/12,IF($E93="BIMENSUAL",$D93/2))))) -> 0 | H93: SI | I93: =IF($H93="NO",IF($E93="MENSUAL",$D93,IF($E93="TRIMESTRAL",$D93/3,IF($E93="SEMESTRAL",$D93/2,IF($E93="ANUAL",$D93/12,IF($E93="BIMENSUAL",$D93/2))))),0) -> 0 | K93: SI | L93: =IF($H93="NO",IF($E93="MENSUAL",$D93,IF($E93="TRIMESTRAL",$D93/3,IF($E93="SEMESTRAL",$D93/2,IF($E93="ANUAL",$D93/12,IF($E93="BIMENSUAL",$D93/2))))),0) -> 0 | N93: SI | O93: =IF($N93="NO",IF($E93="MENSUAL",$D93,IF($E93="TRIMESTRAL",$D93/3,IF($E93="SEMESTRAL",$D93/2,IF($E93="ANUAL",$D93/12,IF($E93="BIMENSUAL",$D93/2))))),0) -> 0 | Q93: SI | R93: =IF($Q93="NO",IF($E93="MENSUAL",$D93,IF($E93="TRIMESTRAL",$D93/3,IF($E93="SEMESTRAL",$D93/2,IF($E93="ANUAL",$D93/12,IF($E93="BIMENSUAL",$D93/2))))),0) -> 0 | T93: SI | U93: =IF($T93="NO",IF($E93="MENSUAL",$D93,IF($E93="TRIMESTRAL",$D93/3,IF($E93="SEMESTRAL",$D93/2,IF($E93="ANUAL",$D93/12,IF($E93="BIMENSUAL",$D93/2))))),0) -> 0
A94: DOMESTIKA | B94: SANTANDER | C94: OCIO | D94: 0 | E94: MENSUAL | F94: =IF($E94="MENSUAL",$D94,IF($E94="TRIMESTRAL",$D94/3,IF($E94="SEMESTRAL",$D94/2,IF($E94="ANUAL",$D94/12,IF($E94="BIMENSUAL",$D94/2))))) -> 0 | H94: SI | I94: =IF($H94="NO",IF($E94="MENSUAL",$D94,IF($E94="TRIMESTRAL",$D94/3,IF($E94="SEMESTRAL",$D94/2,IF($E94="ANUAL",$D94/12,IF($E94="BIMENSUAL",$D94/2))))),0) -> 0 | K94: SI | L94: =IF($H94="NO",IF($E94="MENSUAL",$D94,IF($E94="TRIMESTRAL",$D94/3,IF($E94="SEMESTRAL",$D94/2,IF($E94="ANUAL",$D94/12,IF($E94="BIMENSUAL",$D94/2))))),0) -> 0 | N94: SI | O94: =IF($N94="NO",IF($E94="MENSUAL",$D94,IF($E94="TRIMESTRAL",$D94/3,IF($E94="SEMESTRAL",$D94/2,IF($E94="ANUAL",$D94/12,IF($E94="BIMENSUAL",$D94/2))))),0) -> 0 | Q94: SI | R94: =IF($Q94="NO",IF($E94="MENSUAL",$D94,IF($E94="TRIMESTRAL",$D94/3,IF($E94="SEMESTRAL",$D94/2,IF($E94="ANUAL",$D94/12,IF($E94="BIMENSUAL",$D94/2))))),0) -> 0 | T94: SI | U94: =IF($T94="NO",IF($E94="MENSUAL",$D94,IF($E94="TRIMESTRAL",$D94/3,IF($E94="SEMESTRAL",$D94/2,IF($E94="ANUAL",$D94/12,IF($E94="BIMENSUAL",$D94/2))))),0) -> 0
A95: SERVICIO DIETA | B95: SANTANDER | C95: OCIO | D95: 0 | E95: MENSUAL | F95: =IF($E95="MENSUAL",$D95,IF($E95="TRIMESTRAL",$D95/3,IF($E95="SEMESTRAL",$D95/2,IF($E95="ANUAL",$D95/12,IF($E95="BIMENSUAL",$D95/2))))) -> 0 | H95: SI | I95: =IF($H95="NO",IF($E95="MENSUAL",$D95,IF($E95="TRIMESTRAL",$D95/3,IF($E95="SEMESTRAL",$D95/2,IF($E95="ANUAL",$D95/12,IF($E95="BIMENSUAL",$D95/2))))),0) -> 0 | K95: SI | L95: =IF($H95="NO",IF($E95="MENSUAL",$D95,IF($E95="TRIMESTRAL",$D95/3,IF($E95="SEMESTRAL",$D95/2,IF($E95="ANUAL",$D95/12,IF($E95="BIMENSUAL",$D95/2))))),0) -> 0 | N95: SI | O95: =IF($N95="NO",IF($E95="MENSUAL",$D95,IF($E95="TRIMESTRAL",$D95/3,IF($E95="SEMESTRAL",$D95/2,IF($E95="ANUAL",$D95/12,IF($E95="BIMENSUAL",$D95/2))))),0) -> 0 | Q95: SI | R95: =IF($Q95="NO",IF($E95="MENSUAL",$D95,IF($E95="TRIMESTRAL",$D95/3,IF($E95="SEMESTRAL",$D95/2,IF($E95="ANUAL",$D95/12,IF($E95="BIMENSUAL",$D95/2))))),0) -> 0 | T95: SI | U95: =IF($T95="NO",IF($E95="MENSUAL",$D95,IF($E95="TRIMESTRAL",$D95/3,IF($E95="SEMESTRAL",$D95/2,IF($E95="ANUAL",$D95/12,IF($E95="BIMENSUAL",$D95/2))))),0) -> 0
A96: SERVICIO FITNESS | B96: SANTANDER | C96: OCIO | D96: 0 | E96: MENSUAL | F96: =IF($E96="MENSUAL",$D96,IF($E96="TRIMESTRAL",$D96/3,IF($E96="SEMESTRAL",$D96/2,IF($E96="ANUAL",$D96/12,IF($E96="BIMENSUAL",$D96/2))))) -> 0 | H96: SI | I96: =IF($H96="NO",IF($E96="MENSUAL",$D96,IF($E96="TRIMESTRAL",$D96/3,IF($E96="SEMESTRAL",$D96/2,IF($E96="ANUAL",$D96/12,IF($E96="BIMENSUAL",$D96/2))))),0) -> 0 | K96: SI | L96: =IF($H96="NO",IF($E96="MENSUAL",$D96,IF($E96="TRIMESTRAL",$D96/3,IF($E96="SEMESTRAL",$D96/2,IF($E96="ANUAL",$D96/12,IF($E96="BIMENSUAL",$D96/2))))),0) -> 0 | N96: SI | O96: =IF($N96="NO",IF($E96="MENSUAL",$D96,IF($E96="TRIMESTRAL",$D96/3,IF($E96="SEMESTRAL",$D96/2,IF($E96="ANUAL",$D96/12,IF($E96="BIMENSUAL",$D96/2))))),0) -> 0 | Q96: SI | R96: =IF($Q96="NO",IF($E96="MENSUAL",$D96,IF($E96="TRIMESTRAL",$D96/3,IF($E96="SEMESTRAL",$D96/2,IF($E96="ANUAL",$D96/12,IF($E96="BIMENSUAL",$D96/2))))),0) -> 0 | T96: SI | U96: =IF($T96="NO",IF($E96="MENSUAL",$D96,IF($E96="TRIMESTRAL",$D96/3,IF($E96="SEMESTRAL",$D96/2,IF($E96="ANUAL",$D96/12,IF($E96="BIMENSUAL",$D96/2))))),0) -> 0
A97: GOOGLE ONE | B97: SANTANDER | C97: OCIO | D97: 20 | E97: ANUAL | F97: =IF($E97="MENSUAL",$D97,IF($E97="TRIMESTRAL",$D97/3,IF($E97="SEMESTRAL",$D97/2,IF($E97="ANUAL",$D97/12,IF($E97="BIMENSUAL",$D97/2))))) -> 1.6666667 | H97: NO | I97: =IF($H97="NO",IF($E97="MENSUAL",$D97,IF($E97="TRIMESTRAL",$D97/3,IF($E97="SEMESTRAL",$D97/2,IF($E97="ANUAL",$D97/12,IF($E97="BIMENSUAL",$D97/2))))),0) -> 1.6666667 | K97: NO | L97: =IF($H97="NO",IF($E97="MENSUAL",$D97,IF($E97="TRIMESTRAL",$D97/3,IF($E97="SEMESTRAL",$D97/2,IF($E97="ANUAL",$D97/12,IF($E97="BIMENSUAL",$D97/2))))),0) -> 1.6666667 | N97: SI | O97: =IF($N97="NO",IF($E97="MENSUAL",$D97,IF($E97="TRIMESTRAL",$D97/3,IF($E97="SEMESTRAL",$D97/2,IF($E97="ANUAL",$D97/12,IF($E97="BIMENSUAL",$D97/2))))),0) -> 0 | Q97: NO | R97: =IF($Q97="NO",IF($E97="MENSUAL",$D97,IF($E97="TRIMESTRAL",$D97/3,IF($E97="SEMESTRAL",$D97/2,IF($E97="ANUAL",$D97/12,IF($E97="BIMENSUAL",$D97/2))))),0) -> 1.6666667 | T97: NO | U97: =IF($T97="NO",IF($E97="MENSUAL",$D97,IF($E97="TRIMESTRAL",$D97/3,IF($E97="SEMESTRAL",$D97/2,IF($E97="ANUAL",$D97/12,IF($E97="BIMENSUAL",$D97/2))))),0) -> 1.6666667
A98: HP INSTANTK | B98: SANTANDER | C98: OCIO | D98: 0 | E98: MENSUAL | F98: =IF($E98="MENSUAL",$D98,IF($E98="TRIMESTRAL",$D98/3,IF($E98="SEMESTRAL",$D98/2,IF($E98="ANUAL",$D98/12,IF($E98="BIMENSUAL",$D98/2))))) -> 0 | H98: SI | I98: =IF($H98="NO",IF($E98="MENSUAL",$D98,IF($E98="TRIMESTRAL",$D98/3,IF($E98="SEMESTRAL",$D98/2,IF($E98="ANUAL",$D98/12,IF($E98="BIMENSUAL",$D98/2))))),0) -> 0 | K98: SI | L98: =IF($H98="NO",IF($E98="MENSUAL",$D98,IF($E98="TRIMESTRAL",$D98/3,IF($E98="SEMESTRAL",$D98/2,IF($E98="ANUAL",$D98/12,IF($E98="BIMENSUAL",$D98/2))))),0) -> 0 | N98: SI | O98: =IF($N98="NO",IF($E98="MENSUAL",$D98,IF($E98="TRIMESTRAL",$D98/3,IF($E98="SEMESTRAL",$D98/2,IF($E98="ANUAL",$D98/12,IF($E98="BIMENSUAL",$D98/2))))),0) -> 0 | Q98: SI | R98: =IF($Q98="NO",IF($E98="MENSUAL",$D98,IF($E98="TRIMESTRAL",$D98/3,IF($E98="SEMESTRAL",$D98/2,IF($E98="ANUAL",$D98/12,IF($E98="BIMENSUAL",$D98/2))))),0) -> 0 | T98: SI | U98: =IF($T98="NO",IF($E98="MENSUAL",$D98,IF($E98="TRIMESTRAL",$D98/3,IF($E98="SEMESTRAL",$D98/2,IF($E98="ANUAL",$D98/12,IF($E98="BIMENSUAL",$D98/2))))),0) -> 0
A99: PRESTAMO OLATZ | B99: SANTANDER | C99: PRESTAMO | D99: 400 | E99: MENSUAL | F99: =IF($E99="MENSUAL",$D99,IF($E99="TRIMESTRAL",$D99/3,IF($E99="SEMESTRAL",$D99/2,IF($E99="ANUAL",$D99/12,IF($E99="BIMENSUAL",$D99/2))))) -> 400 | H99: SI | I99: =IF($H99="NO",IF($E99="MENSUAL",$D99,IF($E99="TRIMESTRAL",$D99/3,IF($E99="SEMESTRAL",$D99/2,IF($E99="ANUAL",$D99/12,IF($E99="BIMENSUAL",$D99/2))))),0) -> 0 | K99: SI | L99: =IF($H99="NO",IF($E99="MENSUAL",$D99,IF($E99="TRIMESTRAL",$D99/3,IF($E99="SEMESTRAL",$D99/2,IF($E99="ANUAL",$D99/12,IF($E99="BIMENSUAL",$D99/2))))),0) -> 0 | N99: SI | O99: =IF($N99="NO",IF($E99="MENSUAL",$D99,IF($E99="TRIMESTRAL",$D99/3,IF($E99="SEMESTRAL",$D99/2,IF($E99="ANUAL",$D99/12,IF($E99="BIMENSUAL",$D99/2))))),0) -> 0 | Q99: SI | R99: =IF($Q99="NO",IF($E99="MENSUAL",$D99,IF($E99="TRIMESTRAL",$D99/3,IF($E99="SEMESTRAL",$D99/2,IF($E99="ANUAL",$D99/12,IF($E99="BIMENSUAL",$D99/2))))),0) -> 0 | T99: SI | U99: =IF($T99="NO",IF($E99="MENSUAL",$D99,IF($E99="TRIMESTRAL",$D99/3,IF($E99="SEMESTRAL",$D99/2,IF($E99="ANUAL",$D99/12,IF($E99="BIMENSUAL",$D99/2))))),0) -> 0
A100: IBERDROLA ARDANZA | B100: KUTXA | C100: LOCALES | D100: 14 | E100: MENSUAL | F100: =IF($E100="MENSUAL",$D100,IF($E100="TRIMESTRAL",$D100/3,IF($E100="SEMESTRAL",$D100/2,IF($E100="ANUAL",$D100/12,IF($E100="BIMENSUAL",$D100/2))))) -> 14 | H100: SI | I100: =IF($H100="NO",IF($E100="MENSUAL",$D100,IF($E100="TRIMESTRAL",$D100/3,IF($E100="SEMESTRAL",$D100/2,IF($E100="ANUAL",$D100/12,IF($E100="BIMENSUAL",$D100/2))))),0) -> 0 | K100: SI | L100: =IF($H100="NO",IF($E100="MENSUAL",$D100,IF($E100="TRIMESTRAL",$D100/3,IF($E100="SEMESTRAL",$D100/2,IF($E100="ANUAL",$D100/12,IF($E100="BIMENSUAL",$D100/2))))),0) -> 0 | N100: SI | O100: =IF($N100="NO",IF($E100="MENSUAL",$D100,IF($E100="TRIMESTRAL",$D100/3,IF($E100="SEMESTRAL",$D100/2,IF($E100="ANUAL",$D100/12,IF($E100="BIMENSUAL",$D100/2))))),0) -> 0 | Q100: SI | R100: =IF($Q100="NO",IF($E100="MENSUAL",$D100,IF($E100="TRIMESTRAL",$D100/3,IF($E100="SEMESTRAL",$D100/2,IF($E100="ANUAL",$D100/12,IF($E100="BIMENSUAL",$D100/2))))),0) -> 0 | T100: SI | U100: =IF($T100="NO",IF($E100="MENSUAL",$D100,IF($E100="TRIMESTRAL",$D100/3,IF($E100="SEMESTRAL",$D100/2,IF($E100="ANUAL",$D100/12,IF($E100="BIMENSUAL",$D100/2))))),0) -> 0
A101: AGUA ARDANZA | B101: KUTXA | C101: LOCALES | D101: 85 | E101: TRIMESTRAL | F101: =IF($E101="MENSUAL",$D101,IF($E101="TRIMESTRAL",$D101/3,IF($E101="SEMESTRAL",$D101/2,IF($E101="ANUAL",$D101/12,IF($E101="BIMENSUAL",$D101/2))))) -> 28.333333 | H101: SI | I101: =IF($H101="NO",IF($E101="MENSUAL",$D101,IF($E101="TRIMESTRAL",$D101/3,IF($E101="SEMESTRAL",$D101/2,IF($E101="ANUAL",$D101/12,IF($E101="BIMENSUAL",$D101/2))))),0) -> 0 | K101: SI | L101: =IF($H101="NO",IF($E101="MENSUAL",$D101,IF($E101="TRIMESTRAL",$D101/3,IF($E101="SEMESTRAL",$D101/2,IF($E101="ANUAL",$D101/12,IF($E101="BIMENSUAL",$D101/2))))),0) -> 0 | N101: SI | O101: =IF($N101="NO",IF($E101="MENSUAL",$D101,IF($E101="TRIMESTRAL",$D101/3,IF($E101="SEMESTRAL",$D101/2,IF($E101="ANUAL",$D101/12,IF($E101="BIMENSUAL",$D101/2))))),0) -> 0 | Q101: SI | R101: =IF($Q101="NO",IF($E101="MENSUAL",$D101,IF($E101="TRIMESTRAL",$D101/3,IF($E101="SEMESTRAL",$D101/2,IF($E101="ANUAL",$D101/12,IF($E101="BIMENSUAL",$D101/2))))),0) -> 0 | T101: SI | U101: =IF($T101="NO",IF($E101="MENSUAL",$D101,IF($E101="TRIMESTRAL",$D101/3,IF($E101="SEMESTRAL",$D101/2,IF($E101="ANUAL",$D101/12,IF($E101="BIMENSUAL",$D101/2))))),0) -> 0
A102: IBI ARDANZA | B102: KUTXA | C102: LOCALES | D102: 85 | E102: ANUAL | F102: =IF($E102="MENSUAL",$D102,IF($E102="TRIMESTRAL",$D102/3,IF($E102="SEMESTRAL",$D102/2,IF($E102="ANUAL",$D102/12,IF($E102="BIMENSUAL",$D102/2))))) -> 7.0833333 | H102: SI | I102: =IF($H102="NO",IF($E102="MENSUAL",$D102,IF($E102="TRIMESTRAL",$D102/3,IF($E102="SEMESTRAL",$D102/2,IF($E102="ANUAL",$D102/12,IF($E102="BIMENSUAL",$D102/2))))),0) -> 0 | K102: SI | L102: =IF($H102="NO",IF($E102="MENSUAL",$D102,IF($E102="TRIMESTRAL",$D102/3,IF($E102="SEMESTRAL",$D102/2,IF($E102="ANUAL",$D102/12,IF($E102="BIMENSUAL",$D102/2))))),0) -> 0 | N102: SI | O102: =IF($N102="NO",IF($E102="MENSUAL",$D102,IF($E102="TRIMESTRAL",$D102/3,IF($E102="SEMESTRAL",$D102/2,IF($E102="ANUAL",$D102/12,IF($E102="BIMENSUAL",$D102/2))))),0) -> 0 | Q102: SI | R102: =IF($Q102="NO",IF($E102="MENSUAL",$D102,IF($E102="TRIMESTRAL",$D102/3,IF($E102="SEMESTRAL",$D102/2,IF($E102="ANUAL",$D102/12,IF($E102="BIMENSUAL",$D102/2))))),0) -> 0 | T102: SI | U102: =IF($T102="NO",IF($E102="MENSUAL",$D102,IF($E102="TRIMESTRAL",$D102/3,IF($E102="SEMESTRAL",$D102/2,IF($E102="ANUAL",$D102/12,IF($E102="BIMENSUAL",$D102/2))))),0) -> 0
A103: SEGURO ARDANZA (AXA) | B103: KUTXA | C103: LOCALES | D103: 150 | E103: ANUAL | F103: =IF($E103="MENSUAL",$D103,IF($E103="TRIMESTRAL",$D103/3,IF($E103="SEMESTRAL",$D103/2,IF($E103="ANUAL",$D103/12,IF($E103="BIMENSUAL",$D103/2))))) -> 12.5 | H103: SI | I103: =IF($H103="NO",IF($E103="MENSUAL",$D103,IF($E103="TRIMESTRAL",$D103/3,IF($E103="SEMESTRAL",$D103/2,IF($E103="ANUAL",$D103/12,IF($E103="BIMENSUAL",$D103/2))))),0) -> 0 | K103: SI | L103: =IF($H103="NO",IF($E103="MENSUAL",$D103,IF($E103="TRIMESTRAL",$D103/3,IF($E103="SEMESTRAL",$D103/2,IF($E103="ANUAL",$D103/12,IF($E103="BIMENSUAL",$D103/2))))),0) -> 0 | N103: SI | O103: =IF($N103="NO",IF($E103="MENSUAL",$D103,IF($E103="TRIMESTRAL",$D103/3,IF($E103="SEMESTRAL",$D103/2,IF($E103="ANUAL",$D103/12,IF($E103="BIMENSUAL",$D103/2))))),0) -> 0 | Q103: SI | R103: =IF($Q103="NO",IF($E103="MENSUAL",$D103,IF($E103="TRIMESTRAL",$D103/3,IF($E103="SEMESTRAL",$D103/2,IF($E103="ANUAL",$D103/12,IF($E103="BIMENSUAL",$D103/2))))),0) -> 0 | T103: SI | U103: =IF($T103="NO",IF($E103="MENSUAL",$D103,IF($E103="TRIMESTRAL",$D103/3,IF($E103="SEMESTRAL",$D103/2,IF($E103="ANUAL",$D103/12,IF($E103="BIMENSUAL",$D103/2))))),0) -> 0
A104: DERRAMA ARDANZA | B104: KUTXA | C104: LOCALES | D104: 200 | E104: ANUAL | F104: =IF($E104="MENSUAL",$D104,IF($E104="TRIMESTRAL",$D104/3,IF($E104="SEMESTRAL",$D104/2,IF($E104="ANUAL",$D104/12,IF($E104="BIMENSUAL",$D104/2))))) -> 16.666667 | H104: SI | I104: =IF($H104="NO",IF($E104="MENSUAL",$D104,IF($E104="TRIMESTRAL",$D104/3,IF($E104="SEMESTRAL",$D104/2,IF($E104="ANUAL",$D104/12,IF($E104="BIMENSUAL",$D104/2))))),0) -> 0 | K104: SI | L104: =IF($H104="NO",IF($E104="MENSUAL",$D104,IF($E104="TRIMESTRAL",$D104/3,IF($E104="SEMESTRAL",$D104/2,IF($E104="ANUAL",$D104/12,IF($E104="BIMENSUAL",$D104/2))))),0) -> 0 | N104: SI | O104: =IF($N104="NO",IF($E104="MENSUAL",$D104,IF($E104="TRIMESTRAL",$D104/3,IF($E104="SEMESTRAL",$D104/2,IF($E104="ANUAL",$D104/12,IF($E104="BIMENSUAL",$D104/2))))),0) -> 0 | Q104: SI | R104: =IF($Q104="NO",IF($E104="MENSUAL",$D104,IF($E104="TRIMESTRAL",$D104/3,IF($E104="SEMESTRAL",$D104/2,IF($E104="ANUAL",$D104/12,IF($E104="BIMENSUAL",$D104/2))))),0) -> 0 | T104: SI | U104: =IF($T104="NO",IF($E104="MENSUAL",$D104,IF($E104="TRIMESTRAL",$D104/3,IF($E104="SEMESTRAL",$D104/2,IF($E104="ANUAL",$D104/12,IF($E104="BIMENSUAL",$D104/2))))),0) -> 0
... A109: DERRAMA URKI BAJO | B109: KUTXA | C109: LOCALES | D109: 200 | E109: ANUAL | F109: =IF($E109="MENSUAL",$D109,IF($E109="TRIMESTRAL",$D109/3,IF($E109="SEMESTRAL",$D109/2,IF($E109="ANUAL",$D109/12,IF($E109="BIMENSUAL",$D109/2))))) -> 16.666667 | H109: NO | I109: =IF($H109="NO",IF($E109="MENSUAL",$D109,IF($E109="TRIMESTRAL",$D109/3,IF($E109="SEMESTRAL",$D109/2,IF($E109="ANUAL",$D109/12,IF($E109="BIMENSUAL",$D109/2))))),0) -> 16.666667 | K109: NO | L109: =IF($H109="NO",IF($E109="MENSUAL",$D109,IF($E109="TRIMESTRAL",$D109/3,IF($E109="SEMESTRAL",$D109/2,IF($E109="ANUAL",$D109/12,IF($E109="BIMENSUAL",$D109/2))))),0) -> 16.666667 | N109: NO | O109: =IF($N109="NO",IF($E109="MENSUAL",$D109,IF($E109="TRIMESTRAL",$D109/3,IF($E109="SEMESTRAL",$D109/2,IF($E109="ANUAL",$D109/12,IF($E109="BIMENSUAL",$D109/2))))),0) -> 16.666667 | Q109: SI | R109: =IF($Q109="NO",IF($E109="MENSUAL",$D109,IF($E109="TRIMESTRAL",$D109/3,IF($E109="SEMESTRAL",$D109/2,IF($E109="ANUAL",$D109/12,IF($E109="BIMENSUAL",$D109/2))))),0) -> 0 | T109: SI | U109: =IF($T109="NO",IF($E109="MENSUAL",$D109,IF($E109="TRIMESTRAL",$D109/3,IF($E109="SEMESTRAL",$D109/2,IF($E109="ANUAL",$D109/12,IF($E109="BIMENSUAL",$D109/2))))),0) -> 0
A110: INTERNET URKI BAJO | B110: KUTXA | C110: LOCALES | D110: 30 | E110: MENSUAL | F110: =IF($E110="MENSUAL",$D110,IF($E110="TRIMESTRAL",$D110/3,IF($E110="SEMESTRAL",$D110/2,IF($E110="ANUAL",$D110/12,IF($E110="BIMENSUAL",$D110/2))))) -> 30 | H110: SI | I110: =IF($H110="NO",IF($E110="MENSUAL",$D110,IF($E110="TRIMESTRAL",$D110/3,IF($E110="SEMESTRAL",$D110/2,IF($E110="ANUAL",$D110/12,IF($E110="BIMENSUAL",$D110/2))))),0) -> 0 | K110: SI | L110: =IF($H110="NO",IF($E110="MENSUAL",$D110,IF($E110="TRIMESTRAL",$D110/3,IF($E110="SEMESTRAL",$D110/2,IF($E110="ANUAL",$D110/12,IF($E110="BIMENSUAL",$D110/2))))),0) -> 0 | N110: SI | Q110: SI | R110: =IF($Q110="NO",IF($E110="MENSUAL",$D110,IF($E110="TRIMESTRAL",$D110/3,IF($E110="SEMESTRAL",$D110/2,IF($E110="ANUAL",$D110/12,IF($E110="BIMENSUAL",$D110/2))))),0) -> 0 | T110: SI | U110: =IF($T110="NO",IF($E110="MENSUAL",$D110,IF($E110="TRIMESTRAL",$D110/3,IF($E110="SEMESTRAL",$D110/2,IF($E110="ANUAL",$D110/12,IF($E110="BIMENSUAL",$D110/2))))),0) -> 0
A111: 1&1 (PIXDEMIA) | B111: KUTXA | C111: OCIO | D111: 17 | E111: MENSUAL | F111: =IF($E111="MENSUAL",$D111,IF($E111="TRIMESTRAL",$D111/3,IF($E111="SEMESTRAL",$D111/2,IF($E111="ANUAL",$D111/12,IF($E111="BIMENSUAL",$D111/2))))) -> 17 | H111: SI | I111: =IF($H111="NO",IF($E111="MENSUAL",$D111,IF($E111="TRIMESTRAL",$D111/3,IF($E111="SEMESTRAL",$D111/2,IF($E111="ANUAL",$D111/12,IF($E111="BIMENSUAL",$D111/2))))),0) -> 0 | K111: SI | L111: =IF($H111="NO",IF($E111="MENSUAL",$D111,IF($E111="TRIMESTRAL",$D111/3,IF($E111="SEMESTRAL",$D111/2,IF($E111="ANUAL",$D111/12,IF($E111="BIMENSUAL",$D111/2))))),0) -> 0 | N111: SI | O111: =IF($N111="NO",IF($E111="MENSUAL",$D111,IF($E111="TRIMESTRAL",$D111/3,IF($E111="SEMESTRAL",$D111/2,IF($E111="ANUAL",$D111/12,IF($E111="BIMENSUAL",$D111/2))))),0) -> 0 | Q111: SI | R111: =IF($Q111="NO",IF($E111="MENSUAL",$D111,IF($E111="TRIMESTRAL",$D111/3,IF($E111="SEMESTRAL",$D111/2,IF($E111="ANUAL",$D111/12,IF($E111="BIMENSUAL",$D111/2))))),0) -> 0 | T111: SI | U111: =IF($T111="NO",IF($E111="MENSUAL",$D111,IF($E111="TRIMESTRAL",$D111/3,IF($E111="SEMESTRAL",$D111/2,IF($E111="ANUAL",$D111/12,IF($E111="BIMENSUAL",$D111/2))))),0) -> 0
A112: SEGURO COCHE LEON (KUTXA) | B112: KUTXA | C112: COCHE | D112: 250 | E112: ANUAL | F112: =IF($E112="MENSUAL",$D112,IF($E112="TRIMESTRAL",$D112/3,IF($E112="SEMESTRAL",$D112/2,IF($E112="ANUAL",$D112/12,IF($E112="BIMENSUAL",$D112/2))))) -> 20.833333 | H112: NO | I112: =IF($H112="NO",IF($E112="MENSUAL",$D112,IF($E112="TRIMESTRAL",$D112/3,IF($E112="SEMESTRAL",$D112/2,IF($E112="ANUAL",$D112/12,IF($E112="BIMENSUAL",$D112/2))))),0) -> 20.833333 | K112: NO | L112: =IF($H112="NO",IF($E112="MENSUAL",$D112,IF($E112="TRIMESTRAL",$D112/3,IF($E112="SEMESTRAL",$D112/2,IF($E112="ANUAL",$D112/12,IF($E112="BIMENSUAL",$D112/2))))),0) -> 20.833333 | N112: NO | O112: =IF($N112="NO",IF($E112="MENSUAL",$D112,IF($E112="TRIMESTRAL",$D112/3,IF($E112="SEMESTRAL",$D112/2,IF($E112="ANUAL",$D112/12,IF($E112="BIMENSUAL",$D112/2))))),0) -> 20.833333 | Q112: NO | R112: =IF($Q112="NO",IF($E112="MENSUAL",$D112,IF($E112="TRIMESTRAL",$D112/3,IF($E112="SEMESTRAL",$D112/2,IF($E112="ANUAL",$D112/12,IF($E112="BIMENSUAL",$D112/2))))),0) -> 20.833333 | T112: NO | U112: =IF($T112="NO",IF($E112="MENSUAL",$D112,IF($E112="TRIMESTRAL",$D112/3,IF($E112="SEMESTRAL",$D112/2,IF($E112="ANUAL",$D112/12,IF($E112="BIMENSUAL",$D112/2))))),0) -> 20.833333
A113: SEGURO HOGAR (KUTXA) | B113: KUTXA | C113: CASA | D113: 266 | E113: ANUAL | F113: =IF($E113="MENSUAL",$D113,IF($E113="TRIMESTRAL",$D113/3,IF($E113="SEMESTRAL",$D113/2,IF($E113="ANUAL",$D113/12,IF($E113="BIMENSUAL",$D113/2))))) -> 22.166667 | H113: NO | I113: =IF($H113="NO",IF($E113="MENSUAL",$D113,IF($E113="TRIMESTRAL",$D113/3,IF($E113="SEMESTRAL",$D113/2,IF($E113="ANUAL",$D113/12,IF($E113="BIMENSUAL",$D113/2))))),0) -> 22.166667 | K113: NO | L113: =IF($H113="NO",IF($E113="MENSUAL",$D113,IF($E113="TRIMESTRAL",$D113/3,IF($E113="SEMESTRAL",$D113/2,IF($E113="ANUAL",$D113/12,IF($E113="BIMENSUAL",$D113/2))))),0) -> 22.166667 | N113: NO | O113: =IF($N113="NO",IF($E113="MENSUAL",$D113,IF($E113="TRIMESTRAL",$D113/3,IF($E113="SEMESTRAL",$D113/2,IF($E113="ANUAL",$D113/12,IF($E113="BIMENSUAL",$D113/2))))),0) -> 22.166667 | Q113: NO | R113: =IF($Q113="NO",IF($E113="MENSUAL",$D113,IF($E113="TRIMESTRAL",$D113/3,IF($E113="SEMESTRAL",$D113/2,IF($E113="ANUAL",$D113/12,IF($E113="BIMENSUAL",$D113/2))))),0) -> 22.166667 | T113: NO | U113: =IF($T113="NO",IF($E113="MENSUAL",$D113,IF($E113="TRIMESTRAL",$D113/3,IF($E113="SEMESTRAL",$D113/2,IF($E113="ANUAL",$D113/12,IF($E113="BIMENSUAL",$D113/2))))),0) -> 22.166667
A114: GASTOS | B114: KUTXA | C114: GASTOS | D114: 1400 | E114: MENSUAL | F114: =IF($E114="MENSUAL",$D114,IF($E114="TRIMESTRAL",$D114/3,IF($E114="SEMESTRAL",$D114/2,IF($E114="ANUAL",$D114/12,IF($E114="BIMENSUAL",$D114/2))))) -> 1400 | H114: NO | I114: =IF($H114="NO",IF($E114="MENSUAL",$D114,IF($E114="TRIMESTRAL",$D114/3,IF($E114="SEMESTRAL",$D114/2,IF($E114="ANUAL",$D114/12,IF($E114="BIMENSUAL",$D114/2))))),0) -> 1400 | K114: NO | L114: =IF($H114="NO",IF($E114="MENSUAL",$D114,IF($E114="TRIMESTRAL",$D114/3,IF($E114="SEMESTRAL",$D114/2,IF($E114="ANUAL",$D114/12,IF($E114="BIMENSUAL",$D114/2))))),0) -> 1400 | N114: NO | O114: =IF($N114="NO",IF($E114="MENSUAL",$D114,IF($E114="TRIMESTRAL",$D114/3,IF($E114="SEMESTRAL",$D114/2,IF($E114="ANUAL",$D114/12,IF($E114="BIMENSUAL",$D114/2))))),0) -> 1400 | Q114: NO | R114: =IF($Q114="NO",IF($E114="MENSUAL",$D114,IF($E114="TRIMESTRAL",$D114/3,IF($E114="SEMESTRAL",$D114/2,IF($E114="ANUAL",$D114/12,IF($E114="BIMENSUAL",$D114/2))))),0) -> 1400 | T114: NO | U114: =IF($T114="NO",IF($E114="MENSUAL",$D114,IF($E114="TRIMESTRAL",$D114/3,IF($E114="SEMESTRAL",$D114/2,IF($E114="ANUAL",$D114/12,IF($E114="BIMENSUAL",$D114/2))))),0) -> 1400
A115: PAGA OLATZ | B115: KUTXA | C115: PAGAS | D115: 100 | E115: MENSUAL | F115: =IF($E115="MENSUAL",$D115,IF($E115="TRIMESTRAL",$D115/3,IF($E115="SEMESTRAL",$D115/2,IF($E115="ANUAL",$D115/12,IF($E115="BIMENSUAL",$D115/2))))) -> 100 | H115: NO | I115: =IF($H115="NO",IF($E115="MENSUAL",$D115,IF($E115="TRIMESTRAL",$D115/3,IF($E115="SEMESTRAL",$D115/2,IF($E115="ANUAL",$D115/12,IF($E115="BIMENSUAL",$D115/2))))),0) -> 100 | K115: NO | L115: =IF($H115="NO",IF($E115="MENSUAL",$D115,IF($E115="TRIMESTRAL",$D115/3,IF($E115="SEMESTRAL",$D115/2,IF($E115="ANUAL",$D115/12,IF($E115="BIMENSUAL",$D115/2))))),0) -> 100 | N115: NO | O115: =IF($N115="NO",IF($E115="MENSUAL",$D115,IF($E115="TRIMESTRAL",$D115/3,IF($E115="SEMESTRAL",$D115/2,IF($E115="ANUAL",$D115/12,IF($E115="BIMENSUAL",$D115/2))))),0) -> 100 | Q115: NO | R115: =IF($Q115="NO",IF($E115="MENSUAL",$D115,IF($E115="TRIMESTRAL",$D115/3,IF($E115="SEMESTRAL",$D115/2,IF($E115="ANUAL",$D115/12,IF($E115="BIMENSUAL",$D115/2))))),0) -> 100 | T115: NO | U115: =IF($T115="NO",IF($E115="MENSUAL",$D115,IF($E115="TRIMESTRAL",$D115/3,IF($E115="SEMESTRAL",$D115/2,IF($E115="ANUAL",$D115/12,IF($E115="BIMENSUAL",$D115/2))))),0) -> 100
A116: PAGA AMAIA | B116: KUTXA | C116: PAGAS | D116: 100 | E116: MENSUAL | F116: =IF($E116="MENSUAL",$D116,IF($E116="TRIMESTRAL",$D116/3,IF($E116="SEMESTRAL",$D116/2,IF($E116="ANUAL",$D116/12,IF($E116="BIMENSUAL",$D116/2))))) -> 100 | H116: NO | I116: =IF($H116="NO",IF($E116="MENSUAL",$D116,IF($E116="TRIMESTRAL",$D116/3,IF($E116="SEMESTRAL",$D116/2,IF($E116="ANUAL",$D116/12,IF($E116="BIMENSUAL",$D116/2))))),0) -> 100 | K116: NO | L116: =IF($H116="NO",IF($E116="MENSUAL",$D116,IF($E116="TRIMESTRAL",$D116/3,IF($E116="SEMESTRAL",$D116/2,IF($E116="ANUAL",$D116/12,IF($E116="BIMENSUAL",$D116/2))))),0) -> 100 | N116: NO | O116: =IF($N116="NO",IF($E116="MENSUAL",$D116,IF($E116="TRIMESTRAL",$D116/3,IF($E116="SEMESTRAL",$D116/2,IF($E116="ANUAL",$D116/12,IF($E116="BIMENSUAL",$D116/2))))),0) -> 100 | Q116: NO | R116: =IF($Q116="NO",IF($E116="MENSUAL",$D116,IF($E116="TRIMESTRAL",$D116/3,IF($E116="SEMESTRAL",$D116/2,IF($E116="ANUAL",$D116/12,IF($E116="BIMENSUAL",$D116/2))))),0) -> 100 | T116: NO | U116: =IF($T116="NO",IF($E116="MENSUAL",$D116,IF($E116="TRIMESTRAL",$D116/3,IF($E116="SEMESTRAL",$D116/2,IF($E116="ANUAL",$D116/12,IF($E116="BIMENSUAL",$D116/2))))),0) -> 100
A117: FONDO DE PENSIONES JBN | B117: KUTXA | C117: INVERSION | D117: 32 | E117: MENSUAL | F117: =IF($E117="MENSUAL",$D117,IF($E117="TRIMESTRAL",$D117/3,IF($E117="SEMESTRAL",$D117/2,IF($E117="ANUAL",$D117/12,IF($E117="BIMENSUAL",$D117/2))))) -> 32 | H117: NO | I117: =IF($H117="NO",IF($E117="MENSUAL",$D117,IF($E117="TRIMESTRAL",$D117/3,IF($E117="SEMESTRAL",$D117/2,IF($E117="ANUAL",$D117/12,IF($E117="BIMENSUAL",$D117/2))))),0) -> 32 | K117: NO | L117: =IF($H117="NO",IF($E117="MENSUAL",$D117,IF($E117="TRIMESTRAL",$D117/3,IF($E117="SEMESTRAL",$D117/2,IF($E117="ANUAL",$D117/12,IF($E117="BIMENSUAL",$D117/2))))),0) -> 32 | N117: NO | O117: =IF($N117="NO",IF($E117="MENSUAL",$D117,IF($E117="TRIMESTRAL",$D117/3,IF($E117="SEMESTRAL",$D117/2,IF($E117="ANUAL",$D117/12,IF($E117="BIMENSUAL",$D117/2))))),0) -> 32 | Q117: NO | R117: =IF($Q117="NO",IF($E117="MENSUAL",$D117,IF($E117="TRIMESTRAL",$D117/3,IF($E117="SEMESTRAL",$D117/2,IF($E117="ANUAL",$D117/12,IF($E117="BIMENSUAL",$D117/2))))),0) -> 32 | T117: NO | U117: =IF($T117="NO",IF($E117="MENSUAL",$D117,IF($E117="TRIMESTRAL",$D117/3,IF($E117="SEMESTRAL",$D117/2,IF($E117="ANUAL",$D117/12,IF($E117="BIMENSUAL",$D117/2))))),0) -> 32
A118: FONDO PENSIONES YUG | B118: KUTXA | C118: INVERSION | D118: 32 | E118: MENSUAL | F118: =IF($E118="MENSUAL",$D118,IF($E118="TRIMESTRAL",$D118/3,IF($E118="SEMESTRAL",$D118/2,IF($E118="ANUAL",$D118/12,IF($E118="BIMENSUAL",$D118/2))))) -> 32 | H118: NO | I118: =IF($H118="NO",IF($E118="MENSUAL",$D118,IF($E118="TRIMESTRAL",$D118/3,IF($E118="SEMESTRAL",$D118/2,IF($E118="ANUAL",$D118/12,IF($E118="BIMENSUAL",$D118/2))))),0) -> 32 | K118: NO | L118: =IF($H118="NO",IF($E118="MENSUAL",$D118,IF($E118="TRIMESTRAL",$D118/3,IF($E118="SEMESTRAL",$D118/2,IF($E118="ANUAL",$D118/12,IF($E118="BIMENSUAL",$D118/2))))),0) -> 32 | N118: NO | O118: =IF($N118="NO",IF($E118="MENSUAL",$D118,IF($E118="TRIMESTRAL",$D118/3,IF($E118="SEMESTRAL",$D118/2,IF($E118="ANUAL",$D118/12,IF($E118="BIMENSUAL",$D118/2))))),0) -> 32 | Q118: NO | R118: =IF($Q118="NO",IF($E118="MENSUAL",$D118,IF($E118="TRIMESTRAL",$D118/3,IF($E118="SEMESTRAL",$D118/2,IF($E118="ANUAL",$D118/12,IF($E118="BIMENSUAL",$D118/2))))),0) -> 32 | T118: NO | U118: =IF($T118="NO",IF($E118="MENSUAL",$D118,IF($E118="TRIMESTRAL",$D118/3,IF($E118="SEMESTRAL",$D118/2,IF($E118="ANUAL",$D118/12,IF($E118="BIMENSUAL",$D118/2))))),0) -> 32
A119: LOCAL UBITXA | B119: KUTXA | C119: PRESTAMO | D119: 500 | E119: MENSUAL | F119: =IF($E119="MENSUAL",$D119,IF($E119="TRIMESTRAL",$D119/3,IF($E119="SEMESTRAL",$D119/2,IF($E119="ANUAL",$D119/12,IF($E119="BIMENSUAL",$D119/2))))) -> 500 | H119: NO | I119: =IF($H119="NO",IF($E119="MENSUAL",$D119,IF($E119="TRIMESTRAL",$D119/3,IF($E119="SEMESTRAL",$D119/2,IF($E119="ANUAL",$D119/12,IF($E119="BIMENSUAL",$D119/2))))),0) -> 500 | K119: NO | L119: =IF($H119="NO",IF($E119="MENSUAL",$D119,IF($E119="TRIMESTRAL",$D119/3,IF($E119="SEMESTRAL",$D119/2,IF($E119="ANUAL",$D119/12,IF($E119="BIMENSUAL",$D119/2))))),0) -> 500 | N119: SI | O119: =IF($N119="NO",IF($E119="MENSUAL",$D119,IF($E119="TRIMESTRAL",$D119/3,IF($E119="SEMESTRAL",$D119/2,IF($E119="ANUAL",$D119/12,IF($E119="BIMENSUAL",$D119/2))))),0) -> 0 | Q119: SI | R119: =IF($Q119="NO",IF($E119="MENSUAL",$D119,IF($E119="TRIMESTRAL",$D119/3,IF($E119="SEMESTRAL",$D119/2,IF($E119="ANUAL",$D119/12,IF($E119="BIMENSUAL",$D119/2))))),0) -> 0 | T119: SI | U119: =IF($T119="NO",IF($E119="MENSUAL",$D119,IF($E119="TRIMESTRAL",$D119/3,IF($E119="SEMESTRAL",$D119/2,IF($E119="ANUAL",$D119/12,IF($E119="BIMENSUAL",$D119/2))))),0) -> 0
A120: ALQUILER PISO VITORIA | B120: KUTXA | C120: ALQUILERES | D120: 275 | E120: MENSUAL | F120: =IF($E120="MENSUAL",$D120,IF($E120="TRIMESTRAL",$D120/3,IF($E120="SEMESTRAL",$D120/2,IF($E120="ANUAL",$D120/12,IF($E120="BIMENSUAL",$D120/2))))) -> 275 | H120: NO | I120: =IF($H120="NO",IF($E120="MENSUAL",$D120,IF($E120="TRIMESTRAL",$D120/3,IF($E120="SEMESTRAL",$D120/2,IF($E120="ANUAL",$D120/12,IF($E120="BIMENSUAL",$D120/2))))),0) -> 275 | K120: NO | L120: =IF($H120="NO",IF($E120="MENSUAL",$D120,IF($E120="TRIMESTRAL",$D120/3,IF($E120="SEMESTRAL",$D120/2,IF($E120="ANUAL",$D120/12,IF($E120="BIMENSUAL",$D120/2))))),0) -> 275 | N120: SI | O120: =IF($N120="NO",IF($E120="MENSUAL",$D120,IF($E120="TRIMESTRAL",$D120/3,IF($E120="SEMESTRAL",$D120/2,IF($E120="ANUAL",$D120/12,IF($E120="BIMENSUAL",$D120/2))))),0) -> 0 | Q120: NO | R120: =IF($Q120="NO",IF($E120="MENSUAL",$D120,IF($E120="TRIMESTRAL",$D120/3,IF($E120="SEMESTRAL",$D120/2,IF($E120="ANUAL",$D120/12,IF($E120="BIMENSUAL",$D120/2))))),0) -> 275 | T120: SI | U120: =IF($T120="NO",IF($E120="MENSUAL",$D120,IF($E120="TRIMESTRAL",$D120/3,IF($E120="SEMESTRAL",$D120/2,IF($E120="ANUAL",$D120/12,IF($E120="BIMENSUAL",$D120/2))))),0) -> 0
A121: GASTOS COCHE | B121: N26 | C121: AVERIAS COCHE | D121: 1000 | E121: ANUAL | F121: =IF($E121="MENSUAL",$D121,IF($E121="TRIMESTRAL",$D121/3,IF($E121="SEMESTRAL",$D121/2,IF($E121="ANUAL",$D121/12,IF($E121="BIMENSUAL",$D121/2))))) -> 83.333333 | H121: NO | I121: =IF($H121="NO",IF($E121="MENSUAL",$D121,IF($E121="TRIMESTRAL",$D121/3,IF($E121="SEMESTRAL",$D121/2,IF($E121="ANUAL",$D121/12,IF($E121="BIMENSUAL",$D121/2))))),0) -> 83.333333 | K121: NO | L121: =IF($H121="NO",IF($E121="MENSUAL",$D121,IF($E121="TRIMESTRAL",$D121/3,IF($E121="SEMESTRAL",$D121/2,IF($E121="ANUAL",$D121/12,IF($E121="BIMENSUAL",$D121/2))))),0) -> 83.333333 | N121: NO | O121: =IF($N121="NO",IF($E121="MENSUAL",$D121,IF($E121="TRIMESTRAL",$D121/3,IF($E121="SEMESTRAL",$D121/2,IF($E121="ANUAL",$D121/12,IF($E121="BIMENSUAL",$D121/2))))),0) -> 83.333333 | Q121: NO | R121: =IF($Q121="NO",IF($E121="MENSUAL",$D121,IF($E121="TRIMESTRAL",$D121/3,IF($E121="SEMESTRAL",$D121/2,IF($E121="ANUAL",$D121/12,IF($E121="BIMENSUAL",$D121/2))))),0) -> 83.333333 | T121: NO | U121: =IF($T121="NO",IF($E121="MENSUAL",$D121,IF($E121="TRIMESTRAL",$D121/3,IF($E121="SEMESTRAL",$D121/2,IF($E121="ANUAL",$D121/12,IF($E121="BIMENSUAL",$D121/2))))),0) -> 83.333333
A122: KALA | B122: N26 | C122: MASCOTA | D122: 500 | E122: ANUAL | F122: =IF($E122="MENSUAL",$D122,IF($E122="TRIMESTRAL",$D122/3,IF($E122="SEMESTRAL",$D122/2,IF($E122="ANUAL",$D122/12,IF($E122="BIMENSUAL",$D122/2))))) -> 41.666667 | H122: NO | I122: =IF($H122="NO",IF($E122="MENSUAL",$D122,IF($E122="TRIMESTRAL",$D122/3,IF($E122="SEMESTRAL",$D122/2,IF($E122="ANUAL",$D122/12,IF($E122="BIMENSUAL",$D122/2))))),0) -> 41.666667 | K122: NO | L122: =IF($H122="NO",IF($E122="MENSUAL",$D122,IF($E122="TRIMESTRAL",$D122/3,IF($E122="SEMESTRAL",$D122/2,IF($E122="ANUAL",$D122/12,IF($E122="BIMENSUAL",$D122/2))))),0) -> 41.666667 | N122: NO | O122: =IF($N122="NO",IF($E122="MENSUAL",$D122,IF($E122="TRIMESTRAL",$D122/3,IF($E122="SEMESTRAL",$D122/2,IF($E122="ANUAL",$D122/12,IF($E122="BIMENSUAL",$D122/2))))),0) -> 41.666667 | Q122: NO | R122: =IF($Q122="NO",IF($E122="MENSUAL",$D122,IF($E122="TRIMESTRAL",$D122/3,IF($E122="SEMESTRAL",$D122/2,IF($E122="ANUAL",$D122/12,IF($E122="BIMENSUAL",$D122/2))))),0) -> 41.666667 | T122: NO | U122: =IF($T122="NO",IF($E122="MENSUAL",$D122,IF($E122="TRIMESTRAL",$D122/3,IF($E122="SEMESTRAL",$D122/2,IF($E122="ANUAL",$D122/12,IF($E122="BIMENSUAL",$D122/2))))),0) -> 41.666667
... A126: BODAS | B126: N26 | C126: BODAS | D126: 800 | E126: ANUAL | F126: =IF($E126="MENSUAL",$D126,IF($E126="TRIMESTRAL",$D126/3,IF($E126="SEMESTRAL",$D126/2,IF($E126="ANUAL",$D126/12,IF($E126="BIMENSUAL",$D126/2))))) -> 66.666667 | H126: NO | I126: =IF($H126="NO",IF($E126="MENSUAL",$D126,IF($E126="TRIMESTRAL",$D126/3,IF($E126="SEMESTRAL",$D126/2,IF($E126="ANUAL",$D126/12,IF($E126="BIMENSUAL",$D126/2))))),0) -> 66.666667 | K126: NO | L126: =IF($H126="NO",IF($E126="MENSUAL",$D126,IF($E126="TRIMESTRAL",$D126/3,IF($E126="SEMESTRAL",$D126/2,IF($E126="ANUAL",$D126/12,IF($E126="BIMENSUAL",$D126/2))))),0) -> 66.666667 | N126: NO | O126: =IF($N126="NO",IF($E126="MENSUAL",$D126,IF($E126="TRIMESTRAL",$D126/3,IF($E126="SEMESTRAL",$D126/2,IF($E126="ANUAL",$D126/12,IF($E126="BIMENSUAL",$D126/2))))),0) -> 66.666667 | Q126: NO | R126: =IF($Q126="NO",IF($E126="MENSUAL",$D126,IF($E126="TRIMESTRAL",$D126/3,IF($E126="SEMESTRAL",$D126/2,IF($E126="ANUAL",$D126/12,IF($E126="BIMENSUAL",$D126/2))))),0) -> 66.666667 | T126: NO | U126: =IF($T126="NO",IF($E126="MENSUAL",$D126,IF($E126="TRIMESTRAL",$D126/3,IF($E126="SEMESTRAL",$D126/2,IF($E126="ANUAL",$D126/12,IF($E126="BIMENSUAL",$D126/2))))),0) -> 66.666667
F127: =SUBTOTAL(9,F41:F126) -> 5545.7433 | I127: =SUBTOTAL(9,I41:I126) -> 4973.4933 | L127: =SUBTOTAL(9,L41:L126) -> 4973.4933 | O127: =SUBTOTAL(9,O41:O126) -> 2915.4933 | R127: =SUBTOTAL(9,R41:R126) -> 4415.41 | U127: =SUBTOTAL(9,U41:U126) -> 4140.41

Sheet MINIMOS
B1: ENERO | C1: FEBRERO | D1: MARZO | E1: ABRIL | F1: MAYO | G1: JUNIO | H1: JULIO | I1: AGOSTO | J1: SEPTIEMBRE | K1: OCTUBRE | L1: NOVIEMBRE | M1: DICIEMBRE
A2: MES TERMINADO | B2: Sí | C2: Sí | D2: Sí | E2: Sí | F2: Sí | G2: Sí | H2: Sí | I2: Sí | J2: No | K2: No | L2: No | M2: No
A4: GASTO PREVISTO MES SANTANDER TIPO 1 | B4: 0 | C4: 0 | D4: 1600 | E4: 2700 | F4: 0 | G4: 1300 | H4: 1000 | I4: 0 | J4: 0 | K4: 0 | L4: 0 | M4: 0 | N4: =SUM(B4:M4) -> 6600
A5: ---- GASTOS ASOCIADOS A SANTANDER 1 | B5: ='GASTOS '!E131 -> 345.24 | C5: ='GASTOS '!K131 -> 0 | D5: ='GASTOS '!Q131 -> 1606 | E5: ='GASTOS '!W131 -> 2700 | F5: ='GASTOS '!AC131 -> 119.25 | G5: ='GASTOS '!AI131 -> 1338.3 | H5: ='GASTOS '!AO131 -> 1188.09 | I5: ='GASTOS '!AU131 -> 0 | J5: ='GASTOS '!BO131 -> 0 | K5: ='GASTOS '!BG131 -> 0 | L5: ='GASTOS '!BM131 -> 0 | M5: ='GASTOS '!BS131 -> 0 | N5: =SUM(B5:M5) -> 7296.88
A6: BALANCE GASTOS SANTANDER 1 | B6: =B4-B5 -> -345.24 | C6: =C4-C5 -> 0 | D6: =D4-D5 -> -6 | E6: =E4-E5 -> 0 | F6: =F4-F5 -> -119.25 | G6: =G4-G5 -> -38.3 | H6: =H4-H5 -> -188.09 | I6: =I4-I5 -> 0 | ... M6: =M4-M5 -> 0 | N6: =SUM(B6:M6) -> -696.88
A8: GASTO PREVISTO MES SANTANDER TIPO 2 | B8: =$N$9/12 -> 2513.2492 | C8: =$N$9/12 -> 2513.2492 | D8: =$N$9/12 -> 2513.2492 | E8: =$N$9/12 -> 2513.2492 | F8: =$N$9/12 -> 2513.2492 | G8: =$N$9/12 -> 2513.2492 | H8: =$N$9/12 -> 2513.2492 | I8: =$N$9/12 -> 2513.2492 | ... M8: =$N$9/12 -> 2513.2492 | N8: =SUM(B8:M8) -> 30158.99
A9: ---- GASTOS ASOCIADOS A SANTANDER | B9: ='AÑO 2026'!F99 -> 2696.4 | C9: ='AÑO 2026'!G99 -> 1338.15 | D9: ='AÑO 2026'!H99 -> 2565.99 | E9: ='AÑO 2026'!I99 -> 2296.97 | F9: ='AÑO 2026'!J99 -> 2353.37 | G9: ='AÑO 2026'!K99 -> 2797.81 | H9: ='AÑO 2026'!L99 -> 2189.34 | I9: ='AÑO 2026'!M99 -> 2340.51 | ... M9: ='AÑO 2026'!Q99 -> 4080.67 | N9: =SUM(B9:M9) -> 30158.99 | O9: Esta incluido el traspaso a N26
A10: CONTROL GASTOS SANTANDER (1.835€/MES) | B10: =B8-B9 -> -183.15083 | C10: =C8-C9 -> 1175.0992 | D10: =D8-D9 -> -52.740833 | E10: =E8-E9 -> 216.27917 | F10: =F8-F9 -> 159.87917 | G10: =G8-G9 -> -284.56083 | H10: =H8-H9 -> 323.90917 | I10: =I8-I9 -> 172.73917 | ... M10: =M8-M9 -> -1567.4208 | N10: =SUM(B10:M10) -> -2.2737368e-12
A12: GASTO PREVISTO MES KUTXA TIPO 1 | B12: 1400 | C12: 1400 | D12: 1400 | E12: 1400 | F12: 1400 | G12: 1400 | H12: 1400 | I12: 1400 | J12: 1400 | K12: 1400 | L12: 1400 | M12: 1400 | N12: =SUM(B12:M12) -> 16800
A13: ---- GASTOS ASOCIADOS A KUTXA 1 | B13: ='GASTOS '!E130 -> 1169.85 | C13: ='GASTOS '!K130 -> 1918.47 | D13: ='GASTOS '!Q130 -> 1667.22 | E13: ='GASTOS '!W130 -> 1967.94 | F13: ='GASTOS '!AC130 -> 2295.85 | G13: ='GASTOS '!AI130 -> 1749.47 | H13: ='GASTOS '!AO130 -> 2025.87 | I13: ='GASTOS '!AU130 -> 1626.91 | J13: ='GASTOS '!BA130 -> 0 | K13: ='GASTOS '!BG130 -> 0 | L13: ='GASTOS '!BM130 -> 0 | M13: ='GASTOS '!BS130 -> 0 | N13: =SUM(B13:M13) -> 14421.58
A14: BALANCE GASTOS KUTXA 1 (1.400€/MES) | B14: =B12-B13 -> 230.15 | C14: =C12-C13 -> -518.47 | D14: =D12-D13 -> -267.22 | E14: =E12-E13 -> -567.94 | F14: =F12-F13 -> -895.85 | G14: =G12-G13 -> -349.47 | H14: =H12-H13 -> -625.87 | I14: =I12-I13 -> -226.91 | ... M14: =M12-M13 -> 1400 | N14: =SUM(B14:M14) -> 2378.42
B15: =SUM(B13)/1 -> 1169.85 | C15: {=SUM(B13:C13/2)} -> 1544.16 | D15: =SUM(B13:D13)/3 -> 1585.18 | E15: =SUM(B13:E13)/4 -> 1680.87 | F15: =SUM(B13:F13)/5 -> 1803.866 | G15: =SUM(B13:G13)/6 -> 1794.8 | H15: =SUM(B13:H13)/7 -> 1827.81 | I15: =SUM(B13:I13)/8 -> 1802.6975 | J15: =SUM(B13:J13)/9 -> 1602.3978 | K15: =SUM(B13:K13)/10 -> 1442.158 | L15: =SUM(B13:L13)/11 -> 1311.0527 | M15: =SUM(B13:M13)/12 -> 1201.7983
A16: GASTO PREVISTO MES KUTXA TIPO 2 | B16: =$N$17/12 -> 991.375 | C16: =$N$17/12 -> 991.375 | D16: =$N$17/12 -> 991.375 | E16: =$N$17/12 -> 991.375 | F16: =$N$17/12 -> 991.375 | G16: =$N$17/12 -> 991.375 | H16: =$N$17/12 -> 991.375 | I16: =$N$17/12 -> 991.375 | ... M16: =$N$17/12 -> 991.375 | N16: =SUM(B16:M16) -> 11896.5
A17: ---- GASTOS ASOCIADOS A KUTXA 2 | B17: ='AÑO 2026'!F122 -> 1049.04 | C17: ='AÑO 2026'!G122 -> 1273.18 | D17: ='AÑO 2026'!H122 -> 852.75 | E17: ='AÑO 2026'!I122 -> 1069.95 | F17: ='AÑO 2026'!J122 -> 1088.46 | G17: ='AÑO 2026'!K122 -> 944.52 | H17: ='AÑO 2026'!L122 -> 886.57 | I17: ='AÑO 2026'!M122 -> 954.16 | ... M17: ='AÑO 2026'!Q122 -> 1129.7 | N17: =SUM(B17:M17) -> 11896.5
A18: BALANCE GASTOS KUTXA 2 (1.000€/MES) | B18: =B16-B17 -> -57.665 | C18: =C16-C17 -> -281.805 | D18: =D16-D17 -> 138.625 | E18: =E16-E17 -> -78.575 | F18: =F16-F17 -> -97.085 | G18: =G16-G17 -> 46.855 | H18: =H16-H17 -> 104.805 | I18: =I16-I17 -> 37.215 | ... M18: =M16-M17 -> -138.325 | N18: =SUM(B18:M18) -> 5.6843419e-13
B19: =SUM(B17)/1 -> 1049.04 | C19: {=SUM(B17:C17/2)} -> 1161.11 | D19: =SUM(B17:D17)/3 -> 1058.3233 | E19: =SUM(B17:E17)/4 -> 1061.23 | F19: =SUM(B17:F17)/5 -> 1066.676 | G19: =SUM(B17:G17)/6 -> 1046.3167 | H19: =SUM(B17:H17)/7 -> 1023.4957 | I19: =SUM(B17:I17)/8 -> 1014.8287 | J19: =SUM(B17:J17)/9 -> 988.70333 | K19: =SUM(B17:K17)/10 -> 995.842 | L19: =SUM(B17:L17)/11 -> 978.8 | M19: =SUM(B17:M17)/12 -> 991.375
A20: GASTO PREVISTO MES N26 TIPO 1 | B20: 500 | C20: 500 | D20: 500 | E20: 500 | F20: 500 | G20: 500 | H20: 500 | I20: 500 | J20: 500 | K20: 500 | L20: 500 | M20: 500 | N20: =SUM(B20:M20) -> 6000
A21: ---- GASTOS ASOCIADOS A N26 | B21: ='GASTOS '!E129 -> 0 | C21: ='GASTOS '!K129 -> 192 | D21: ='GASTOS '!Q129 -> 140 | E21: ='GASTOS '!W129 -> 0 | F21: ='GASTOS '!AC129 -> 185 | G21: ='GASTOS '!AI129 -> 0 | H21: ='GASTOS '!AO129 -> 127 | I21: ='GASTOS '!AU129 -> 0 | J21: ='GASTOS '!BA129 -> 500 | K21: ='GASTOS '!BG129 -> 500 | L21: ='GASTOS '!BM129 -> 500 | M21: ='GASTOS '!BS129 -> 500 | N21: =SUM(B21:M21) -> 2644
A22: BALANCE GASTOS N26 (500€/MES) | B22: =B20-B21 -> 500 | C22: =C20-C21 -> 308 | D22: =D20-D21 -> 360 | E22: =E20-E21 -> 500 | F22: =F20-F21 -> 315 | G22: =G20-G21 -> 500 | H22: =H20-H21 -> 373 | I22: =I20-I21 -> 500 | ... M22: =M20-M21 -> 0 | N22: =SUM(B22:M22) -> 3356
B23: =SUM(B21)/1 -> 0 | C23: {=SUM(B21:C21/2)} -> 96 | D23: =SUM(B21:D21)/3 -> 110.66667 | E23: =SUM(B21:E21)/4 -> 83 | F23: =SUM(B21:F21)/5 -> 103.4 | G23: =SUM(B21:G21)/6 -> 86.166667 | H23: =SUM(B21:H21)/7 -> 92 | I23: =SUM(B21:I21)/8 -> 80.5 | J23: =SUM(B21:J21)/9 -> 127.11111 | K23: =SUM(B21:K21)/10 -> 164.4 | L23: =SUM(B21:L21)/11 -> 194.90909 | M23: =SUM(B21:M21)/12 -> 220.33333
N24: GASTO ACTUAL | O24: GASTO PREVISTO | P24: INGRESOS | Q24: GASTO PENDIENTE | R24: AHORRO
A25: GASTOS ASOCIADOS A SANTANDER (TIPO 1 + TIPO 2) | B25: =B5+IF(B2="Sí",B9,0) -> 3041.64 | C25: =C5+IF(C2="Sí",C9,0) -> 1338.15 | D25: =D5+IF(D2="Sí",D9,0) -> 4171.99 | E25: =E5+IF(E2="Sí",E9,0) -> 4996.97 | F25: =F5+IF(F2="Sí",F9,0) -> 2472.62 | G25: =G5+IF(G2="Sí",G9,0) -> 4136.11 | H25: =H5+IF(H2="Sí",H9,0) -> 3377.43 | I25: =I5+IF(I2="Sí",I9,0) -> 2340.51 | ... M25: =M5+IF(M2="Sí",M9,0) -> 0 | N25: =SUM(B25:M25) -> 25875.42 | O25: =N4+N8 -> 36758.99 | P25: ='AÑO 2026'!S33 -> 35499.24 | Q25: =N8-N25 -> 4283.57 | R25: =P25-O25 -> -1259.75
A26: GASTOS ASOCIADOS A KUTXA (TIPO 1 + TIPO 2) | B26: =B13+IF(B2="Sí",B17,0) -> 2218.89 | C26: =C13+IF(C2="Sí",C17,0) -> 3191.65 | D26: =D13+IF(D2="Sí",D17,0) -> 2519.97 | E26: =E13+IF(E2="Sí",E17,0) -> 3037.89 | F26: =F13+IF(F2="Sí",F17,0) -> 3384.31 | G26: =G13+IF(G2="Sí",G17,0) -> 2693.99 | H26: =H13+IF(H2="Sí",H17,0) -> 2912.44 | I26: =I13+IF(I2="Sí",I17,0) -> 2581.07 | ... M26: =M13+IF(M2="Sí",M17,0) -> 0 | N26: =SUM(B26:M26) -> 22540.21 | O26: =N12+N16 -> 28696.5 | P26: ='AÑO 2026'!S39 -> 30932.5 | Q26: =(N12+N16)-N26 -> 6156.29 | R26: =P26-O26 -> 2236
A27: GASTOS ASOCIADOS A N26 (TIPO 1) | B27: =B21 -> 0 | C27: =C21 -> 192 | D27: =D21 -> 140 | E27: =E21 -> 0 | F27: =F21 -> 185 | G27: =G21 -> 0 | H27: =H21 -> 127 | I27: =I21 -> 0 | ... M27: =M21 -> 500 | N27: =SUM(B27:M27) -> 2644 | O27: =N20 -> 6000 | P27: ='AÑO 2026'!S44 -> 6000 | Q27: =N20-N27 -> 3356 | R27: =P27-O27 -> 0
N28: =SUM(N26:N26) -> 22540.21 | O28: =SUM(O26:O26) -> 28696.5 | P28: =SUM(P26:P26) -> 30932.5 | Q28: =IF(P28>O28,SUM(Q26:Q26),P28-O28) -> 6156.29 | R28: =IF(P28>O28,P28-O28,P28-O28) -> 2236 | S28: * EL SALDO ES NEGATIVO PERO NO PARTIMOS DE 0, PARTIMOS DE 9318€
A29: GASTOS TIPO 1
A30: SALDO ACUMULADO KUTXA | B30: =B12-B13 -> 230.15 | C30: =B12+C12-B13-C13 -> -288.32 | D30: =B12+C12+D12-B13-C13-D13 -> -555.54 | E30: =B12+C12+D12+E12-B13-C13-D13-E13 -> -1123.48 | F30: =B12+C12+D12+E12+F12-B13-C13-D13-E13-F13 -> -2019.33 | G30: =B12+C12+D12+E12+F12+G12-B13-C13-D13-E13-F13-G13 -> -2368.8 | H30: =B12+C12+D12+E12+F12+G12+H12-B13-C13-D13-E13-F13-G13-H13 -> -2994.67 | I30: =B12+C12+D12+E12+F12+G12+H12+I12-B13-C13-D13-E13-F13-G13-H13-I13 -> -3221.58 | J30: =B12+C12+D12+E12+F12+G12+H12+I12+J12-B13-C13-D13-E13-F13-G13-H13-I13-J13 -> -1821.58 | K30: =B12+C12+D12+E12+F12+G12+H12+I12+J12+K12-B13-C13-D13-E13-F13-G13-H13-I13-J13-K13 -> -421.58 | L30: =B12+C12+D12+E12+F12+G12+H12+I12+J12+K12+L12-B13-C13-D13-E13-F13-G13-H13-I13-J13-K13-L13 -> 978.42 | M30: =B12+C12+D12+E12+F12+G12+H12+I12+J12+K12+L12+M12-B13-C13-D13-E13-F13-G13-H13-I13-J13-K13-L13-M13 -> 2378.42
A31: GASTO POSIBLE AL MES KUTXA | B31: =$M$30/12 -> 198.20167 | C31: =$M$30/11 -> 216.22 | D31: =$M$30/10 -> 237.842 | E31: =$M$30/9 -> 264.26889 | F31: =$M$30/8 -> 297.3025 | G31: =$M$30/7 -> 339.77429 | H31: =$M$30/6 -> 396.40333 | I31: =$M$30/5 -> 475.684 | J31: =$M$30/4 -> 594.605 | K31: =$M$30/3 -> 792.80667 | L31: =$M$30/2 -> 1189.21 | M31: =$M$30/1 -> 2378.42
A32: SALDO ACUMULADO N26 | B32: =B20-B21 -> 500 | C32: =B20+C20-B21-C21 -> 808 | D32: =B20+C20+D20-B21-C21-D21 -> 1168 | E32: =B20+C20+D20+E20-B21-C21-D21-E21 -> 1668 | F32: =B20+C20+D20+E20+F20-B21-C21-D21-E21-F21 -> 1983 | G32: =B20+C20+D20+E20+F20+G20-B21-C21-D21-E21-F21-G21 -> 2483 | H32: =B20+C20+D20+E20+F20+G20+H20-B21-C21-D21-E21-F21-G21-H21 -> 2856 | I32: =B20+C20+D20+E20+F20+G20+H20+I20-B21-C21-D21-E21-F21-G21-H21-I21 -> 3356 | J32: =B20+C20+D20+E20+F20+G20+H20+I20+J20-B21-C21-D21-E21-F21-G21-H21-I21-J21 -> 3356 | K32: =B20+C20+D20+E20+F20+G20+H20+I20+J20+K20-B21-C21-D21-E21-F21-G21-H21-I21-J21-K21 -> 3356 | L32: =B20+C20+D20+E20+F20+G20+H20+I20+J20+K20+L20-B21-C21-D21-E21-F21-G21-H21-I21-J21-K21-L21 -> 3356 | M32: =B20+C20+D20+E20+F20+G20+H20+I20+J20+K20+L20+M20-B21-C21-D21-E21-F21-G21-H21-I21-J21-K21-L21-M21 -> 3356
A33: GASTO POSIBLE AL MES N26 | B33: =$M$32/12 -> 279.66667 | C33: =$M$32/11 -> 305.09091 | D33: =$M$32/10 -> 335.6 | E33: =$M$32/9 -> 372.88889 | F33: =$M$32/8 -> 419.5 | G33: =$M$32/7 -> 479.42857 | H33: =$M$32/6 -> 559.33333 | I33: =$M$32/5 -> 671.2 | J33: =$M$32/4 -> 839 | K33: =$M$32/3 -> 1118.6667 | L33: =$M$32/2 -> 1678 | M33: =$M$32/1 -> 3356
H35: KUTXA GASTOS TIPO 2 | K35: Meses | L35: Mes | M35: Año
H36: PAGAS | I36: 200 | J36: MENSUAL | K36: 12 | L36: =IF($J36="MENSUAL",$I36,IF($J36="TRIMESTRAL",$I36/3,IF($J36="SEMESTRAL",$I36/2,IF($J36="ANUAL",$I36/12,IF($J36="BIMENSUAL",$I36/2))))) -> 200 | M36: =L36*K36 -> 2400
H37: PISO | I37: 275 | J37: MENSUAL | K37: 8 | L37: =IF($J37="MENSUAL",$I37,IF($J37="TRIMESTRAL",$I37/3,IF($J37="SEMESTRAL",$I37/2,IF($J37="ANUAL",$I37/12,IF($J37="BIMENSUAL",$I37/2))))) -> 275 | M37: =L37*K37 -> 2200
H38: JUANCAR | I38: 500 | J38: MENSUAL | K38: 12 | L38: =IF($J38="MENSUAL",$I38,IF($J38="TRIMESTRAL",$I38/3,IF($J38="SEMESTRAL",$I38/2,IF($J38="ANUAL",$I38/12,IF($J38="BIMENSUAL",$I38/2))))) -> 500 | M38: =L38*K38 -> 6000
H39: SEG COCHE | I39: 250 | J39: ANUAL | K39: 12 | L39: =IF($J39="MENSUAL",$I39,IF($J39="TRIMESTRAL",$I39/3,IF($J39="SEMESTRAL",$I39/2,IF($J39="ANUAL",$I39/12,IF($J39="BIMENSUAL",$I39/2))))) -> 20.833333 | M39: =L39*K39 -> 250
H40: SEG CASA | I40: 350 | J40: ANUAL | K40: 12 | L40: =IF($J40="MENSUAL",$I40,IF($J40="TRIMESTRAL",$I40/3,IF($J40="SEMESTRAL",$I40/2,IF($J40="ANUAL",$I40/12,IF($J40="BIMENSUAL",$I40/2))))) -> 29.166667 | M40: =L40*K40 -> 350
H41: SEG LOCAL | I41: 175 | J41: ANUAL | K41: 12 | L41: =IF($J41="MENSUAL",$I41,IF($J41="TRIMESTRAL",$I41/3,IF($J41="SEMESTRAL",$I41/2,IF($J41="ANUAL",$I41/12,IF($J41="BIMENSUAL",$I41/2))))) -> 14.583333 | M41: =L41*K41 -> 175
H42: FONDO | I42: 70 | J42: MENSUAL | K42: 12 | L42: =IF($J42="MENSUAL",$I42,IF($J42="TRIMESTRAL",$I42/3,IF($J42="SEMESTRAL",$I42/2,IF($J42="ANUAL",$I42/12,IF($J42="BIMENSUAL",$I42/2))))) -> 70 | M42: =L42*K42 -> 840
H43: IBERDROLA | I43: 10 | J43: MENSUAL | K43: 12 | L43: =IF($J43="MENSUAL",$I43,IF($J43="TRIMESTRAL",$I43/3,IF($J43="SEMESTRAL",$I43/2,IF($J43="ANUAL",$I43/12,IF($J43="BIMENSUAL",$I43/2))))) -> 10 | M43: =L43*K43 -> 120
H44: AGUA | I44: 40 | J44: TRIMESTRAL | K44: 12 | L44: =IF($J44="MENSUAL",$I44,IF($J44="TRIMESTRAL",$I44/3,IF($J44="SEMESTRAL",$I44/2,IF($J44="ANUAL",$I44/12,IF($J44="BIMENSUAL",$I44/2))))) -> 13.333333 | M44: =L44*K44 -> 160
H45: IBI LOCAL | I45: 60 | J45: ANUAL | K45: 12 | L45: =IF($J45="MENSUAL",$I45,IF($J45="TRIMESTRAL",$I45/3,IF($J45="SEMESTRAL",$I45/2,IF($J45="ANUAL",$I45/12,IF($J45="BIMENSUAL",$I45/2))))) -> 5 | M45: =L45*K45 -> 60
J46: MENSUAL | L46: =IF($J46="MENSUAL",$I46,IF($J46="TRIMESTRAL",$I46/3,IF($J46="SEMESTRAL",$I46/2,IF($J46="ANUAL",$I46/12,IF($J46="BIMENSUAL",$I46/2))))) -> 0 | M46: =L46*K46 -> 0
J47: MENSUAL | L47: =IF($J47="MENSUAL",$I47,IF($J47="TRIMESTRAL",$I47/3,IF($J47="SEMESTRAL",$I47/2,IF($J47="ANUAL",$I47/12,IF($J47="BIMENSUAL",$I47/2))))) -> 0 | M47: =L47*K47 -> 0
H48: FURGONETA | I48: 0 | J48: MENSUAL | K48: 12 | L48: =IF($J48="MENSUAL",$I48,IF($J48="TRIMESTRAL",$I48/3,IF($J48="SEMESTRAL",$I48/2,IF($J48="ANUAL",$I48/12,IF($J48="BIMENSUAL",$I48/2))))) -> 0 | M48: =L48*K48 -> 0 | N48: TOTAL AL MES
M49: =SUM(M36:M48) -> 12555 | N49: =M49/12 -> 1046.25

Sheet AMORTIZACIONES 1
B1: AÑO | C1: MES | D1: HIPOTECA | I1: JUANCAR
D2: AMORTIZADO | F2: RESTO | G2: INTERESES | H2: RESTO
I3: 45500 | K3: AHORRO 1 | L3: AHORRO 2
A4: 0 | B4: 2022 | C4: 1 | I4: 0 | J4: =I3-I4 -> 45500
C5: 2 | I5: 0 | J5: =J4-I5 -> 45500
C6: 3 | I6: 0 | J6: =J5-I6 -> 45500
C7: 4 | I7: 0 | J7: =J6-I7 -> 45500
C8: 5 | I8: 0 | J8: =J7-I8 -> 45500
C9: 6 | I9: 500 | J9: =J8-I9 -> 45000
C10: 7 | I10: 500 | J10: =J9-I10 -> 44500
C11: 8 | I11: 500 | J11: =J10-I11 -> 44000
C12: 9 | I12: 500 | J12: =J11-I12 -> 43500
C13: 10 | I13: 500 | J13: =J12-I13 -> 43000
C14: 11 | I14: 500 | J14: =J13-I14 -> 42500
C15: 12 | I15: 500 | J15: =J14-I15 -> 42000
A16: 0 | B16: 2023 | C16: 1 | I16: 500 | J16: =J15-I16 -> 41500
C17: 2 | I17: 500 | J17: =J16-I17 -> 41000
C18: 3 | I18: 500 | J18: =J17-I18 -> 40500
C19: 4 | I19: 500 | J19: =J18-I19 -> 40000
C20: 5 | I20: 500 | J20: =J19-I20 -> 39500
C21: 6 | I21: 500 | J21: =J20-I21 -> 39000
C22: 7 | I22: 500 | J22: =J21-I22 -> 38500
C23: 8 | I23: 500 | J23: =J22-I23 -> 38000
C24: 9 | I24: 500 | J24: =J23-I24 -> 37500
C25: 10 | I25: 500 | J25: =J24-I25 -> 37000
C26: 11 | I26: 500 | J26: =J25-I26 -> 36500
C27: 12 | I27: 500 | J27: =J26-I27 -> 36000
A28: 1 | B28: 2024 | C28: 1 | I28: 500 | J28: =J27-I28 -> 35500 | P28: ESCENARIO 1 | X28: ESCENARIO 2 | AF28: ESCENARIO 3 | AN28: ESCENARIO 4
C29: 2 | E29: 525.33 | G29: 324.87 | H29: =SUM(G29:$G$107) -> 7671.93 | I29: 500 | J29: =J28-I29 -> 35000 | T29: AMORTIZACION | V29: INTERESES | AB29: AMORTIZACION | AD29: INTERESES | AJ29: AMORTIZACION | AL29: INTERESES | AR29: AMORTIZACION | AT29: INTERESES
C30: 3 | E30: 527.31 | G30: 322.89 | H30: =SUM(G30:$G$107) -> 7347.06 | I30: 500 | J30: =J29-I30 -> 34500 | P30: 2024 | Q30: Disponible | R30: 23000 | X30: 2024 | Y30: Disponible | Z30: 23000 | AC30: =M39 -> 0 | AF30: 2024 | AG30: Disponible | AH30: 23000 | AN30: 2024 | AO30: Disponible | AP30: 23000
C31: 4 | E31: 529.3 | G31: 320.9 | H31: =SUM(G31:$G$107) -> 7024.17 | I31: 500 | J31: =J30-I31 -> 34000
C32: 5 | E32: 531.29 | G32: 318.91 | H32: =SUM(G32:$G$107) -> 6703.27 | I32: 500 | J32: =J31-I32 -> 33500 | P32: 2025 | Q32: Pendiente Hipoteca | S32: 66500 | X32: 2025 | Y32: Pendiente Hipoteca | AA32: 66500 | AF32: 2025 | AG32: Pendiente Hipoteca | AI32: 66500 | AN32: 2025 | AO32: Pendiente Hipoteca | AQ32: 66500
C33: 6 | D33: 14000 | E33: 533.3 | G33: 316.9 | H33: =SUM(G33:$G$107) -> 6384.36 | I33: 500 | J33: =J32-I33 -> 33000 | Q33: Disponible | T33: 15500 | Y33: Disponible | AB33: 15500 | AG33: Disponible | AJ33: 23000 | AO33: Disponible | AR33: 15500
C34: 7 | E34: 535.31 | G34: 314.89 | H34: =SUM(G34:$G$107) -> 6067.46 | I34: 500 | J34: =J33-I34 -> 32500 | Q34: Hacienda | T34: 4000 | Y34: Hacienda | AB34: 4000 | AG34: Hacienda | AJ34: 4000 | AO34: Hacienda | AR34: 1500
C35: 8 | E35: 537.32 | G35: 312.88 | H35: =SUM(G35:$G$107) -> 5752.57 | I35: 500 | J35: =J34-I35 -> 32000 | Q35: Cuotas | T35: 7000 | V35: 3600 | Y35: Cuotas | AB35: 7000 | AD35: 3600 | AG35: Cuotas | AJ35: 7000 | AL35: 3600 | AO35: Cuotas | AR35: 7000 | AT35: 3600
C36: 9 | E36: 539.35 | G36: 310.85 | H36: =SUM(G36:$G$107) -> 5439.69 | I36: 500 | J36: =J35-I36 -> 31500 | Q36: Ahorro | T36: 0 | Y36: Ahorro | AB36: 0 | AC36: =M51 -> 0 | AG36: Ahorro | AJ36: 0 | AO36: Ahorro | AR36: 0
C37: 10 | E37: 541.38 | G37: 308.82 | H37: =SUM(G37:$G$107) -> 5128.84 | I37: 500 | J37: =J36-I37 -> 31000 | Q37: TOTAL | T37: =SUM(T33:T36) -> 26500 | V37: =SUM(V35:V36) -> 3600 | Y37: TOTAL | AB37: =SUM(AB33:AB36) -> 26500 | AC37: =AC30+AC36 -> 0 | AD37: =SUM(AD35:AD36) -> 3600 | AG37: TOTAL | AJ37: =SUM(AJ33:AJ36) -> 34000 | AK37: =SUM(AK33:AK36) -> 0 | AL37: =SUM(AL35:AL36) -> 3600 | AO37: TOTAL | AR37: =SUM(AR33:AR36) -> 24000 | AS37: =SUM(AS33:AS36) -> 0 | AT37: =SUM(AT35:AT36) -> 3600
C38: 11 | E38: 596.96 | G38: 253.24 | H38: =SUM(G38:$G$107) -> 4820.02 | I38: 500 | J38: =J37-I38 -> 30500
C39: 12 | E39: 599.21 | G39: 250.99 | H39: =SUM(G39:$G$107) -> 4566.78 | I39: 500 | J39: =J38-I39 -> 30000 | P39: 2026 | Q39: Pendiente Hipoteca | S39: =S32-T33-T34-T35-T36 -> 40000 | X39: 2026 | Y39: Pendiente Hipoteca | AA39: =AA32-AB33-AB34-AB35-AB36 -> 40000 | AF39: 2026 | AG39: Pendiente Hipoteca | AI39: =AI32-AJ33-AJ34-AJ35-AJ36 -> 32500 | AN39: 2026 | AO39: Pendiente Hipoteca | AQ39: =AQ32-AR33-AR34-AR35-AR36 -> 42500 | AU39: 42500
A40: 2 | B40: 2025 | C40: 1 | D40: 15404.5 | E40: 601.47 | G40: 248.73 | H40: =SUM(G40:$G$107) -> 4315.79 | I40: 500 | J40: =J39-I40 -> 29500 | Q40: Disponible | T40: =R30-T33 -> 7500 | Y40: Disponible | AB40: =Z30-AB33 -> 7500 | AG40: Disponible | AJ40: =AH30-AJ33 -> 0 | AO40: Disponible | AR40: 0
C41: 2 | E41: 897.77 | G41: 126.54 | H41: =SUM(G41:$G$107) -> 4067.06 | I41: 500 | J41: =J40-I41 -> 29000 | Q41: Hacienda | T41: 4000 | Y41: Hacienda | AB41: 4000 | AG41: Hacienda | AJ41: 4000 | AO41: Hacienda | AR41: 0
C42: 3 | E42: 685.1 | G42: 123 | H42: =SUM(G42:$G$107) -> 3940.52 | I42: 500 | J42: =J41-I42 -> 28500 | Q42: Cuotas | T42: 8400 | V42: 3600 | Y42: Cuotas | AB42: 8400 | AD42: 3600 | AG42: Cuotas | AJ42: 8400 | AL42: 3600 | AO42: Cuotas | AR42: 8400 | AT42: 3600
C43: 4 | E43: 686.82 | G43: 121.28 | H43: =SUM(G43:$G$107) -> 3817.52 | I43: 500 | J43: =J42-I43 -> 28000 | Q43: Ahorro | T43: 0 | Y43: Ahorro | AB43: 0 | AC43: =M63 -> 1700 | AG43: Ahorro | AJ43: 11000 | AO43: Ahorro | AR43: 0
C44: 5 | E44: 688.54 | G44: 119.56 | H44: =SUM(G44:$G$107) -> 3696.24 | I44: 500 | J44: =J43-I44 -> 27500 | Q44: TOTAL | T44: =SUM(T40:T43) -> 19900 | V44: =SUM(V42:V43) -> 3600 | Y44: TOTAL | AB44: =SUM(AB40:AB43) -> 19900 | AC44: =AC30+AC36+AC43 -> 1700 | AD44: =SUM(AD42:AD43) -> 3600 | AG44: TOTAL | AJ44: =SUM(AJ40:AJ43) -> 23400 | AK44: =SUM(AK40:AK43) -> 0 | AL44: =SUM(AL42:AL43) -> 3600 | AO44: TOTAL | AR44: =SUM(AR40:AR43) -> 8400 | AS44: =SUM(AS40:AS43) -> 0 | AT44: =SUM(AT42:AT43) -> 3600
C45: 6 | E45: 690.26 | G45: 117.84 | H45: =SUM(G45:$G$107) -> 3576.68 | I45: 500 | J45: =J44-I45 -> 27000
C46: 7 | E46: 691.99 | G46: 116.11 | H46: =SUM(G46:$G$107) -> 3458.84 | I46: 500 | J46: =J45-I46 -> 26500 | P46: 2027 | Q46: Pendiente Hipoteca | S46: =S39-T40-T41-T42-T43 -> 20100 | X46: 2027 | Y46: Pendiente Hipoteca | AA46: =AA39-AB40-AB41-AB42-AB43 -> 20100 | AF46: 2027 | AG46: Pendiente Hipoteca | AI46: =AI39-AJ40-AJ41-AJ42-AJ43 -> 9100 | AN46: 2027 | AO46: Pendiente Hipoteca | AQ46: =AQ39-AR40-AR41-AR42-AR43 -> 34100 | AU46: 34100
C47: 8 | E47: 693.72 | G47: 114.38 | H47: =SUM(G47:$G$107) -> 3342.73 | I47: 500 | J47: =J46-I47 -> 26000 | Q47: Disponible | T47: =R30-T33-T40 -> 0 | Y47: Disponible | AB47: =Z30-AB33-AB40 -> 0 | AG47: Disponible | AJ47: =AH30-AJ33-AJ40 -> 0 | AO47: Disponible | AR47: 0
C48: 9 | E48: 695.46 | G48: 112.64 | H48: =SUM(G48:$G$107) -> 3228.35 | I48: 500 | J48: =J47-I48 -> 25500 | Q48: Hacienda | T48: 4000 | Y48: Hacienda | AB48: 4000 | AG48: Hacienda | AJ48: 0 | AO48: Hacienda | AR48: 0
C49: 10 | E49: 697.2 | G49: 110.9 | H49: =SUM(G49:$G$107) -> 3115.71 | I49: 500 | J49: =J48-I49 -> 25000 | Q49: Cuotas | T49: 8800 | V49: 1500 | Y49: Cuotas | AB49: 8800 | AD49: 3600 | AG49: Cuotas | AJ49: 8800 | AL49: 3600 | AO49: Cuotas | AR49: 8800 | AT49: 3600
C50: 11 | E50: 698.95 | G50: 109.15 | H50: =SUM(G50:$G$107) -> 3004.81 | I50: 500 | J50: =J49-I50 -> 24500 | Q50: Ahorro | T50: 8000 | Y50: Ahorro | AB50: 0 | AC50: =M71+M75 -> 5100 | AG50: Ahorro | AJ50: 0 | AK50: 3925 | AO50: Ahorro | AR50: 0 | AS50: 3925
C51: 12 | E51: 700.7 | G51: 107.4 | H51: =SUM(G51:$G$107) -> 2895.66 | I51: 500 | J51: =J50-I51 -> 24000 | Q51: TOTAL | T51: =SUM(T47:T50) -> 20800 | V51: =SUM(V49:V50) -> 1500 | Y51: TOTAL | AB51: =SUM(AB47:AB50) -> 12800 | AC51: =AC30+AC36+AC43+AC50 -> 6800 | AD51: =SUM(AD49:AD50) -> 3600 | AG51: TOTAL | AJ51: =SUM(AJ47:AJ50) -> 8800 | AK51: =SUM(AK47:AK50) -> 3925 | AL51: =SUM(AL49:AL50) -> 3600 | AO51: TOTAL | AR51: =SUM(AR47:AR50) -> 8800 | AS51: =SUM(AS47:AS50) -> 3925 | AT51: =SUM(AT49:AT50) -> 3600
A52: 3 | B52: 2026 | C52: 1 | E52: 702.46 | G52: 105.64 | H52: =SUM(G52:$G$107) -> 2788.26 | I52: 500 | J52: =J51-I52 -> 23500
C53: 2 | E53: 708.89 | G53: 93.9 | H53: =SUM(G53:$G$107) -> 2682.62 | I53: 500 | J53: =J52-I53 -> 23000 | P53: 2028 | Q53: Pendiente Hipoteca | S53: =S46-T47-T48-T49-T50 -> -700 | X53: 2028 | Y53: Pendiente Hipoteca | AA53: =AA46-AB47-AB48-AB49-AB50 -> 7300 | AF53: 2028 | AG53: Pendiente Hipoteca | AI53: =AI46-AJ47-AJ48-AJ49-AJ50 -> 300 | AN53: 2028 | AO53: Pendiente Hipoteca | AQ53: =AQ46-AR47-AR48-AR49-AR50 -> 25300 | AU53: 25300
C54: 3 | E54: 710.5 | G54: 92.29 | H54: =SUM(G54:$G$107) -> 2588.72 | I54: 500 | J54: =J53-I54 -> 22500 | Q54: Disponible | T54: =R30-T33-T40-T47 -> 0 | Y54: Disponible | AB54: =Z30-AB33-AB40-AB47 -> 0 | AG54: Disponible | AJ54: =AH37-AJ40-AJ47 -> 0 | AO54: Disponible | AR54: =AP37-AR40-AR47 -> 0
C55: 4 | E55: 712.11 | G55: 90.68 | H55: =SUM(G55:$G$107) -> 2496.43 | I55: 500 | J55: =J54-I55 -> 22000 | Q55: Hacienda | T55: 0 | U55: 4000 | Y55: Hacienda | AB55: 0 | AG55: Hacienda | AJ55: 0 | AK55: 2000 | AO55: Hacienda | AR55: 0 | AS55: 2000
C56: 5 | E56: 713.72 | G56: 89.07 | H56: =SUM(G56:$G$107) -> 2405.75 | I56: 500 | J56: =J55-I56 -> 21500 | Q56: Cuotas | T56: 0 | U56: 5950 | V56: 0 | Y56: Cuotas | AB56: 9300 | AD56: 3600 | AG56: Cuotas | AJ56: 0 | AL56: 0 | AO56: Cuotas | AR56: 9300 | AT56: 0
C57: 6 | E57: 715.34 | F57: 37910.46 | G57: 87.45 | H57: =SUM(G57:$G$107) -> 2316.68 | I57: 500 | J57: =J56-I57 -> 21000 | Q57: Ahorro | T57: 0 | U57: =M87 -> 5100 | Y57: Ahorro | AB57: 0 | AC57: =M87 -> 5100 | AG57: Ahorro | AJ57: 0 | AK57: 5100 | AO57: Ahorro | AR57: 0 | AS57: 5100
C58: 7 | E58: 716.95 | F58: =F57-D58-E58 -> 37193.51 | G58: 85.84 | H58: =SUM(G58:$G$107) -> 2229.23 | I58: 500 | J58: =J57-I58 -> 20500 | Q58: TOTAL | T58: =SUM(T54:T57) -> 0 | U58: =SUM(U54:U57) -> 15050 | V58: =SUM(V56:V57) -> 0 | Y58: TOTAL | AB58: =SUM(AB54:AB57) -> 9300 | AC58: =AC30+AC36+AC43+AC50+AC57 -> 11900 | AD58: =SUM(AD56:AD57) -> 3600 | AG58: TOTAL | AJ58: =SUM(AJ54:AJ57) -> 0 | AK58: =SUM(AK54:AK57) -> 7100 | AL58: =SUM(AL56:AL57) -> 0 | AO58: TOTAL | AR58: =SUM(AR54:AR57) -> 9300 | AS58: =SUM(AS54:AS57) -> 7100 | AT58: =SUM(AT56:AT57) -> 0
C59: 8 | E59: 718.58 | F59: =F58-D59-E59 -> 36474.93 | G59: 84.21 | H59: =SUM(G59:$G$107) -> 2143.39 | I59: 500 | J59: =J58-I59 -> 20000
C60: 9 | E60: 720.2 | F60: =F59-D60-E60 -> 35754.73 | G60: 82.59 | H60: =SUM(G60:$G$107) -> 2059.18 | I60: 500 | J60: =J59-I60 -> 19500 | K60: 250 | L60: 175 | P60: 2029 | Q60: Pendiente Hipoteca | S60: =S53-T54-T55-T56-T57 -> -700 | X60: 2029 | Y60: Pendiente Hipoteca | AA60: =AA53-AB54-AB55-AB56-AB57 -> -2000 | AF60: 2029 | AG60: Pendiente Hipoteca | AI60: =AI53-AJ54-AJ55-AJ56-AJ57 -> 300 | AN60: 2029 | AO60: Pendiente Hipoteca | AQ60: =AQ53-AR54-AR55-AR56-AR57 -> 16000 | AU60: 16000
C61: 10 | E61: 721.84 | F61: =F60-D61-E61 -> 35032.89 | G61: 80.95 | H61: =SUM(G61:$G$107) -> 1976.59 | I61: 500 | J61: =J60-I61 -> 19000 | K61: 250 | L61: 175 | Q61: Disponible | T61: =R30-T33-T40-T47-T54 -> 0 | Y61: Disponible | AB61: =Z30-AB33-AB40-AB47-AB54 -> 0 | AG61: Disponible | AJ61: =AH30-AJ33-AJ40-AJ47-AJ54 -> 0 | AO61: Disponible | AR61: 0
C62: 11 | E62: 723.47 | F62: =F61-D62-E62 -> 34309.42 | G62: 79.32 | H62: =SUM(G62:$G$107) -> 1895.64 | I62: 500 | J62: =J61-I62 -> 18500 | K62: 250 | L62: 175 | Q62: Hacienda | T62: 0 | Y62: Hacienda | AB62: 0 | AG62: Hacienda | AJ62: 0 | AO62: Hacienda | AR62: 0
C63: 12 | E63: 725.11 | F63: =F62-D63-E63 -> 33584.31 | G63: 77.68 | H63: =SUM(G63:$G$107) -> 1816.32 | I63: 500 | J63: =J62-I63 -> 18000 | K63: 250 | L63: 175 | M63: =SUM(K52:L63) -> 1700 | N63: =SUM(M28:M63) -> 1700 | Q63: Cuotas | T63: 0 | V63: 1200 | Y63: Cuotas | AB63: 2000 | AD63: 1200 | AG63: Cuotas | AJ63: 0 | AL63: 1200 | AO63: Cuotas | AR63: 9600 | AT63: 1200
A64: 4 | B64: 2027 | C64: 1 | E64: 726.75 | F64: =F63-D64-E64 -> 32857.56 | G64: 76.04 | H64: =SUM(G64:$G$107) -> 1738.64 | I64: 500 | J64: =J63-I64 -> 17500 | K64: 250 | L64: 175 | Q64: Ahorro | T64: 0 | Y64: Ahorro | AB64: 0 | AC64: =M98 -> 4675 | AG64: Ahorro | AJ64: 0 | AK64: 5100 | AO64: Ahorro | AR64: 0 | AS64: 5100
C65: 2 | E65: 728.39 | F65: =F64-D65-E65 -> 32129.17 | G65: 74.4 | H65: =SUM(G65:$G$107) -> 1662.6 | I65: 500 | J65: =J64-I65 -> 17000 | K65: 250 | L65: 175 | Q65: TOTAL | T65: =SUM(T61:T64) -> 0 | V65: =SUM(V63:V64) -> 1200 | Y65: TOTAL | AB65: =SUM(AB61:AB64) -> 2000 | AC65: =AC30+AC36+AC43+AC50+AC57+AC64 -> 16575 | AD65: =SUM(AD63:AD64) -> 1200 | AG65: TOTAL | AJ65: =SUM(AJ61:AJ64) -> 0 | AK65: =AK30+AK37+AK44+AK51+AK58+AK64 -> 16125 | AL65: =SUM(AL63:AL64) -> 1200 | AO65: TOTAL | AR65: =SUM(AR61:AR64) -> 9600 | AS65: =SUM(AS61:AS64) -> 5100 | AT65: =SUM(AT63:AT64) -> 1200
C66: 3 | E66: 730.04 | F66: =F65-D66-E66 -> 31399.13 | G66: 72.75 | H66: =SUM(G66:$G$107) -> 1588.2 | I66: 500 | J66: =J65-I66 -> 16500 | K66: 250 | L66: 175
C67: 4 | E67: 731.7 | F67: =F66-D67-E67 -> 30667.43 | G67: 71.09 | H67: =SUM(G67:$G$107) -> 1515.45 | I67: 500 | J67: =J66-I67 -> 16000 | K67: 250 | L67: 175 | AN67: 2030 | AO67: Pendiente Hipoteca | AQ67: =AQ60-AR61-AR62-AR63-AR64 -> 6400 | AU67: 6400
C68: 5 | E68: 733.35 | F68: =F67-D68-E68 -> 29934.08 | G68: 69.44 | H68: =SUM(G68:$G$107) -> 1444.36 | I68: 500 | J68: =J67-I68 -> 15500 | K68: 250 | L68: 175 | AO68: Disponible | AR68: 0
C69: 6 | E69: 735.01 | F69: =F68-D69-E69 -> 29199.07 | G69: 67.78 | H69: =SUM(G69:$G$107) -> 1374.92 | I69: 500 | J69: =J68-I69 -> 15000 | K69: 250 | L69: 175 | AO69: Hacienda | AR69: 0
C70: 7 | E70: 736.68 | F70: =F69-D70-E70 -> 28462.39 | G70: 66.11 | H70: =SUM(G70:$G$107) -> 1307.14 | I70: 500 | J70: =J69-I70 -> 14500 | K70: 250 | L70: 175 | AO70: Cuotas | AR70: 6400 | AT70: 1200
C71: 8 | E71: 738.35 | F71: =F70-D71-E71 -> 27724.04 | G71: 64.44 | H71: =SUM(G71:$G$107) -> 1241.03 | I71: 500 | J71: =J70-I71 -> 14000 | K71: 250 | L71: 175 | AO71: Ahorro | AR71: 0 | AS71: 5100
C72: 9 | E72: 740.02 | F72: =F71-D72-E72 -> 26984.02 | G72: 62.77 | H72: =SUM(G72:$G$107) -> 1176.59 | I72: 500 | J72: =J71-I72 -> 13500 | K72: 250 | L72: 175 | AO72: TOTAL | AR72: =SUM(AR68:AR71) -> 6400 | AS72: =AS37+AS44+AS51+AS58+AS65+AS71 -> 21225 | AT72: =SUM(AT70:AT71) -> 1200
C73: 10 | E73: 741.69 | F73: =F72-D73-E73 -> 26242.33 | G73: 61.1 | H73: =SUM(G73:$G$107) -> 1113.82 | I73: 500 | J73: =J72-I73 -> 13000 | K73: 250 | L73: 175 | P73: A partir de Abril de 2027 tendriamos 850€ (de la hipoteca + 425€ del ahorro disponibles) | X73: En abril 2029 habriamos pagado la hipoteca y habriamos estado pagando 5 años de coche. Nos querdarian 1.
C74: 11 | E74: 743.37 | F74: =F73-D74-E74 -> 25498.96 | G74: 59.42 | H74: =SUM(G74:$G$107) -> 1052.72 | I74: 500 | J74: =J73-I74 -> 12500 | K74: 250 | L74: 175 | P74: 1275€ al mes | X74: Cuota de 617€ (200€ mas que los 425€ disponibles)
C75: 12 | E75: 745.06 | F75: =F74-D75-E75 -> 24753.9 | G75: 57.73 | H75: =SUM(G75:$G$107) -> 993.3 | I75: 500 | J75: =J74-I75 -> 12000 | K75: 250 | L75: 175 | M75: =SUM(K64:L75) -> 5100 | N75: =SUM(M28:M75) -> 6800 | O75: ESCENARIO 1 | P75: En un año 15300€ (Abril 2028)
A76: 5 | B76: 2028 | C76: 1 | E76: 746.74 | F76: =F75-D76-E76 -> 24007.16 | G76: 56.05 | H76: =SUM(G76:$G$107) -> 935.57 | I76: 500 | J76: =J75-I76 -> 11500 | K76: 250 | L76: 175 | P76: En dos años 30600€ (Abril 2029)
C77: 2 | E77: 748.43 | F77: =F76-D77-E77 -> 23258.73 | G77: 54.36 | H77: =SUM(G77:$G$107) -> 879.52 | I77: 500 | J77: =J76-I77 -> 11000 | K77: 250 | L77: 175 | P77: Pagando al mes 625€ de financiación a los dos años tendriamos 650x24=15.600€
C78: 3 | E78: 750.13 | F78: =F77-D78-E78 -> 22508.6 | G78: 52.66 | H78: =SUM(G78:$G$107) -> 825.16 | I78: 500 | J78: =J77-I78 -> 10500 | K78: 250 | L78: 175 | X78: 2030 casa,coche y local pagado
C79: 4 | E79: 751.83 | F79: =F78-D79-E79 -> 21756.77 | G79: 50.96 | H79: =SUM(G79:$G$107) -> 772.5 | I79: 500 | J79: =J78-I79 -> 10000 | K79: 250 | L79: 175
C80: 5 | E80: 753.53 | F80: =F79-D80-E80 -> 21003.24 | G80: 49.26 | H80: =SUM(G80:$G$107) -> 721.54 | I80: 500 | J80: =J79-I80 -> 9500 | K80: 250 | L80: 175 | P80: En 2027 Casa pagada
C81: 6 | E81: 755.24 | F81: =F80-D81-E81 -> 20248 | G81: 47.55 | H81: =SUM(G81:$G$107) -> 672.28 | I81: 500 | J81: =J80-I81 -> 9000 | K81: 250 | L81: 175 | P81: En 2029-2030 Coche pagado
C82: 7 | E82: 756.95 | F82: =F81-D82-E82 -> 19491.05 | G82: 45.84 | H82: =SUM(G82:$G$107) -> 624.73 | I82: 500 | J82: =J81-I82 -> 8500 | K82: 250 | L82: 175 | P82: En 2030 Local pagado
C83: 8 | E83: 758.66 | F83: =F82-D83-E83 -> 18732.39 | G83: 44.13 | H83: =SUM(G83:$G$107) -> 578.89 | I83: 500 | J83: =J82-I83 -> 8000 | K83: 250 | L83: 175
C84: 9 | E84: 760.38 | F84: =F83-D84-E84 -> 17972.01 | G84: 42.41 | H84: =SUM(G84:$G$107) -> 534.76 | I84: 500 | J84: =J83-I84 -> 7500 | K84: 250 | L84: 175
C85: 10 | E85: 762.1 | F85: =F84-D85-E85 -> 17209.91 | G85: 40.69 | H85: =SUM(G85:$G$107) -> 492.35 | I85: 500 | J85: =J84-I85 -> 7000 | K85: 250 | L85: 175
C86: 11 | E86: 763.82 | F86: =F85-D86-E86 -> 16446.09 | G86: 38.97 | H86: =SUM(G86:$G$107) -> 451.66 | I86: 500 | J86: =J85-I86 -> 6500 | K86: 250 | L86: 175
C87: 12 | E87: 765.55 | F87: =F86-D87-E87 -> 15680.54 | G87: 37.24 | H87: =SUM(G87:$G$107) -> 412.69 | I87: 500 | J87: =J86-I87 -> 6000 | K87: 250 | L87: 175 | M87: =SUM(K76:L87) -> 5100
A88: 6 | B88: 2029 | C88: 1 | E88: 767.29 | F88: =F87-D88-E88 -> 14913.25 | G88: 35.5 | H88: =SUM(G88:$G$107) -> 375.45 | I88: 500 | J88: =J87-I88 -> 5500 | K88: 250 | L88: 175
C89: 2 | E89: 769.02 | F89: =F88-D89-E89 -> 14144.23 | G89: 33.77 | H89: =SUM(G89:$G$107) -> 339.95 | I89: 500 | J89: =J88-I89 -> 5000 | K89: 250 | L89: 175
C90: 3 | E90: 770.77 | F90: =F89-D90-E90 -> 13373.46 | G90: 32.02 | H90: =SUM(G90:$G$107) -> 306.18 | I90: 500 | J90: =J89-I90 -> 4500 | K90: 250 | L90: 175
C91: 4 | E91: 772.51 | F91: =F90-D91-E91 -> 12600.95 | G91: 30.28 | H91: =SUM(G91:$G$107) -> 274.16 | I91: 500 | J91: =J90-I91 -> 4000 | K91: 250 | L91: 175
C92: 5 | E92: 774.26 | F92: =F91-D92-E92 -> 11826.69 | G92: 28.53 | H92: =SUM(G92:$G$107) -> 243.88 | I92: 500 | J92: =J91-I92 -> 3500 | K92: 250 | L92: 175
C93: 6 | E93: 776.01 | F93: =F92-D93-E93 -> 11050.68 | G93: 26.78 | H93: =SUM(G93:$G$107) -> 215.35 | I93: 500 | J93: =J92-I93 -> 3000 | K93: 250 | L93: 175
C94: 7 | E94: 777.77 | F94: =F93-D94-E94 -> 10272.91 | G94: 25.02 | H94: =SUM(G94:$G$107) -> 188.57 | I94: 500 | J94: =J93-I94 -> 2500 | K94: 250 | L94: 175
C95: 8 | E95: 779.53 | F95: =F94-D95-E95 -> 9493.38 | G95: 23.26 | H95: =SUM(G95:$G$107) -> 163.55 | I95: 500 | J95: =J94-I95 -> 2000 | K95: 250 | L95: 175
C96: 9 | E96: 781.3 | F96: =F95-D96-E96 -> 8712.08 | G96: 21.49 | H96: =SUM(G96:$G$107) -> 140.29 | I96: 500 | J96: =J95-I96 -> 1500 | K96: 250 | L96: 175 | V96: Al contado | W96: 33000
C97: 10 | E97: 783.06 | F97: =F96-D97-E97 -> 7929.02 | G97: 19.73 | H97: =SUM(G97:$G$107) -> 118.8 | I97: 500 | J97: =J96-I97 -> 1000 | K97: 250 | L97: 175 | V97: Financiado | W97: 30000
C98: 11 | E98: 784.84 | F98: =F97-D98-E98 -> 7144.18 | G98: 17.95 | H98: =SUM(G98:$G$107) -> 99.07 | I98: 500 | J98: =J97-I98 -> 500 | K98: 250 | L98: 175 | M98: =SUM(K88:L98) -> 4675 | N98: =SUM(M39:M98) -> 16575 | O98: ESCENARIO 2 | W98: Meses | X98: 72 | Y98: 84 | Z98: 96
C99: 12 | E99: 786.61 | F99: =F98-D99-E99 -> 6357.57 | G99: 16.18 | H99: =SUM(G99:$G$107) -> 81.12 | W99: Años | X99: 6 | Y99: 7 | Z99: 8
A100: 7 | B100: 2030 | C100: 1 | E100: 788.4 | F100: =F99-D100-E100 -> 5569.17 | G100: 14.39 | H100: =SUM(G100:$G$107) -> 64.94 | W100: Cuota | X100: 617 | Y100: 559 | Z100: 517
...
